Workbook

Sheet Raw_data
A1: External | B1: Mat | C1: Url | D1: Full name | E1: Email | F1: Entry date | G1: Work experience since | H1: Total engagements | I1: Engagements with invalid dates | J1: Ongoing engagements | K1: Oldest ongoing engagement start date | L1: Last finished engagement start date | M1: Last finished engagement end date | N1: Is profile photo missing | O1: Months since entry baseline | P1: Absolute months since entry | Q1: Weighted months since entry | R1: Absolute missing months since entry | S1: Weighted missing months since entry | T1: Absolute coverage ratio since entry | U1: Weighted coverage ratio since entry | V1: Months before entry baseline | W1: Absolute months before entry | X1: Weighted months before entry | Y1: Absolute missing months before entry | Z1: Weighted missing months before entry | AA1: Absolute coverage ratio before entry | AB1: Weighted coverage ratio before entry | AC1: Is entry date missing | AD1: Is work experience since missing | AE1: Is work experience since after entry date | AF1: Is available | AG1: Available from | AH1: Available to | AI1: Is willing to travel | AJ1: Available days per week | AK1: Availability comment | AL1: Department | AM1: Team | AN1: Unit | AO1: Legal entity | AP1: Location | AQ1: Lead
A2: 2221 | B2: 594F6B | C2: https://app.matchical.com/Consulting/ConsultantDetail?ConsultantId=81c0d4c6-ad00-4890-a981-23b344efe2f7 | D2: Abdulsalam Ginebas | E2: abdulsalam.ginebas@bridging-it.de | F2: 43282 | G2: 40330 | H2: 9 | I2: 0 | J2: 0 | L2: 45748 | M2: 46021 | N2: FALSE | O2: 92 | P2: 171 | Q2: 91 | R2: =ROUND(O2-P2,2) | S2: =ROUND(O2-Q2,2) | T2: =IFERROR(P2/O2,"") | U2: =IFERROR(Q2/O2,"") | V2: 97 | W2: 29 | X2: 29 | Y2: =ROUND(V2-W2,2) | Z2: =ROUND(V2-X2,2) | AA2: =IFERROR(W2/V2,"") | AB2: =IFERROR(X2/V2,"") | AC2: FALSE | AD2: FALSE | AE2: FALSE | AF2: No | AI2: FALSE | AJ2: 0 | AK2: - Software Architect Focus on international projects in the context of AWS, Analytics, Security, Mobility | AL2: ES Enterprise Solutions (Gina H.) | AM2: DA Data & AI Solutions (Ralf Fi.) | AN2: PA Platform & Application Solutions (Thomas K.) | AO2: bridgingIT GmbH | AP2: Stuttgart | AQ2: Ralf Fischer
A3: 1208 | B3: C085E2 | C3: https://app.matchical.com/Consulting/ConsultantDetail?ConsultantId=0d3173bb-0ead-4fb6-8eab-b9083e90c3e1 | D3: Adam Birkstedt | E3: adam.birkstedt@bridging-it.de | F3: 41183 | G3: 41187 | H3: 11 | I3: 0 | J3: 2 | K3: 41760 | L3: 41334 | M3: 43829 | N3: FALSE | O3: 161 | P3: 583.97 | Q3: 160.79 | R3: =ROUND(O3-P3,2) | S3: =ROUND(O3-Q3,2) | T3: =IFERROR(P3/O3,"") | U3: =IFERROR(Q3/O3,"") | V3: 0 | W3: 0 | X3: 0 | Y3: =ROUND(V3-W3,2) | Z3: =ROUND(V3-X3,2) | AA3: =IFERROR(W3/V3,"") | AB3: =IFERROR(X3/V3,"") | AC3: FALSE | AD3: FALSE | AE3: TRUE | AF3: No | AI3: FALSE | AJ3: 0 | AL3: A&SE Analytics & Software Engineering (Philip R.) | AM3: FH Fullstack Heroes (Lars P.) | AN3: FUN Fullstack Ninjas (Stefan Z.) | AO3: bridgingIT GmbH | AP3: Mannheim | AQ3: Lars Preschke
A4: 10058 | B4: 201440 | C4: https://app.matchical.com/Consulting/ConsultantDetail?ConsultantId=bdfa7b90-c6cb-4737-938e-acb11e9d5c1f | D4: Adrian Josef Krolczyk | E4: adrian.krolczyk@fastahead.com | F4: 44958 | G4: 39052 | H4: 9 | I4: 0 | J4: 0 | L4: 45761 | M4: 46022 | N4: FALSE | O4: 37 | P4: 59 | Q4: 35 | R4: =ROUND(O4-P4,2) | S4: =ROUND(O4-Q4,2) | T4: =IFERROR(P4/O4,"") | U4: =IFERROR(Q4/O4,"") | V4: 194 | W4: 97 | X4: 97 | Y4: =ROUND(V4-W4,2) | Z4: =ROUND(V4-X4,2) | AA4: =IFERROR(W4/V4,"") | AB4: =IFERROR(X4/V4,"") | AC4: FALSE | AD4: FALSE | AE4: FALSE | AF4: No | AI4: TRUE | AJ4: 0 | AK4: The project end date is fixed with the handover of activities. In the meantime, another project can already start (ramp-up). | AL4: ORG fastahead GmbH & Co. KG | AM4: Business-driven Architectures (Dr. C. Gitte) | AN4: fah Tim Thierfelder | AO4: fastahead GmbH & Co. KG | AP4: Berlin | AQ4: Christian Gitte
A5: 3249 | B5: D167A3 | C5: https://app.matchical.com/Consulting/ConsultantDetail?ConsultantId=a0d832f3-d590-4d40-ade1-db1aba8fbea2 | D5: Adrian Knorr | E5: adrian.knorr@bridging-it.de | F5: 44669 | G5: 41518 | H5: 8 | I5: 0 | J5: 0 | L5: 45658 | M5: 46022 | N5: FALSE | O5: 46 | P5: 53 | Q5: 42 | R5: =ROUND(O5-P5,2) | S5: =ROUND(O5-Q5,2) | T5: =IFERROR(P5/O5,"") | U5: =IFERROR(Q5/O5,"") | V5: 104 | W5: 118 | X5: 90 | Y5: =ROUND(V5-W5,2) | Z5: =ROUND(V5-X5,2) | AA5: =IFERROR(W5/V5,"") | AB5: =IFERROR(X5/V5,"") | AC5: FALSE | AD5: FALSE | AE5: FALSE | AF5: No | AI5: TRUE | AJ5: 0 | AK5: Adrian is an experienced business analyst and product manager with experience in UI/UX and AI. Adrian is actively seeking a project in the AI field and also brings the necessary knowledge for it. | AL5: ORG bIT | AM5: BAPO - BA and Product Ownership (Edgar K.) | AN5: ABC Analysing Business & Collaboration (Edgar K.) | AO5: bridgingIT GmbH | AP5: Frankfurt | AQ5: Edgar Kauz
A6: 8663 | B6: 87292E | C6: https://app.matchical.com/Consulting/ConsultantDetail?ConsultantId=8afb61cd-046f-4995-b171-7cfdf8099644 | D6: Adrian Roser | E6: adrian.roser@crafting-it.de | F6: 44197 | G6: 43344 | H6: 23 | I6: 0 | J6: 0 | L6: 45658 | M6: 45838 | N6: FALSE | O6: 62 | P6: 257.97 | Q6: 54.99 | R6: =ROUND(O6-P6,2) | S6: =ROUND(O6-Q6,2) | T6: =IFERROR(P6/O6,"") | U6: =IFERROR(Q6/O6,"") | V6: 28 | W6: 0.03 | X6: 0.01 | Y6: =ROUND(V6-W6,2) | Z6: =ROUND(V6-X6,2) | AA6: =IFERROR(W6/V6,"") | AB6: =IFERROR(X6/V6,"") | AC6: FALSE | AD6: FALSE | AE6: FALSE | AF6: No | AI6: TRUE | AJ6: 0 | AL6: ORG cIT | AM6: cIT AMS / GIS Services (Michael B.) | AN6: cIT Service Delivery Magdeburg (Steffen A.) | AO6: craftingIT GmbH | AP6: Karlsruhe | AQ6: Michael Buchter
A7: 2064 | B7: F8F6B0 | C7: https://app.matchical.com/Consulting/ConsultantDetail?ConsultantId=c20648d7-9db2-4d22-bcb1-28e927b563da | D7: Afshan Tabbasum | E7: afshan.tabbasum@bridging-it.de | F7: 41275 | G7: 39934 | H7: 51 | I7: 0 | J7: 3 | K7: 44347 | L7: 45839 | M7: 46022 | N7: FALSE | O7: 158 | P7: 557 | Q7: 157.77 | R7: =ROUND(O7-P7,2) | S7: =ROUND(O7-Q7,2) | T7: =IFERROR(P7/O7,"") | U7: =IFERROR(Q7/O7,"") | V7: 44 | W7: 57.01 | X7: 38.01 | Y7: =ROUND(V7-W7,2) | Z7: =ROUND(V7-X7,2) | AA7: =IFERROR(W7/V7,"") | AB7: =IFERROR(X7/V7,"") | AC7: FALSE | AD7: FALSE | AE7: FALSE | AF7: No | AI7: FALSE | AJ7: 0 | AK7: * Microsoft 365 Power Platform, Power Apps and Power Automate * Microsoft Adaptive Cards Development * K2 Workflow Development | AL7: ES Enterprise Solutions (Gina H.) | AM7: PE Platform Engineering (Thomas K.) | AN7: PA Platform & Application Solutions (Thomas K.) | AO7: bridgingIT GmbH | AP7: Stuttgart | AQ7: Thomas Kiri
A8: 10052 | B8: 48C410 | C8: https://app.matchical.com/Consulting/ConsultantDetail?ConsultantId=1b3c0d4f-857b-47c6-907f-57d01862cd86 | D8: Ahmad Kamhieh | E8: ahmad.kamhieh@bridging-it.de | F8: 44958 | G8: 44409 | H8: 14 | I8: 0 | J8: 0 | L8: 45414 | M8: 45504 | N8: FALSE | O8: 37 | P8: 54.64 | Q8: 19.32 | R8: =ROUND(O8-P8,2) | S8: =ROUND(O8-Q8,2) | T8: =IFERROR(P8/O8,"") | U8: =IFERROR(Q8/O8,"") | V8: 18 | W8: 15.36 | X8: 12.68 | Y8: =ROUND(V8-W8,2) | Z8: =ROUND(V8-X8,2) | AA8: =IFERROR(W8/V8,"") | AB8: =IFERROR(X8/V8,"") | AC8: FALSE | AD8: FALSE | AE8: FALSE | AF8: Yes | AG8: 46174 | AI8: FALSE | AJ8: 1.82 | AK8: Fullstack (.NET and Angular) Developer Leads at: TKE, SPIE JSS, KVNO | AL8: ES Enterprise Solutions (Gina H.) | AM8: IEM .Net II (Aleksandar B.) | AN8: IEJ Individualentwicklung JAVA (Dominik S.) | AO8: bridgingIT GmbH | AP8: Stuttgart | AQ8: Aleksandar Blagojevic
A9: 10430 | B9: 3A0086 | C9: https://app.matchical.com/Consulting/ConsultantDetail?ConsultantId=ec49d130-9afa-4329-883f-4e918e6e1bfe | D9: Ahmad Osman | E9: ahmad.osman@bridging-it.de | F9: 46054 | G9: 41275 | H9: 8 | I9: 0 | J9: 0 | L9: 44926 | M9: 46052 | N9: FALSE | O9: 1 | P9: 0 | Q9: 0 | R9: =ROUND(O9-P9,2) | S9: =ROUND(O9-Q9,2) | T9: =IFERROR(P9/O9,"") | U9: =IFERROR(Q9/O9,"") | V9: 157 | W9: 183.92 | X9: 154.94 | Y9: =ROUND(V9-W9,2) | Z9: =ROUND(V9-X9,2) | AA9: =IFERROR(W9/V9,"") | AB9: =IFERROR(X9/V9,"") | AC9: FALSE | AD9: FALSE | AE9: FALSE | AF9: Yes | AG9: 46062 | AI9: TRUE | AJ9: 5 | AL9: IT - Information Technology (HH) | AM9: CRM I - Platform Solutions & CRM (Fortunato D. D.) | AN9: BAA HH (Torben H.) | AO9: bridgingIT GmbH | AP9: Hamburg | AQ9: Fortunato Di Donato
A10: 10044 | B10: 2CE8C5 | C10: https://app.matchical.com/Consulting/ConsultantDetail?ConsultantId=609d0e65-d3d2-486c-a4de-ad31eb1e1a1d | D10: Akash Saraswat | E10: akash.saraswat@bridging-it.de | F10: 44986 | G10: 43831 | H10: 10 | I10: 0 | J10: 2 | K10: 45292 | L10: 45658 | M10: 46022 | N10: FALSE | O10: 36 | P10: 105 | Q10: 35 | R10: =ROUND(O10-P10,2) | S10: =ROUND(O10-Q10,2) | T10: =IFERROR(P10/O10,"") | U10: =IFERROR(Q10/O10,"") | V10: 38 | W10: 72.97 | X10: 37.95 | Y10: =ROUND(V10-W10,2) | Z10: =ROUND(V10-X10,2) | AA10: =IFERROR(W10/V10,"") | AB10: =IFERROR(X10/V10,"") | AC10: FALSE | AD10: FALSE | AE10: FALSE | AF10: No | AI10: TRUE | AJ10: 0 | AK10: Experience with process digitization and low-code, as well as BI (primarily SAP Analytics Cloud, and Power BI), dashboard design, and process design. | AL10: DO Digital Organizations (Michael H.) | AM10: PD Process Digitalization II (Ralf Fr.) | AN10: DP Digital Processes (Hermann L.) | AO10: bridgingIT GmbH | AP10: Stuttgart | AQ10: Ralf Frotscher
A11: 2136 | B11: 75F54F | C11: https://app.matchical.com/Consulting/ConsultantDetail?ConsultantId=25ffe9cd-2779-4db8-b1fc-6e8cb3ac0a50 | D11: Aleksandar Blagojevic | E11: aleksandar.blagojevic@bridging-it.de | F11: 42401 | G11: 38412 | H11: 26 | I11: 0 | J11: 0 | L11: 44787 | M11: 45077 | N11: FALSE | O11: 121 | P11: 167 | Q11: 88 | R11: =ROUND(O11-P11,2) | S11: =ROUND(O11-Q11,2) | T11: =IFERROR(P11/O11,"") | U11: =IFERROR(Q11/O11,"") | V11: 131 | W11: 117 | X11: 76 | Y11: =ROUND(V11-W11,2) | Z11: =ROUND(V11-X11,2) | AA11: =IFERROR(W11/V11,"") | AB11: =IFERROR(X11/V11,"") | AC11: FALSE | AD11: FALSE | AE11: FALSE | AF11: No | AI11: FALSE | AJ11: 5 | AL11: ES Enterprise Solutions (Gina H.) | AM11: IEM .Net II (Aleksandar B.) | AN11: IEJ Individualentwicklung JAVA (Dominik S.) | AO11: bridgingIT GmbH | AP11: Stuttgart | AQ11: Dominik Schadow
A12: 10299 | B12: 8734EF | C12: https://app.matchical.com/Consulting/ConsultantDetail?ConsultantId=ac32b51f-8c73-497e-857a-f2829db9398f | D12: Aleksandar Bozic | E12: aleksandar.bozic@bridging-it.de | F12: 45536 | G12: 44562 | H12: 7 | I12: 0 | J12: 0 | L12: 45607 | M12: 46022 | N12: FALSE | O12: 18 | P12: 14 | Q12: 14 | R12: =ROUND(O12-P12,2) | S12: =ROUND(O12-Q12,2) | T12: =IFERROR(P12/O12,"") | U12: =IFERROR(Q12/O12,"") | V12: 32 | W12: 95 | X12: 31 | Y12: =ROUND(V12-W12,2) | Z12: =ROUND(V12-X12,2) | AA12: =IFERROR(W12/V12,"") | AB12: =IFERROR(X12/V12,"") | AC12: FALSE | AD12: FALSE | AE12: FALSE | AF12: Yes | AG12: 46143 | AI12: TRUE | AJ12: 5 | AL12: IT - Information Technology (Sebastian L.) | AM12: P&P - Processes & Platforms (Bernd O.) | AN12: P&DE - Platforms & Digital Ecosystems (David S.) | AO12: bridgingIT GmbH | AP12: Mannheim | AQ12: Bernd Opitz
A13: 10273 | B13: A7182D | C13: https://app.matchical.com/Consulting/ConsultantDetail?ConsultantId=e17d68c8-49df-4439-a5f1-5da226881413 | D13: Alex Befort | E13: alex.befort@bridging-it.de | F13: 45352 | G13: 42552 | H13: 9 | I13: 0 | J13: 0 | L13: 45404 | M13: 46021 | N13: FALSE | O13: 24 | P13: 21.67 | Q13: 21.67 | R13: =ROUND(O13-P13,2) | S13: =ROUND(O13-Q13,2) | T13: =IFERROR(P13/O13,"") | U13: =IFERROR(Q13/O13,"") | V13: 92 | W13: 94.97 | X13: 83.97 | Y13: =ROUND(V13-W13,2) | Z13: =ROUND(V13-X13,2) | AA13: =IFERROR(W13/V13,"") | AB13: =IFERROR(X13/V13,"") | AC13: FALSE | AD13: FALSE | AE13: FALSE | AF13: No | AI13: TRUE | AJ13: 0 | AL13: ORG bIT | AM13: SE Software Engineering Frankfurt (Sebastian F.) | AN13: ES Enterprise Solutions (Dominik H.) | AO13: bridgingIT GmbH | AP13: Frankfurt | AQ13: Sebastian Fischer
A14: 2311 | B14: 043588 | C14: https://app.matchical.com/Consulting/ConsultantDetail?ConsultantId=01ccef19-031b-4be5-8f8e-7fbfaece0176 | D14: Alexander Bloch | E14: alexander.bloch@bridging-it.de | F14: 44682 | G14: 44682 | H14: 15 | I14: 0 | J14: 2 | K14: 44682 | L14: 45658 | M14: 46052 | N14: FALSE | O14: 46 | P14: 177 | Q14: 45.83 | R14: =ROUND(O14-P14,2) | S14: =ROUND(O14-Q14,2) | T14: =IFERROR(P14/O14,"") | U14: =IFERROR(Q14/O14,"") | V14: 0 | W14: 0 | X14: 0 | Y14: =ROUND(V14-W14,2) | Z14: =ROUND(V14-X14,2) | AA14: =IFERROR(W14/V14,"") | AB14: =IFERROR(X14/V14,"") | AC14: FALSE | AD14: FALSE | AE14: FALSE | AF14: No | AI14: TRUE | AJ14: 0 | AK14: Focus areas in IT security, cloud security, and cloud technologies. | AL14: IT Information Technology (Hauke G.) | AM14: ITS IT Security (Erhan N.) | AN14: GRC IT-GRC (Erhan N.) | AO14: bridgingIT GmbH | AP14: Stuttgart | AQ14: Erhan Nurdogan
A15: 10413 | B15: 45C492 | C15: https://app.matchical.com/Consulting/ConsultantDetail?ConsultantId=221f5fc7-f67a-43f7-85e5-7bf6f590c1d0 | D15: Alexander Celik | E15: alexander.celik@bridging-it.de | F15: 46023 | G15: 39661 | H15: 2 | I15: 0 | J15: 0 | L15: 45747 | M15: 46021 | N15: FALSE | O15: 2 | P15: 0 | Q15: 0 | R15: =ROUND(O15-P15,2) | S15: =ROUND(O15-Q15,2) | T15: =IFERROR(P15/O15,"") | U15: =IFERROR(Q15/O15,"") | V15: 209 | W15: 42 | X15: 42 | Y15: =ROUND(V15-W15,2) | Z15: =ROUND(V15-X15,2) | AA15: =IFERROR(W15/V15,"") | AB15: =IFERROR(X15/V15,"") | AC15: FALSE | AD15: FALSE | AE15: FALSE | AF15: Yes | AG15: 46113 | AI15: FALSE | AJ15: 5 | AL15: IT - Information Technology (HH) | AM15: TM - Transition Management (Christoph W.) | AN15: MWT HH (Udo P.) | AO15: bridgingIT GmbH | AP15: Hamburg | AQ15: Christoph Wudtke
A16: 3220 | B16: 040D65 | C16: https://app.matchical.com/Consulting/ConsultantDetail?ConsultantId=5353bccf-0e19-4f9f-b1db-1278b9ae1cbf | D16: Alexander Galesky | E16: alexander.galesky@bridging-it.de | F16: 44242 | G16: 33848 | H16: 3 | I16: 0 | J16: 1 | K16: 43466 | L16: 43709 | M16: 43922 | N16: FALSE | O16: 60 | P16: 59.74 | Q16: 57.28 | R16: =ROUND(O16-P16,2) | S16: =ROUND(O16-Q16,2) | T16: =IFERROR(P16/O16,"") | U16: =IFERROR(Q16/O16,"") | V16: 341 | W16: 35.26 | X16: 30.72 | Y16: =ROUND(V16-W16,2) | Z16: =ROUND(V16-X16,2) | AA16: =IFERROR(W16/V16,"") | AB16: =IFERROR(X16/V16,"") | AC16: FALSE | AD16: FALSE | AE16: FALSE | AF16: No | AG16: 44317 | AH16: 44561 | AI16: FALSE | AJ16: 5 | AK16: Alex's topics: GDPR, PL, DBs, Siebel CRM, Automic Automation ONE, OneTrust | AL16: ORG bIT | AM16: Life Science Solutions FFM1 (Holger B.) | AN16: CC Life Science Solutions (Sabine S.) | AO16: bridgingIT GmbH | AP16: Frankfurt | AQ16: Holger Bohlen
A17: 8241 | B17: 46AECD | C17: https://app.matchical.com/Consulting/ConsultantDetail?ConsultantId=4f3787e9-29ce-4cd4-9884-d9a6748620a3 | D17: Alexander Jende | E17: alexander.jende@crafting-it.de | F17: 42856 | G17: 36069 | H17: 2 | I17: 0 | J17: 0 | L17: 45292 | M17: 45657 | N17: FALSE | O17: 106 | P17: 22 | Q17: 22 | R17: =ROUND(O17-P17,2) | S17: =ROUND(O17-Q17,2) | T17: =IFERROR(P17/O17,"") | U17: =IFERROR(Q17/O17,"") | V17: 223 | W17: 0 | X17: 0 | Y17: =ROUND(V17-W17,2) | Z17: =ROUND(V17-X17,2) | AA17: =IFERROR(W17/V17,"") | AB17: =IFERROR(X17/V17,"") | AC17: FALSE | AD17: FALSE | AE17: FALSE | AF17: No | AI17: TRUE | AJ17: 0 | AL17: ORG cIT 2 | AM17: LS Lokation Magdeburg | AN17: LS Lokation Magdeburg (Alexander J.) | AO17: craftingIT GmbH | AP17: Magdeburg | AQ17: Christian Kobl
A18: 10390 | B18: 4267DA | C18: https://app.matchical.com/Consulting/ConsultantDetail?ConsultantId=7ce6750c-3db0-4359-b087-9566472115e4 | D18: Alexander Käther | E18: alexander.kaether@bridging-it.de | F18: 45901 | H18: 3 | I18: 0 | J18: 0 | L18: 45412 | M18: 45746 | N18: FALSE | O18: 6 | P18: 0 | Q18: 0 | R18: =ROUND(O18-P18,2) | S18: =ROUND(O18-Q18,2) | T18: =IFERROR(P18/O18,"") | U18: =IFERROR(Q18/O18,"") | V18: 1508 | W18: 58 | X18: 58 | Y18: =ROUND(V18-W18,2) | Z18: =ROUND(V18-X18,2) | AA18: =IFERROR(W18/V18,"") | AB18: =IFERROR(X18/V18,"") | AC18: FALSE | AD18: FALSE | AE18: FALSE | AF18: Yes | AG18: 46143 | AI18: TRUE | AJ18: 1.59 | AK18: Experienced IT project manager and Product Owner with a strong focus on hands-on IT implementation. In IT initiatives involving transformation projects with a strategic component, he is at home just as in end-to-end deployments of new software with innovative UI/UX. Alexander Käther operates confidently in both business and IT, effectively bridging the gap between the two. | AL18: IT Information Technology (Hauke G.) | AM18: AM IT-Architecture Management (Wilfried W.) | AN18: ITM IT-Management (Jörg M.) | AO18: bridgingIT GmbH | AP18: Stuttgart | AQ18: Wilfried Wessel
A19: 10148 | B19: BA4C90 | C19: https://app.matchical.com/Consulting/ConsultantDetail?ConsultantId=4fc60955-ce30-4a69-b133-251d5aba3c20 | D19: Alexander Mai | E19: alexander.mai@bridging-it.de | F19: 45061 | G19: 43525 | H19: 7 | I19: 0 | J19: 1 | K19: 45657 | L19: 45761 | M19: 45869 | N19: FALSE | O19: 33 | P19: 41.46 | Q19: 33.38 | R19: =ROUND(O19-P19,2) | S19: =ROUND(O19-Q19,2) | T19: =IFERROR(P19/O19,"") | U19: =IFERROR(Q19/O19,"") | V19: 50 | W19: 40.5 | X19: 40.5 | Y19: =ROUND(V19-W19,2) | Z19: =ROUND(V19-X19,2) | AA19: =IFERROR(W19/V19,"") | AB19: =IFERROR(X19/V19,"") | AC19: FALSE | AD19: FALSE | AE19: FALSE | AF19: Yes | AG19: 46082 | AI19: TRUE | AJ19: 0.05 | AK19: I have a project, but I would like to switch if a more technical project becomes available. Kubernetes is the main focus. | AL19: IT - Information Technology (Sebastian L.) | AM19: DOE DevOps Enablement (Florian W.) | AN19: C&DO - Cloud & DevOps (Sebastian L.) | AO19: bridgingIT GmbH | AP19: Mannheim | AQ19: Florian Wendel
A20: 7048 | B20: A7B3EC | C20: https://app.matchical.com/Consulting/ConsultantDetail?ConsultantId=360ab819-fb0d-4dcc-99b1-b8168d2b77ff | D20: Alexander Neben | E20: alexander.neben@bridging-it.de | F20: 44805 | G20: 41183 | H20: 6 | I20: 0 | J20: 1 | K20: 44886 | L20: 44817 | M20: 46021 | N20: FALSE | O20: 42 | P20: 79 | Q20: 41.79 | R20: =ROUND(O20-P20,2) | S20: =ROUND(O20-Q20,2) | T20: =IFERROR(P20/O20,"") | U20: =IFERROR(Q20/O20,"") | V20: 119 | W20: 108 | X20: 77 | Y20: =ROUND(V20-W20,2) | Z20: =ROUND(V20-X20,2) | AA20: =IFERROR(W20/V20,"") | AB20: =IFERROR(X20/V20,"") | AC20: FALSE | AD20: FALSE | AE20: FALSE | AF20: Yes | AG20: 46059 | AH20: 46072 | AI20: TRUE | AJ20: 5 | AL20: ORG bIT | AM20: SHH Standort Hamburg (Claudia P.) | AN20: SHH Standort Hamburg (Claudia P) | AO20: bridgingIT GmbH | AP20: Hamburg | AQ20: Claudia Peters
A21: 10434 | B21: 4165F5 | C21: https://app.matchical.com/Consulting/ConsultantDetail?ConsultantId=b1ed7480-989d-45c2-b1b6-73bac484600b | D21: Alexander Schulte | E21: alexander.schulte@bridging-it.de | F21: 46054 | G21: 40391 | H21: 8 | I21: 0 | J21: 0 | L21: 45107 | M21: 45656 | N21: FALSE | O21: 1 | P21: 0 | Q21: 0 | R21: =ROUND(O21-P21,2) | S21: =ROUND(O21-Q21,2) | T21: =IFERROR(P21/O21,"") | U21: =IFERROR(Q21/O21,"") | V21: 186 | W21: 93 | X21: 70 | Y21: =ROUND(V21-W21,2) | Z21: =ROUND(V21-X21,2) | AA21: =IFERROR(W21/V21,"") | AB21: =IFERROR(X21/V21,"") | AC21: FALSE | AD21: FALSE | AE21: FALSE | AF21: Yes | AG21: 46054 | AI21: TRUE | AJ21: 5 | AL21: IT - Information Technology (HH) | AM21: IPM - IT PM (Peter T.) | AN21: MWT HH (Udo P.) | AO21: bridgingIT GmbH | AP21: Hamburg | AQ21: Peter Triftshäuser
A22: 10065 | B22: 986EA5 | C22: https://app.matchical.com/Consulting/ConsultantDetail?ConsultantId=35086c7e-da1f-4f51-8fed-75d05a5930f3 | D22: Alexander Wittmann | E22: alexander.wittmann@bridging-it.de | F22: 44958 | G22: 42795 | H22: 11 | I22: 0 | J22: 3 | K22: 45626 | L22: 45550 | M22: 45746 | N22: FALSE | O22: 37 | P22: 77 | Q22: 35 | R22: =ROUND(O22-P22,2) | S22: =ROUND(O22-Q22,2) | T22: =IFERROR(P22/O22,"") | U22: =IFERROR(Q22/O22,"") | V22: 71 | W22: 87 | X22: 54 | Y22: =ROUND(V22-W22,2) | Z22: =ROUND(V22-X22,2) | AA22: =IFERROR(W22/V22,"") | AB22: =IFERROR(X22/V22,"") | AC22: FALSE | AD22: FALSE | AE22: FALSE | AF22: No | AI22: TRUE | AJ22: 0 | AK22: DevOps, cloud architecture, development experience | AL22: IT - Information Technology (Sebastian L.) | AM22: DOE DevOps Enablement (Florian W.) | AN22: C&DO - Cloud & DevOps (Sebastian L.) | AO22: bridgingIT GmbH | AP22: Mannheim | AQ22: Florian Wendel
A23: 10333 | B23: B90484 | C23: https://app.matchical.com/Consulting/ConsultantDetail?ConsultantId=65e11dc6-ed62-4cbe-8468-42c99a28c7cc | D23: Alexandra Schwarz | E23: alexandra.schwarz@bridging-it.de | F23: 45566 | G23: 43617 | H23: 9 | I23: 0 | J23: 1 | K23: 45596 | L23: 45151 | M23: 45401 | N23: FALSE | O23: 17 | P23: 16 | Q23: 16 | R23: =ROUND(O23-P23,2) | S23: =ROUND(O23-Q23,2) | T23: =IFERROR(P23/O23,"") | U23: =IFERROR(Q23/O23,"") | V23: 64 | W23: 57 | X23: 55.5 | Y23: =ROUND(V23-W23,2) | Z23: =ROUND(V23-X23,2) | AA23: =IFERROR(W23/V23,"") | AB23: =IFERROR(X23/V23,"") | AC23: FALSE | AD23: FALSE | AE23: FALSE | AF23: No | AI23: TRUE | AJ23: 0 | AL23: ORG bIT | AM23: BABC - BA and Business Complexity (Karola B.) | AN23: ABC Analysing Business & Collaboration (Edgar K.) | AO23: bridgingIT GmbH | AP23: Frankfurt | AQ23: Karola Bischof
A24: 1500 | B24: 5DBECD | C24: https://app.matchical.com/Consulting/ConsultantDetail?ConsultantId=50a1aae9-ac3c-44f3-a7b8-ed53e0be1801 | D24: Alexandra Welter | E24: alexandra.welter@bridging-it.de | F24: 44652 | G24: 42917 | H24: 7 | I24: 0 | J24: 0 | L24: 45839 | M24: 45930 | N24: FALSE | O24: 47 | P24: 53.92 | Q24: 42.23 | R24: =ROUND(O24-P24,2) | S24: =ROUND(O24-Q24,2) | T24: =IFERROR(P24/O24,"") | U24: =IFERROR(Q24/O24,"") | V24: 57 | W24: 67.06 | X24: 57 | Y24: =ROUND(V24-W24,2) | Z24: =ROUND(V24-X24,2) | AA24: =IFERROR(W24/V24,"") | AB24: =IFERROR(X24/V24,"") | AC24: FALSE | AD24: FALSE | AE24: FALSE | AF24: Yes | AG24: 46113 | AI24: TRUE | AJ24: 5 | AK24: Alex has extensive experience in agile and traditional project management, rollout and interim management, as well as in organizational and change management — particularly in the retail and life sciences industries. | AL24: T&A - Transformation & Agility (Arne K.) | AM24: P&OS - Processes & Organizational Str. (Raina B.) | AN24: TB - Transforming Business (Arne K.) | AO24: bridgingIT GmbH | AP24: Mannheim | AQ24: Raina Beck
A25: 10269 | B25: 00AD2B | C25: https://app.matchical.com/Consulting/ConsultantDetail?ConsultantId=5631ca75-1d76-4afa-81c7-905e09b62c79 | D25: Alexej Walther | E25: alexej.walther@bridging-it.de | F25: 45413 | G25: 42186 | H25: 18 | I25: 0 | J25: 2 | K25: 45412 | L25: 45445 | M25: 45534 | N25: FALSE | O25: 22 | P25: 40.97 | Q25: 20.98 | R25: =ROUND(O25-P25,2) | S25: =ROUND(O25-Q25,2) | T25: =IFERROR(P25/O25,"") | U25: =IFERROR(Q25/O25,"") | V25: 106 | W25: 259.03 | X25: 80.02 | Y25: =ROUND(V25-W25,2) | Z25: =ROUND(V25-X25,2) | AA25: =IFERROR(W25/V25,"") | AB25: =IFERROR(X25/V25,"") | AC25: FALSE | AD25: FALSE | AE25: FALSE | AF25: No | AI25: TRUE | AJ25: 0 | AL25: IT Information Technology (Hauke G.) | AM25: CT Cloud Technology II (Marc L.) | AN25: TC Technology & Cloud (Martin S.) | AO25: bridgingIT GmbH | AP25: Stuttgart | AQ25: Marc Leunig
A26: 10129 | B26: C58D1E | C26: https://app.matchical.com/Consulting/ConsultantDetail?ConsultantId=2aa0b085-d204-4627-8c3e-2e1a8973b6f0 | D26: Ali Karaarslan | E26: ali.karaarslan@bridging-it.de | F26: 45047 | G26: 43922 | H26: 5 | I26: 0 | J26: 0 | L26: 45396 | M26: 45656 | N26: FALSE | O26: 34 | P26: 31.97 | Q26: 22.98 | R26: =ROUND(O26-P26,2) | S26: =ROUND(O26-Q26,2) | T26: =IFERROR(P26/O26,"") | U26: =IFERROR(Q26/O26,"") | V26: 37 | W26: 30 | X26: 29.99 | Y26: =ROUND(V26-W26,2) | Z26: =ROUND(V26-X26,2) | AA26: =IFERROR(W26/V26,"") | AB26: =IFERROR(X26/V26,"") | AC26: FALSE | AD26: FALSE | AE26: FALSE | AF26: No | AI26: TRUE | AJ26: 0 | AL26: ORG bIT | AM26: SE Software Engineering Frankfurt (Steffen F.) | AN26: ES Enterprise Solutions (Dominik H.) | AO26: bridgingIT GmbH | AP26: Frankfurt | AQ26: Steffen Flick
A27: 9570 | B27: 5A6FD1 | C27: https://app.matchical.com/Consulting/ConsultantDetail?ConsultantId=3d36865e-1d68-4b82-8f9f-6190cdda7e3b | D27: Alwina Bonk | E27: alwina.bonk@leistungen.de | F27: 43374 | H27: 0 | I27: 0 | J27: 0 | N27: TRUE | O27: 89 | P27: 0 | Q27: 0 | R27: =ROUND(O27-P27,2) | S27: =ROUND(O27-Q27,2) | T27: =IFERROR(P27/O27,"") | U27: =IFERROR(Q27/O27,"") | V27: 1425 | W27: 0 | X27: 0 | Y27: =ROUND(V27-W27,2) | Z27: =ROUND(V27-X27,2) | AA27: =IFERROR(W27/V27,"") | AB27: =IFERROR(X27/V27,"") | AC27: FALSE | AD27: FALSE | AE27: FALSE | AF27: No | AI27: TRUE | AJ27: 0 | AL27: Geschäftsleitung und Support | AM27: Support Externe Partner | AN27: Frank Wallner | AO27: bridgingIT GmbH | AP27: Mannheim | AQ27: Nina Beckenbach
A28: 10340 | B28: 9617C1 | C28: https://app.matchical.com/Consulting/ConsultantDetail?ConsultantId=a8566670-a574-40b4-894e-61297b3d2201 | D28: Amadou Wolfgang Cisse | E28: amadou.cisse@bridging-it.de | F28: 45597 | H28: 10 | I28: 0 | J28: 1 | K28: 44804 | L28: 45719 | M28: 45807 | N28: FALSE | O28: 16 | P28: 22.46 | Q28: 15.09 | R28: =ROUND(O28-P28,2) | S28: =ROUND(O28-Q28,2) | T28: =IFERROR(P28/O28,"") | U28: =IFERROR(Q28/O28,"") | V28: 1498 | W28: 88.54 | X28: 46.91 | Y28: =ROUND(V28-W28,2) | Z28: =ROUND(V28-X28,2) | AA28: =IFERROR(W28/V28,"") | AB28: =IFERROR(X28/V28,"") | AC28: FALSE | AD28: FALSE | AE28: FALSE | AF28: Yes | AG28: 46143 | AI28: TRUE | AJ28: 5 | AL28: ORG bIT Bayern | AM28: DSA Data Solutions & AI (Philip R.) | AN28: BPD Business Processes & Data Engineering(Arne K.) | AO28: bridgingIT GmbH | AP28: München | AQ28: Philip Rausch
A29: 10369 | B29: 26A2E7 | C29: https://app.matchical.com/Consulting/ConsultantDetail?ConsultantId=3078fbb8-d547-457a-adba-64739b9b6e67 | D29: Amin Ataei | E29: amin.ataei@bridging-it.de | F29: 45839 | G29: 44197 | H29: 5 | I29: 0 | J29: 0 | L29: 44865 | M29: 45715 | N29: FALSE | O29: 8 | P29: 10.68 | Q29: 7.82 | R29: =ROUND(O29-P29,2) | S29: =ROUND(O29-Q29,2) | T29: =IFERROR(P29/O29,"") | U29: =IFERROR(Q29/O29,"") | V29: 54 | W29: 48 | X29: 45.49 | Y29: =ROUND(V29-W29,2) | Z29: =ROUND(V29-X29,2) | AA29: =IFERROR(W29/V29,"") | AB29: =IFERROR(X29/V29,"") | AC29: FALSE | AD29: FALSE | AE29: FALSE | AF29: Yes | AG29: 46113 | AI29: FALSE | AJ29: 5 | AK29: Cloud & DevOps Engineer with a focus on Microsoft Azure, automation, and Infrastructure as Code (IaC). Strong expertise in the development and implementation of cloud architectures, CI/CD pipelines, and IT security. Extensive experience with Terraform, PowerShell, and Docker. Passionate about cloud automation and DevOps culture. | AL29: IT - Information Technology (Sebastian L.) | AM29: DOE DevOps Enablement (Florian W.) | AN29: C&DO - Cloud & DevOps (Sebastian L.) | AO29: bridgingIT GmbH | AP29: Mannheim | AQ29: Florian Wendel
A30: 7018 | B30: F6B176 | C30: https://app.matchical.com/Consulting/ConsultantDetail?ConsultantId=e2dd0b01-309a-402d-abe0-2e1b80205a9f | D30: Anastasia Rettberg-Kluter | E30: anastasia.rettberg-kluter@fastahead.com | F30: 43160 | G30: 41214 | H30: 16 | I30: 0 | J30: 1 | K30: 44928 | L30: 44719 | M30: 44926 | N30: FALSE | O30: 96 | P30: 116 | Q30: 92 | R30: =ROUND(O30-P30,2) | S30: =ROUND(O30-Q30,2) | T30: =IFERROR(P30/O30,"") | U30: =IFERROR(Q30/O30,"") | V30: 64 | W30: 46 | X30: 31 | Y30: =ROUND(V30-W30,2) | Z30: =ROUND(V30-X30,2) | AA30: =IFERROR(W30/V30,"") | AB30: =IFERROR(X30/V30,"") | AC30: FALSE | AD30: FALSE | AE30: FALSE | AF30: Yes | AG30: 46204 | AI30: TRUE | AJ30: 5 | AL30: ORG fastahead GmbH & Co. KG | AM30: User Experience Design | AN30: fah Tim Thierfelder | AO30: fastahead GmbH & Co. KG | AP30: Berlin | AQ30: Tim Thierfelder
A31: 10007 | B31: 67B144 | C31: https://app.matchical.com/Consulting/ConsultantDetail?ConsultantId=00713c49-1d9f-4cca-8954-7f1ffce1269b | D31: Anatoli Schäfer | E31: anatoli.schaefer@bridging-it.de | F31: 44866 | G31: 44562 | H31: 9 | I31: 0 | J31: 0 | L31: 45658 | M31: 46022 | N31: FALSE | O31: 40 | P31: 38.97 | Q31: 38.97 | R31: =ROUND(O31-P31,2) | S31: =ROUND(O31-Q31,2) | T31: =IFERROR(P31/O31,"") | U31: =IFERROR(Q31/O31,"") | V31: 10 | W31: 8 | X31: 8 | Y31: =ROUND(V31-W31,2) | Z31: =ROUND(V31-X31,2) | AA31: =IFERROR(W31/V31,"") | AB31: =IFERROR(X31/V31,"") | AC31: FALSE | AD31: FALSE | AE31: FALSE | AF31: No | AI31: FALSE | AJ31: 0 | AL31: A&SE Analytics & Software Engineering (Philip R.) | AM31: FV Fullstack Visionaries (Matthias H.) | AN31: FUN Fullstack Ninjas (Stefan Z.) | AO31: bridgingIT GmbH | AP31: Mannheim | AQ31: Matthias Hetz
A32: 10264 | B32: E9AC01 | C32: https://app.matchical.com/Consulting/ConsultantDetail?ConsultantId=1b6f2d18-bb04-4f51-9faf-6516176ba681 | D32: Andre Hein | E32: andre.hein@bridging-it.de | F32: 45383 | G32: 40330 | H32: 12 | I32: 0 | J32: 2 | K32: 45596 | L32: 45397 | M32: 45657 | N32: FALSE | O32: 23 | P32: 39 | Q32: 21 | R32: =ROUND(O32-P32,2) | S32: =ROUND(O32-Q32,2) | T32: =IFERROR(P32/O32,"") | U32: =IFERROR(Q32/O32,"") | V32: 166 | W32: 150 | X32: 74 | Y32: =ROUND(V32-W32,2) | Z32: =ROUND(V32-X32,2) | AA32: =IFERROR(W32/V32,"") | AB32: =IFERROR(X32/V32,"") | AC32: FALSE | AD32: FALSE | AE32: FALSE | AF32: No | AI32: TRUE | AJ32: 0 | AL32: T&A - Transformation & Agility (Arne K.) | AM32: CTM – Change & Transformationmgmt. HH (Katja R.) | AN32: A&PM Agility & Project Management (Jan H.) | AO32: bridgingIT GmbH | AP32: Hamburg | AQ32: Katja Runge
A33: 8687 | B33: 6161A5 | C33: https://app.matchical.com/Consulting/ConsultantDetail?ConsultantId=9c4bab4b-c38b-4386-a474-b976cad6f763 | D33: André Krippendorf | E33: andre.krippendorf@crafting-it.de | F33: 44348 | G33: 41456 | H33: 15 | I33: 0 | J33: 2 | K33: 44561 | L33: 45364 | M33: 45657 | N33: FALSE | O33: 57 | P33: 210.79 | Q33: 56.8 | R33: =ROUND(O33-P33,2) | S33: =ROUND(O33-Q33,2) | T33: =IFERROR(P33/O33,"") | U33: =IFERROR(Q33/O33,"") | V33: 95 | W33: 0 | X33: 0 | Y33: =ROUND(V33-W33,2) | Z33: =ROUND(V33-X33,2) | AA33: =IFERROR(W33/V33,"") | AB33: =IFERROR(X33/V33,"") | AC33: FALSE | AD33: FALSE | AE33: FALSE | AF33: Yes | AG33: 45931 | AI33: TRUE | AJ33: 3 | AK33: Occasional on-site client meetings can indeed be represented. | AL33: ORG cIT | AM33: cIT Development | AN33: cIT Service Delivery Magdeburg (Steffen A.) | AO33: craftingIT GmbH | AP33: Magdeburg | AQ33: Jennifer Saalfeld
A34: 8722 | B34: 3F7D01 | C34: https://app.matchical.com/Consulting/ConsultantDetail?ConsultantId=89e26302-5625-42b2-b010-1cb4a8bc8554 | D34: Andre Lexow | E34: andre.lexow@crafting-it.de | F34: 44545 | G34: 44545 | H34: 20 | I34: 0 | J34: 1 | K34: 46022 | L34: 45658 | M34: 46022 | N34: FALSE | O34: 50 | P34: 195.14 | Q34: 50.33 | R34: =ROUND(O34-P34,2) | S34: =ROUND(O34-Q34,2) | T34: =IFERROR(P34/O34,"") | U34: =IFERROR(Q34/O34,"") | V34: 0 | W34: 0 | X34: 0 | Y34: =ROUND(V34-W34,2) | Z34: =ROUND(V34-X34,2) | AA34: =IFERROR(W34/V34,"") | AB34: =IFERROR(X34/V34,"") | AC34: FALSE | AD34: FALSE | AE34: FALSE | AF34: Yes | AG34: 45809 | AI34: TRUE | AJ34: 3 | AL34: ORG cIT | AM34: cIT AMS / GIS Services (Michael B.) | AN34: cIT Service Delivery Magdeburg (Steffen A.) | AO34: craftingIT GmbH | AP34: Magdeburg | AQ34: Michael Buchter
A35: 1327 | B35: E894F1 | C35: https://app.matchical.com/Consulting/ConsultantDetail?ConsultantId=97ba9131-62f0-433e-b541-fbbb5b2d5e22 | D35: Andreas Bürkle | E35: andreas.buerkle@bridging-it.de | F35: 42384 | G35: 39448 | H35: 17 | I35: 0 | J35: 2 | K35: 44423 | L35: 42442 | M35: 45827 | N35: FALSE | O35: 121 | P35: 386.9 | Q35: 120.97 | R35: =ROUND(O35-P35,2) | S35: =ROUND(O35-Q35,2) | T35: =IFERROR(P35/O35,"") | U35: =IFERROR(Q35/O35,"") | V35: 96 | W35: 71 | X35: 71 | Y35: =ROUND(V35-W35,2) | Z35: =ROUND(V35-X35,2) | AA35: =IFERROR(W35/V35,"") | AB35: =IFERROR(X35/V35,"") | AC35: FALSE | AD35: FALSE | AE35: FALSE | AF35: Yes | AG35: 46023 | AI35: TRUE | AJ35: 5 | AK35: Target role: RTE, Scrum Master, Agile Coach Industry experience: Automotive, Retail, Pharmaceutical, Energy Willingness to travel: Occasional travel to Frankfurt, Stuttgart, and Cologne is acceptable. Up to three hotel overnight stays per month are acceptable. | AL35: T&A - Transformation & Agility (Arne K.) | AM35: HPMI - Hybrid Project Mgmt & Innovat. (Sascha W.) | AN35: A&PM Agility & Project Management (Jan H.) | AO35: bridgingIT GmbH | AP35: Mannheim | AQ35: Sascha Wacker
A36: 10357 | B36: 8574CB | C36: https://app.matchical.com/Consulting/ConsultantDetail?ConsultantId=9373d136-b4bf-4a1c-b467-e0440d963037 | D36: Andreas Diel | E36: andreas.diel@fastahead.com | F36: 45748 | G36: 35765 | H36: 20 | I36: 0 | J36: 0 | L36: 45838 | M36: 45960 | N36: FALSE | O36: 11 | P36: 4.76 | Q36: 4.76 | R36: =ROUND(O36-P36,2) | S36: =ROUND(O36-Q36,2) | T36: =IFERROR(P36/O36,"") | U36: =IFERROR(Q36/O36,"") | V36: 328 | W36: 278 | X36: 127 | Y36: =ROUND(V36-W36,2) | Z36: =ROUND(V36-X36,2) | AA36: =IFERROR(W36/V36,"") | AB36: =IFERROR(X36/V36,"") | AC36: FALSE | AD36: FALSE | AE36: FALSE | AF36: No | AI36: TRUE | AJ36: 0 | AK36: Key skills: Banking, Finance, Strategy consulting, KPI systems, Spanish | AL36: ORG fastahead GmbH & Co. KG | AM36: Banking (R. Weygand) | AN36: fah Ralf Weygand | AO36: fastahead GmbH & Co. KG | AP36: Köln | AQ36: Ralf Weygand
A37: 1040 | B37: DA65EB | C37: https://app.matchical.com/Consulting/ConsultantDetail?ConsultantId=f9614ca2-7a00-4b51-9ecb-13f7c5e79b23 | D37: Andreas Dietz | E37: andreas.dietz@bridging-it.de | F37: 39569 | G37: 36526 | H37: 30 | I37: 0 | J37: 2 | K37: 41274 | L37: 41275 | M37: 45715 | N37: FALSE | O37: 214 | P37: 924.94 | Q37: 213.82 | R37: =ROUND(O37-P37,2) | S37: =ROUND(O37-Q37,2) | T37: =IFERROR(P37/O37,"") | U37: =IFERROR(Q37/O37,"") | V37: 100 | W37: 96.06 | X37: 91.88 | Y37: =ROUND(V37-W37,2) | Z37: =ROUND(V37-X37,2) | AA37: =IFERROR(W37/V37,"") | AB37: =IFERROR(X37/V37,"") | AC37: FALSE | AD37: FALSE | AE37: FALSE | AF37: Yes | AG37: 46037 | AH37: 46080 | AI37: FALSE | AJ37: 2.5 | AK37: Andreas works at the start of the year at 50% (4 hours per day) | AL37: ORG bIT | AM37: PITS Professional IT-Services (Martin R.) | AN37: MIT Management of IT (Torsten R.) | AO37: bridgingIT GmbH | AP37: Frankfurt | AQ37: Martin Redemsky
A38: 2284 | B38: 47D30E | C38: https://app.matchical.com/Consulting/ConsultantDetail?ConsultantId=5a972972-e205-4df7-b8d4-328765f2877d | D38: Andreas Glasa | E38: andreas.glasa@bridging-it.de | F38: 44470 | G38: 39510 | H38: 6 | I38: 0 | J38: 2 | K38: 44695 | L38: 45504 | M38: 45776 | N38: FALSE | O38: 53 | P38: 115 | Q38: 52.8 | R38: =ROUND(O38-P38,2) | S38: =ROUND(O38-Q38,2) | T38: =IFERROR(P38/O38,"") | U38: =IFERROR(Q38/O38,"") | V38: 163 | W38: 34 | X38: 34 | Y38: =ROUND(V38-W38,2) | Z38: =ROUND(V38-X38,2) | AA38: =IFERROR(W38/V38,"") | AB38: =IFERROR(X38/V38,"") | AC38: FALSE | AD38: FALSE | AE38: FALSE | AF38: No | AI38: TRUE | AJ38: 0 | AK38: Andreas is a highly experienced Agile Coach/RTE and SAFe trainer. | AL38: DO Digital Organizations (Michael H.) | AM38: AO Agile Organizations (Andreas G.) | AN38: BT Business Transformation (Julian D.) | AO38: bridgingIT GmbH | AP38: Stuttgart | AQ38: Julian Dahlbender
A39: 2236 | B39: D992B7 | C39: https://app.matchical.com/Consulting/ConsultantDetail?ConsultantId=e4f77298-25ef-4c96-9dc5-f5a8f77253f7 | D39: Andreas Hellner | E39: andreas.hellner@bridging-it.de | F39: 43466 | G39: 40756 | H39: 7 | I39: 0 | J39: 1 | K39: 44885 | L39: 43830 | M39: 44546 | N39: FALSE | O39: 86 | P39: 74 | Q39: 70 | R39: =ROUND(O39-P39,2) | S39: =ROUND(O39-Q39,2) | T39: =IFERROR(P39/O39,"") | U39: =IFERROR(Q39/O39,"") | V39: 89 | W39: 89.46 | X39: 89.03 | Y39: =ROUND(V39-W39,2) | Z39: =ROUND(V39-X39,2) | AA39: =IFERROR(W39/V39,"") | AB39: =IFERROR(X39/V39,"") | AC39: FALSE | AD39: FALSE | AE39: FALSE | AF39: No | AI39: FALSE | AJ39: 5 | AK39: Key skills: * .NET software development (Backend) * Azure * Software architecture | AL39: ES Enterprise Solutions (Gina H.) | AM39: IEM .Net I (Christoph M.) | AN39: IEJ Individualentwicklung JAVA (Dominik S.) | AO39: bridgingIT GmbH | AP39: Stuttgart | AQ39: Christoph Müller
A40: 10164 | B40: 38CDEF | C40: https://app.matchical.com/Consulting/ConsultantDetail?ConsultantId=e27d9444-1faf-468a-bd3e-be13f2d08b2a | D40: Andreas Hofmann | E40: andreas.hofmann@fastahead.com | F40: 45170 | G40: 36800 | H40: 10 | I40: 0 | J40: 0 | L40: 45748 | M40: 46022 | N40: FALSE | O40: 30 | P40: 18.02 | Q40: 18.02 | R40: =ROUND(O40-P40,2) | S40: =ROUND(O40-Q40,2) | T40: =IFERROR(P40/O40,"") | U40: =IFERROR(Q40/O40,"") | V40: 275 | W40: 136.98 | X40: 95.98 | Y40: =ROUND(V40-W40,2) | Z40: =ROUND(V40-X40,2) | AA40: =IFERROR(W40/V40,"") | AB40: =IFERROR(X40/V40,"") | AC40: FALSE | AD40: FALSE | AE40: FALSE | AF40: Yes | AG40: 46023 | AI40: TRUE | AJ40: 5 | AK40: Financial Services, Banking and Credit Industry, Technology, Structured Finance, Distributed Ledger Technologies, Regulation, Project Management, Interim Management | AL40: ORG fastahead GmbH & Co. KG | AM40: Banking (R. Weygand) | AN40: fah Ralf Weygand | AO40: fastahead GmbH & Co. KG | AP40: München | AQ40: Ralf Weygand
A41: 3254 | B41: 075195 | C41: https://app.matchical.com/Consulting/ConsultantDetail?ConsultantId=71fc7cd7-4199-403b-adcb-cf61b70750f8 | D41: Andreas Kernbach | E41: andreas.kernbach@bridging-it.de | F41: 44743 | G41: 32964 | H41: 9 | I41: 0 | J41: 0 | L41: 44805 | M41: 45291 | N41: FALSE | O41: 44 | P41: 16 | Q41: 16 | R41: =ROUND(O41-P41,2) | S41: =ROUND(O41-Q41,2) | T41: =IFERROR(P41/O41,"") | U41: =IFERROR(Q41/O41,"") | V41: 387 | W41: 168 | X41: 139 | Y41: =ROUND(V41-W41,2) | Z41: =ROUND(V41-X41,2) | AA41: =IFERROR(W41/V41,"") | AB41: =IFERROR(X41/V41,"") | AC41: FALSE | AD41: FALSE | AE41: FALSE | AF41: No | AG41: 44743 | AH41: 45291 | AI41: TRUE | AJ41: 5 | AK41: Focus on managed services, provider and contract management | AL41: Sales BL | AM41: SAL Team Kernbach | AN41: Capability Management (Tim T.) | AO41: bridgingIT GmbH | AP41: Frankfurt | AQ41: Tim Thierfelder
A42: 8723 | B42: 0D059A | C42: https://app.matchical.com/Consulting/ConsultantDetail?ConsultantId=e5b1518c-965a-4157-ab81-6b05467e39c7 | D42: Andreas Lexow | E42: andreas.lexow@crafting-it.de | F42: 44545 | G42: 44545 | H42: 4 | I42: 0 | J42: 0 | L42: 44561 | M42: 45657 | N42: FALSE | O42: 50 | P42: 104 | Q42: 38 | R42: =ROUND(O42-P42,2) | S42: =ROUND(O42-Q42,2) | T42: =IFERROR(P42/O42,"") | U42: =IFERROR(Q42/O42,"") | V42: 0 | W42: 0 | X42: 0 | Y42: =ROUND(V42-W42,2) | Z42: =ROUND(V42-X42,2) | AA42: =IFERROR(W42/V42,"") | AB42: =IFERROR(X42/V42,"") | AC42: FALSE | AD42: FALSE | AE42: FALSE | AF42: Yes | AG42: 45809 | AI42: TRUE | AJ42: 4 | AL42: ORG cIT | AM42: cIT AMS / GIS Services (Michael B.) | AN42: cIT Service Delivery Magdeburg (Steffen A.) | AO42: craftingIT GmbH | AP42: Magdeburg | AQ42: Michael Buchter
A43: 1291 | B43: 158BD7 | C43: https://app.matchical.com/Consulting/ConsultantDetail?ConsultantId=2452d67e-e196-471c-9bd4-6f93c0b00bbd | D43: Andreas Menrath | E43: andreas.menrath@bridging-it.de | F43: 42125 | G43: 36495 | H43: 23 | I43: 0 | J43: 1 | K43: 43616 | L43: 44469 | M43: 44680 | N43: FALSE | O43: 130 | P43: 211 | Q43: 129 | R43: =ROUND(O43-P43,2) | S43: =ROUND(O43-Q43,2) | T43: =IFERROR(P43/O43,"") | U43: =IFERROR(Q43/O43,"") | V43: 185 | W43: 133 | X43: 76 | Y43: =ROUND(V43-W43,2) | Z43: =ROUND(V43-X43,2) | AA43: =IFERROR(W43/V43,"") | AB43: =IFERROR(X43/V43,"") | AC43: FALSE | AD43: FALSE | AE43: FALSE | AF43: Yes | AG43: 46204 | AI43: TRUE | AJ43: 5 | AK43: Desired role: Agile Coach, SAFe Coach Industry experience: Pharma, Chemistry, Logistics, Automotive, Insurance | AL43: T&A - Transformation & Agility (Arne K.) | AM43: PACE – Project Agility & Cont' Evolution (Jan H.) | AN43: A&PM Agility & Project Management (Jan H.) | AO43: bridgingIT GmbH | AP43: Mannheim | AQ43: Jan Heinemann
A44: 1396 | B44: FF1C6E | C44: https://app.matchical.com/Consulting/ConsultantDetail?ConsultantId=9b9f363c-ab57-4367-b0d7-a6e7b87ebe95 | D44: Andreas Morgenstern | E44: andreas.morgenstern@bridging-it.de | F44: 43009 | G44: 38292 | H44: 22 | I44: 0 | J44: 2 | K44: 43465 | L44: 45662 | M44: 45839 | N44: FALSE | O44: 101 | P44: 175 | Q44: 96 | R44: =ROUND(O44-P44,2) | S44: =ROUND(O44-Q44,2) | T44: =IFERROR(P44/O44,"") | U44: =IFERROR(Q44/O44,"") | V44: 155 | W44: 207 | X44: 154.97 | Y44: =ROUND(V44-W44,2) | Z44: =ROUND(V44-X44,2) | AA44: =IFERROR(W44/V44,"") | AB44: =IFERROR(X44/V44,"") | AC44: FALSE | AD44: FALSE | AE44: FALSE | AF44: No | AI44: FALSE | AJ44: 2 | AL44: ORG bIT | AM44: SE Software Engineering Frankfurt (Andreas M.) | AN44: ES Enterprise Solutions (Dominik H.) | AO44: bridgingIT GmbH | AP44: Frankfurt | AQ44: Dominik Hanft
A45: 10222 | B45: 035C87 | C45: https://app.matchical.com/Consulting/ConsultantDetail?ConsultantId=cf98450d-ffb7-4029-b68d-d9ed91de08bd | D45: Andreas Rothe | E45: andreas.rothe@fastahead.com | F45: 45292 | G45: 38078 | H45: 13 | I45: 0 | J45: 0 | L45: 45657 | M45: 45944 | N45: FALSE | O45: 26 | P45: 19 | Q45: 17 | R45: =ROUND(O45-P45,2) | S45: =ROUND(O45-Q45,2) | T45: =IFERROR(P45/O45,"") | U45: =IFERROR(Q45/O45,"") | V45: 237 | W45: 193 | X45: 117 | Y45: =ROUND(V45-W45,2) | Z45: =ROUND(V45-X45,2) | AA45: =IFERROR(W45/V45,"") | AB45: =IFERROR(X45/V45,"") | AC45: FALSE | AD45: FALSE | AE45: FALSE | AF45: No | AI45: TRUE | AJ45: 0 | AL45: ORG fastahead GmbH & Co. KG | AM45: Digital Services and Process-Innovation | AN45: fah Paul Seelmeyer | AO45: fastahead GmbH & Co. KG | AP45: Berlin | AQ45: Paul Seelmeyer
A46: 4048 | B46: 582097 | C46: https://app.matchical.com/Consulting/ConsultantDetail?ConsultantId=0dbe375f-061b-4e29-8b7a-6cf6455a1a00 | D46: Andree Große | E46: andree.grosse@bridging-it.de | F46: 42505 | G46: 34121 | H46: 11 | I46: 0 | J46: 1 | K46: 44115 | L46: 44378 | M46: 44742 | N46: FALSE | O46: 117 | P46: 122 | Q46: 110 | R46: =ROUND(O46-P46,2) | S46: =ROUND(O46-Q46,2) | T46: =IFERROR(P46/O46,"") | U46: =IFERROR(Q46/O46,"") | V46: 275 | W46: 41 | X46: 41 | Y46: =ROUND(V46-W46,2) | Z46: =ROUND(V46-X46,2) | AA46: =IFERROR(W46/V46,"") | AB46: =IFERROR(X46/V46,"") | AC46: FALSE | AD46: FALSE | AE46: FALSE | AF46: No | AI46: TRUE | AJ46: 0 | AL46: ORG bIT Bayern | AM46: LM Location Management BAY (Eli G.) | AN46: LM Lokation MUC (Elisabeth G.) | AO46: bridgingIT GmbH | AP46: München | AQ46: Elisabeth Gerlinger
A47: 7032 | B47: 34CD01 | C47: https://app.matchical.com/Consulting/ConsultantDetail?ConsultantId=41a60832-9731-49b1-b19c-8342f6d79748 | D47: Andrej Olsen | E47: andrej.olsen@fastahead.com | F47: 44211 | G47: 41913 | H47: 9 | I47: 0 | J47: 1 | K47: 45292 | L47: 45028 | M47: 45350 | N47: FALSE | O47: 61 | P47: 61 | Q47: 53 | R47: =ROUND(O47-P47,2) | S47: =ROUND(O47-Q47,2) | T47: =IFERROR(P47/O47,"") | U47: =IFERROR(Q47/O47,"") | V47: 76 | W47: 0 | X47: 0 | Y47: =ROUND(V47-W47,2) | Z47: =ROUND(V47-X47,2) | AA47: =IFERROR(W47/V47,"") | AB47: =IFERROR(X47/V47,"") | AC47: FALSE | AD47: FALSE | AE47: FALSE | AF47: No | AI47: TRUE | AJ47: 0 | AK47: Please request the profile via Anastasia Kluter. | AL47: ORG fastahead GmbH & Co. KG | AM47: User Experience Design | AN47: fah Tim Thierfelder | AO47: fastahead GmbH & Co. KG | AP47: Stuttgart | AQ47: Anastasia Rettberg-Kluter
A48: 1489 | B48: 6A8F1C | C48: https://app.matchical.com/Consulting/ConsultantDetail?ConsultantId=7797ce4f-ab17-4677-a219-1d405d76fc83 | D48: Andrey Ivashutin | E48: andrey.ivashutin@bridging-it.de | F48: 44501 | G48: 43556 | H48: 6 | I48: 0 | J48: 1 | K48: 44774 | L48: 45658 | M48: 46022 | N48: FALSE | O48: 52 | P48: 63 | Q48: 50 | R48: =ROUND(O48-P48,2) | S48: =ROUND(O48-Q48,2) | T48: =IFERROR(P48/O48,"") | U48: =IFERROR(Q48/O48,"") | V48: 31 | W48: 12.97 | X48: 12.97 | Y48: =ROUND(V48-W48,2) | Z48: =ROUND(V48-X48,2) | AA48: =IFERROR(W48/V48,"") | AB48: =IFERROR(X48/V48,"") | AC48: FALSE | AD48: FALSE | AE48: FALSE | AF48: No | AI48: FALSE | AJ48: 0 | AK48: Andrey has been on a project for Roche, the client, for several years, and in this context he has gained very solid experience in both back-end development with Spring Boot/Java and front-end development. | AL48: A&SE Analytics & Software Engineering (Philip R.) | AM48: FV Fullstack Visionaries (Matthias H.) | AN48: FUN Fullstack Ninjas (Stefan Z.) | AO48: bridgingIT GmbH | AP48: Mannheim | AQ48: Matthias Hetz
A49: 2323 | B49: F5C61C | C49: https://app.matchical.com/Consulting/ConsultantDetail?ConsultantId=b05eb2fd-5503-4cc1-8b39-e20a527b41e7 | D49: Angela Napoli | E49: angela.napoli@bridging-it.de | F49: 44835 | G49: 44423 | H49: 6 | I49: 0 | J49: 2 | K49: 45446 | L49: 44469 | M49: 45443 | N49: FALSE | O49: 41 | P49: 62.98 | Q49: 37.55 | R49: =ROUND(O49-P49,2) | S49: =ROUND(O49-Q49,2) | T49: =IFERROR(P49/O49,"") | U49: =IFERROR(Q49/O49,"") | V49: 14 | W49: 25.02 | X49: 13.54 | Y49: =ROUND(V49-W49,2) | Z49: =ROUND(V49-X49,2) | AA49: =IFERROR(W49/V49,"") | AB49: =IFERROR(X49/V49,"") | AC49: FALSE | AD49: FALSE | AE49: FALSE | AF49: No | AI49: TRUE | AJ49: 0 | AL49: IT Information Technology (Hauke G.) | AM49: ITT IT-Transformation (Carmen D.) | AN49: ITM IT-Management (Jörg M.) | AO49: bridgingIT GmbH | AP49: Stuttgart | AQ49: Carmen Deubelbeiss
A50: 2228 | B50: 8D4281 | C50: https://app.matchical.com/Consulting/ConsultantDetail?ConsultantId=fead2f58-8986-4e9b-9506-3efe60d5954b | D50: Anika Wurster | E50: anika.wurster@bridging-it.de | F50: 43374 | G50: 42324 | H50: 17 | I50: 0 | J50: 0 | L50: 45518 | M50: 45868 | N50: FALSE | O50: 89 | P50: 137.97 | Q50: 88.8 | R50: =ROUND(O50-P50,2) | S50: =ROUND(O50-Q50,2) | T50: =IFERROR(P50/O50,"") | U50: =IFERROR(Q50/O50,"") | V50: 34 | W50: 73.48 | X50: 34.5 | Y50: =ROUND(V50-W50,2) | Z50: =ROUND(V50-X50,2) | AA50: =IFERROR(W50/V50,"") | AB50: =IFERROR(X50/V50,"") | AC50: FALSE | AD50: FALSE | AE50: FALSE | AF50: No | AI50: TRUE | AJ50: 0 | AL50: IT Information Technology (Hauke G.) | AM50: ITT IT-Transformation (Carmen D.) | AN50: ITM IT-Management (Jörg M.) | AO50: bridgingIT GmbH | AP50: Stuttgart | AQ50: Carmen Deubelbeiss
A51: 1529 | B51: A56C88 | C51: https://app.matchical.com/Consulting/ConsultantDetail?ConsultantId=d015fdec-23a6-4362-9b93-62093a14959b | D51: Anissa Wannowius | E51: anissa.wannowius@bridging-it.de | F51: 44835 | G51: 43952 | H51: 7 | I51: 0 | J51: 0 | L51: 45536 | M51: 45837 | N51: FALSE | O51: 41 | P51: 34 | Q51: 34 | R51: =ROUND(O51-P51,2) | S51: =ROUND(O51-Q51,2) | T51: =IFERROR(P51/O51,"") | U51: =IFERROR(Q51/O51,"") | V51: 29 | W51: 52 | X51: 28 | Y51: =ROUND(V51-W51,2) | Z51: =ROUND(V51-X51,2) | AA51: =IFERROR(W51/V51,"") | AB51: =IFERROR(X51/V51,"") | AC51: FALSE | AD51: FALSE | AE51: FALSE | AF51: No | AI51: FALSE | AJ51: 0 | AL51: IT - Information Technology (Sebastian L.) | AM51: ESM Enterprise Service Management (Christian Wo.) | AN51: C&DO - Cloud & DevOps (Sebastian L.) | AO51: bridgingIT GmbH | AP51: Mannheim | AQ51: Christian Wolf
A52: 8289 | B52: 8D27F9 | C52: https://app.matchical.com/Consulting/ConsultantDetail?ConsultantId=a911ddf4-87b8-41aa-9dc3-a33ee8a8ace2 | D52: Anja Felgenhauer | E52: anja.felgenhauer@crafting-it.de | F52: 42917 | G52: 40909 | H52: 22 | I52: 0 | J52: 0 | L52: 45139 | M52: 46022 | N52: FALSE | O52: 104 | P52: 226 | Q52: 85.5 | R52: =ROUND(O52-P52,2) | S52: =ROUND(O52-Q52,2) | T52: =IFERROR(P52/O52,"") | U52: =IFERROR(Q52/O52,"") | V52: 66 | W52: 0 | X52: 0 | Y52: =ROUND(V52-W52,2) | Z52: =ROUND(V52-X52,2) | AA52: =IFERROR(W52/V52,"") | AB52: =IFERROR(X52/V52,"") | AC52: FALSE | AD52: FALSE | AE52: FALSE | AF52: No | AI52: TRUE | AJ52: 0 | AL52: ORG cIT 2 | AM52: cIT Service Management | AN52: cIT Services allgemein (Christian K.) | AO52: craftingIT GmbH | AP52: Magdeburg | AQ52: Christopher Schweinsteiger
A53: 10032 | B53: F889EB | C53: https://app.matchical.com/Consulting/ConsultantDetail?ConsultantId=1415f946-211a-4870-a812-df70f7bbdcdf | D53: Ann-Kathrin Woska | E53: ann-kathrin.woska@fastahead.com | F53: 45017 | G53: 43831 | H53: 5 | I53: 0 | J53: 1 | K53: 45291 | L53: 45017 | M53: 45259 | N53: FALSE | O53: 35 | P53: 38 | Q53: 33 | R53: =ROUND(O53-P53,2) | S53: =ROUND(O53-Q53,2) | T53: =IFERROR(P53/O53,"") | U53: =IFERROR(Q53/O53,"") | V53: 39 | W53: 36.97 | X53: 36.97 | Y53: =ROUND(V53-W53,2) | Z53: =ROUND(V53-X53,2) | AA53: =IFERROR(W53/V53,"") | AB53: =IFERROR(X53/V53,"") | AC53: FALSE | AD53: FALSE | AE53: FALSE | AF53: No | AI53: TRUE | AJ53: 0 | AK53: 50 Hz engagement until the end of 2024, Focus on data engineering topics with a perspective on data governance and data strategy, business analysis topics with data relevance, data visualization; | AL53: ORG fastahead GmbH & Co. KG | AM53: Business-driven Architectures (Dr. C. Gitte) | AN53: fah Tim Thierfelder | AO53: fastahead GmbH & Co. KG | AP53: Mannheim | AQ53: Christian Gitte
A54: 10395 | B54: 9AF94F | C54: https://app.matchical.com/Consulting/ConsultantDetail?ConsultantId=a1560d6d-a94c-4eea-9ab4-5be1cad455df | D54: Anna Holzmann | E54: anna.holzmann@bridging-it.de | F54: 45931 | G54: 44348 | H54: 10 | I54: 0 | J54: 1 | K54: 45942 | L54: 45942 | M54: 46022 | N54: FALSE | O54: 5 | P54: 7 | Q54: 4.8 | R54: =ROUND(O54-P54,2) | S54: =ROUND(O54-Q54,2) | T54: =IFERROR(P54/O54,"") | U54: =IFERROR(Q54/O54,"") | V54: 52 | W54: 60.97 | X54: 42.97 | Y54: =ROUND(V54-W54,2) | Z54: =ROUND(V54-X54,2) | AA54: =IFERROR(W54/V54,"") | AB54: =IFERROR(X54/V54,"") | AC54: FALSE | AD54: FALSE | AE54: FALSE | AF54: Yes | AG54: 46143 | AI54: TRUE | AJ54: 5 | AK54: [BASF] Continuation of the validation with LLM (Holger Bohlen) | AL54: ORG bIT Bayern | AM54: DSA Data Solutions & AI (Philip R.) | AN54: BPD Business Processes & Data Engineering(Arne K.) | AO54: bridgingIT GmbH | AP54: München | AQ54: Philip Rausch
A55: 10374 | B55: 91093C | C55: https://app.matchical.com/Consulting/ConsultantDetail?ConsultantId=ce80b052-4530-48d0-916f-18e373f2b217 | D55: Anna Rolke | E55: anna.rolke@bridging-it.de | F55: 45870 | G55: 41548 | H55: 11 | I55: 0 | J55: 0 | L55: 45915 | M55: 46021 | N55: FALSE | O55: 7 | P55: 4 | Q55: 4 | R55: =ROUND(O55-P55,2) | S55: =ROUND(O55-Q55,2) | T55: =IFERROR(P55/O55,"") | U55: =IFERROR(Q55/O55,"") | V55: 142 | W55: 97 | X55: 56.33 | Y55: =ROUND(V55-W55,2) | Z55: =ROUND(V55-X55,2) | AA55: =IFERROR(W55/V55,"") | AB55: =IFERROR(X55/V55,"") | AC55: FALSE | AD55: FALSE | AE55: FALSE | AF55: No | AI55: TRUE | AJ55: 0 | AK55: Anna has 3 years of experience in IT consulting and is seeking a project in project management, requirements management, or change management. Her strength lies particularly in managing many stakeholders with heterogeneous requirements. She has experience in digitization projects for public administrations and has carried out, among other things, process standardization and optimization. | AL55: T&A - Transformation & Agility (Arne K.) | AM55: P&OS - Processes & Organizational Str. (Raina B.) | AN55: TB - Transforming Business (Arne K.) | AO55: bridgingIT GmbH | AP55: Mannheim | AQ55: Raina Beck
A56: 3082 | B56: 2EF1BB | C56: https://app.matchical.com/Consulting/ConsultantDetail?ConsultantId=578394bc-5d45-4aa5-a570-f3617eff0a6c | D56: Anna Schnorrenberger | E56: anna.schnorrenberger@bridging-it.de | F56: 41699 | G56: 36770 | H56: 35 | I56: 0 | J56: 2 | K56: 43465 | L56: 45615 | M56: 46022 | N56: FALSE | O56: 144 | P56: 419.76 | Q56: 143.84 | R56: =ROUND(O56-P56,2) | S56: =ROUND(O56-Q56,2) | T56: =IFERROR(P56/O56,"") | U56: =IFERROR(Q56/O56,"") | V56: 162 | W56: 115 | X56: 97 | Y56: =ROUND(V56-W56,2) | Z56: =ROUND(V56-X56,2) | AA56: =IFERROR(W56/V56,"") | AB56: =IFERROR(X56/V56,"") | AC56: FALSE | AD56: FALSE | AE56: FALSE | AF56: No | AI56: FALSE | AJ56: 0 | AL56: ORG bIT | AM56: AT Agile Transformation (Anna S.) | AN56: TH Transformation Hub (Ulrich W.) | AO56: bridgingIT GmbH | AP56: Frankfurt | AQ56: Ulrich Waltinger
A57: 1385 | B57: 3EA6E2 | C57: https://app.matchical.com/Consulting/ConsultantDetail?ConsultantId=73037617-f6bb-4d42-96bf-88779b7193e6 | D57: Anna Wanzek | E57: anna.wanzek@bridging-it.de | F57: 42826 | G57: 41913 | H57: 18 | I57: 0 | J57: 4 | K57: 42794 | L57: 45657 | M57: 45925 | N57: FALSE | O57: 107 | P57: 426.5 | Q57: 106.81 | R57: =ROUND(O57-P57,2) | S57: =ROUND(O57-Q57,2) | T57: =IFERROR(P57/O57,"") | U57: =IFERROR(Q57/O57,"") | V57: 30 | W57: 38.8 | X57: 25.61 | Y57: =ROUND(V57-W57,2) | Z57: =ROUND(V57-X57,2) | AA57: =IFERROR(W57/V57,"") | AB57: =IFERROR(X57/V57,"") | AC57: FALSE | AD57: FALSE | AE57: FALSE | AF57: No | AI57: FALSE | AJ57: 0 | AK57: - Re-engagement at KGAL in the iPaaS project, currently under clarification, high probability (Responsible: Denise Gillmann/Michael Hof) - Idea: actively pitch through Peter Müller at [DZ Bank] in the context of Tableau | AL57: A&SE Analytics & Software Engineering (Philip R.) | AM57: DS Data Science (Dr. Philip W.) | AN57: A&DDS - Analytics & Data-driven Solutions (M. Hof) | AO57: bridgingIT GmbH | AP57: Mannheim | AQ57: Philip Wollfarth
A58: 10073 | B58: 57E481 | C58: https://app.matchical.com/Consulting/ConsultantDetail?ConsultantId=235d9050-cf1d-439b-819b-03db6ced6a9a | D58: Annette Funk | E58: annette.funk@bridging-it.de | F58: 44958 | G58: 43647 | H58: 6 | I58: 0 | J58: 0 | L58: 44985 | M58: 45595 | N58: FALSE | O58: 37 | P58: 35.88 | Q58: 35.88 | R58: =ROUND(O58-P58,2) | S58: =ROUND(O58-Q58,2) | T58: =IFERROR(P58/O58,"") | U58: =IFERROR(Q58/O58,"") | V58: 43 | W58: 40.97 | X58: 40.97 | Y58: =ROUND(V58-W58,2) | Z58: =ROUND(V58-X58,2) | AA58: =IFERROR(W58/V58,"") | AB58: =IFERROR(X58/V58,"") | AC58: FALSE | AD58: FALSE | AE58: FALSE | AF58: Yes | AG58: 46113 | AH58: 47483 | AI58: TRUE | AJ58: 5 | AL58: ORG bIT | AM58: BABA - BA and Business Architectures (Carsten S.) | AN58: ABC Analysing Business & Collaboration (Edgar K.) | AO58: bridgingIT GmbH | AP58: Frankfurt | AQ58: Carsten Schindler
A59: 10392 | B59: 4744FE | C59: https://app.matchical.com/Consulting/ConsultantDetail?ConsultantId=1dd8a2ac-d350-424b-a080-57a203d61272 | D59: Ante Limov | E59: ante.limov@bridging-it.de | F59: 45901 | G59: 43466 | H59: 8 | I59: 0 | J59: 0 | L59: 45870 | M59: 46022 | N59: FALSE | O59: 6 | P59: 3.98 | Q59: 3.98 | R59: =ROUND(O59-P59,2) | S59: =ROUND(O59-Q59,2) | T59: =IFERROR(P59/O59,"") | U59: =IFERROR(Q59/O59,"") | V59: 80 | W59: 72.02 | X59: 66.02 | Y59: =ROUND(V59-W59,2) | Z59: =ROUND(V59-X59,2) | AA59: =IFERROR(W59/V59,"") | AB59: =IFERROR(X59/V59,"") | AC59: FALSE | AD59: FALSE | AE59: FALSE | AF59: No | AI59: TRUE | AJ59: 0 | AL59: ES Enterprise Solutions (Gina H.) | AM59: DA Data & AI Solutions (Ralf Fi.) | AN59: PA Platform & Application Solutions (Thomas K.) | AO59: bridgingIT GmbH | AP59: Stuttgart | AQ59: Ralf Fischer
A60: 10110 | B60: D51C2D | C60: https://app.matchical.com/Consulting/ConsultantDetail?ConsultantId=32f8ef66-15b2-40a1-b485-70771f666b13 | D60: Aram Barazandeh | E60: aram.barazandeh@bridging-it.de | F60: 45078 | G60: 40179 | H60: 11 | I60: 0 | J60: 2 | K60: 45077 | L60: 45218 | M60: 45290 | N60: FALSE | O60: 33 | P60: 65.94 | Q60: 32.82 | R60: =ROUND(O60-P60,2) | S60: =ROUND(O60-Q60,2) | T60: =IFERROR(P60/O60,"") | U60: =IFERROR(Q60/O60,"") | V60: 161 | W60: 173.06 | X60: 139.03 | Y60: =ROUND(V60-W60,2) | Z60: =ROUND(V60-X60,2) | AA60: =IFERROR(W60/V60,"") | AB60: =IFERROR(X60/V60,"") | AC60: FALSE | AD60: FALSE | AE60: FALSE | AF60: No | AI60: TRUE | AJ60: 0 | AL60: ORG bIT Bayern | AM60: LM Location Management BAY (Eli G.) | AN60: LM Lokation MUC (Elisabeth G.) | AO60: bridgingIT GmbH | AP60: München | AQ60: Elisabeth Gerlinger
A61: 1090 | B61: 29B54C | C61: https://app.matchical.com/Consulting/ConsultantDetail?ConsultantId=05c422c9-30c3-430e-bf2f-a1f614bea012 | D61: Arne Kunstmann | E61: arne.kunstmann@bridging-it.de | F61: 39722 | G61: 36861 | H61: 38 | I61: 0 | J61: 1 | K61: 45382 | L61: 45322 | M61: 45837 | N61: FALSE | O61: 209 | P61: 348 | Q61: 208.79 | R61: =ROUND(O61-P61,2) | S61: =ROUND(O61-Q61,2) | T61: =IFERROR(P61/O61,"") | U61: =IFERROR(Q61/O61,"") | V61: 94 | W61: 96 | X61: 85 | Y61: =ROUND(V61-W61,2) | Z61: =ROUND(V61-X61,2) | AA61: =IFERROR(W61/V61,"") | AB61: =IFERROR(X61/V61,"") | AC61: FALSE | AD61: FALSE | AE61: FALSE | AF61: No | AI61: TRUE | AJ61: 2 | AK61: I am seeking a project management / coordination role at a Mannheim-based account (Key/Strat) to establish a new scalable environment. Availability: 1–2.5 days per week. | AL61: T&A - Transformation & Agility (Arne K.) | AM61: TE - Transformation Enablement (Arne K.) | AN61: TB - Transforming Business (Arne K.) | AO61: bridgingIT GmbH | AP61: Mannheim | AQ61: Michael Mohrbacher
A62: 3196 | B62: 815C81 | C62: https://app.matchical.com/Consulting/ConsultantDetail?ConsultantId=2fb6e874-c310-482b-a50d-efc5ca5f539c | D62: Axel Dedio | E62: axel.dedio@bridging-it.de | F62: 43678 | G62: 43010 | H62: 11 | I62: 0 | J62: 0 | L62: 44570 | M62: 45746 | N62: FALSE | O62: 79 | P62: 111.86 | Q62: 77.52 | R62: =ROUND(O62-P62,2) | S62: =ROUND(O62-Q62,2) | T62: =IFERROR(P62/O62,"") | U62: =IFERROR(Q62/O62,"") | V62: 22 | W62: 39.93 | X62: 21.95 | Y62: =ROUND(V62-W62,2) | Z62: =ROUND(V62-X62,2) | AA62: =IFERROR(W62/V62,"") | AB62: =IFERROR(X62/V62,"") | AC62: FALSE | AD62: FALSE | AE62: FALSE | AF62: No | AI62: FALSE | AJ62: 0 | AL62: ORG bIT | AM62: SE Software Engineering Frankfurt (Sebastian F.) | AN62: ES Enterprise Solutions (Dominik H.) | AO62: bridgingIT GmbH | AP62: Frankfurt | AQ62: Sebastian Fischer
A63: 3008 | B63: F7A3CD | C63: https://app.matchical.com/Consulting/ConsultantDetail?ConsultantId=8325bd5c-d550-436e-9e73-0e1cff6b9473 | D63: Axel Pfannenschmidt | E63: axel.pfannenschmidt@bridging-it.de | F63: 39569 | G63: 33970 | H63: 68 | I63: 0 | J63: 2 | K63: 42860 | L63: 43024 | M63: 43097 | N63: FALSE | O63: 214 | P63: 358.95 | Q63: 206.24 | R63: =ROUND(O63-P63,2) | S63: =ROUND(O63-Q63,2) | T63: =IFERROR(P63/O63,"") | U63: =IFERROR(Q63/O63,"") | V63: 184 | W63: 181.05 | X63: 157.1 | Y63: =ROUND(V63-W63,2) | Z63: =ROUND(V63-X63,2) | AA63: =IFERROR(W63/V63,"") | AB63: =IFERROR(X63/V63,"") | AC63: FALSE | AD63: FALSE | AE63: FALSE | AF63: No | AG63: 42979 | AH63: 43100 | AI63: TRUE | AJ63: 2.5 | AL63: ORG bIT | AM63: PITS Professional IT-Services (Martin R.) | AN63: MIT Management of IT (Torsten R.) | AO63: bridgingIT GmbH | AP63: Frankfurt | AQ63: Martin Redemsky
A64: 10438 | B64: 74747A | C64: https://app.matchical.com/Consulting/ConsultantDetail?ConsultantId=641ddd0e-983d-4db2-afd1-3cfcd0aad469 | D64: Axel Wilkening | E64: axel.wilkening@bridging-it.de | F64: 46023 | G64: 37104 | H64: 4 | I64: 0 | J64: 1 | K64: 45565 | L64: 45535 | M64: 45807 | N64: FALSE | O64: 2 | P64: 1.69 | Q64: 1.27 | R64: =ROUND(O64-P64,2) | S64: =ROUND(O64-Q64,2) | T64: =IFERROR(P64/O64,"") | U64: =IFERROR(Q64/O64,"") | V64: 293 | W64: 64.31 | X64: 57.23 | Y64: =ROUND(V64-W64,2) | Z64: =ROUND(V64-X64,2) | AA64: =IFERROR(W64/V64,"") | AB64: =IFERROR(X64/V64,"") | AC64: FALSE | AD64: FALSE | AE64: FALSE | AF64: Yes | AG64: 46023 | AI64: TRUE | AJ64: 2.5 | AL64: IT - Information Technology (HH) | AM64: CG - Cloud Governance (Leyla V.) | AN64: ITC HH (Nicole F.) | AO64: bridgingIT GmbH | AP64: Hamburg | AQ64: Leyla Varli
A65: 10261 | B65: B01900 | C65: https://app.matchical.com/Consulting/ConsultantDetail?ConsultantId=a9bcd640-1ec5-4f08-9cba-811f00eb4c39 | D65: Barbara Vettel | E65: barbara.vettel@fastahead.com | F65: 45323 | G65: 33025 | H65: 2 | I65: 0 | J65: 0 | L65: 45481 | M65: 45657 | N65: FALSE | O65: 25 | P65: 13 | Q65: 7 | R65: =ROUND(O65-P65,2) | S65: =ROUND(O65-Q65,2) | T65: =IFERROR(P65/O65,"") | U65: =IFERROR(Q65/O65,"") | V65: 404 | W65: 0 | X65: 0 | Y65: =ROUND(V65-W65,2) | Z65: =ROUND(V65-X65,2) | AA65: =IFERROR(W65/V65,"") | AB65: =IFERROR(X65/V65,"") | AC65: FALSE | AD65: FALSE | AE65: FALSE | AF65: No | AI65: TRUE | AJ65: 0 | AL65: ORG fastahead GmbH & Co. KG | AM65: Enterprise Transformation (Dr. Barbara Vettel) | AN65: fah Dr. Barbara Vettel | AO65: fastahead GmbH & Co. KG | AP65: Mannheim | AQ65: Tim Thierfelder
A66: 1235 | B66: E0CAA3 | C66: https://app.matchical.com/Consulting/ConsultantDetail?ConsultantId=69a6dd17-3e5b-4f22-8d4b-3c8e6978d526 | D66: Bastian Trauth | E66: bastian.trauth@bridging-it.de | F66: 41487 | G66: 38201 | H66: 22 | I66: 0 | J66: 0 | L66: 45203 | M66: 45624 | N66: FALSE | O66: 151 | P66: 207 | Q66: 139 | R66: =ROUND(O66-P66,2) | S66: =ROUND(O66-Q66,2) | T66: =IFERROR(P66/O66,"") | U66: =IFERROR(Q66/O66,"") | V66: 108 | W66: 10 | X66: 7 | Y66: =ROUND(V66-W66,2) | Z66: =ROUND(V66-X66,2) | AA66: =IFERROR(W66/V66,"") | AB66: =IFERROR(X66/V66,"") | AC66: FALSE | AD66: FALSE | AE66: FALSE | AF66: No | AI66: TRUE | AJ66: 0 | AL66: T&A - Transformation & Agility (Arne K.) | AM66: TBC - Transforming Business Concepts (Bastian T.) | AN66: TBC - Transforming Business Concepts (Bastian T.) | AO66: bridgingIT GmbH | AP66: Mannheim | AQ66: Arne Kunstmann
A67: 10286 | B67: BF35A6 | C67: https://app.matchical.com/Consulting/ConsultantDetail?ConsultantId=bb5028b9-d5f1-4b6a-990d-ab5fb90a432a | D67: Batuhan Kayis | E67: batuhan.kayis@bridging-it.de | F67: 45474 | H67: 7 | I67: 0 | J67: 1 | K67: 45536 | L67: 45657 | M67: 46021 | N67: FALSE | O67: 20 | P67: 42 | Q67: 19.81 | R67: =ROUND(O67-P67,2) | S67: =ROUND(O67-Q67,2) | T67: =IFERROR(P67/O67,"") | U67: =IFERROR(Q67/O67,"") | V67: 1494 | W67: 36 | X67: 36 | Y67: =ROUND(V67-W67,2) | Z67: =ROUND(V67-X67,2) | AA67: =IFERROR(W67/V67,"") | AB67: =IFERROR(X67/V67,"") | AC67: FALSE | AD67: FALSE | AE67: FALSE | AF67: Yes | AG67: 46113 | AI67: TRUE | AJ67: 2 | AK67: Data protection Information security Testing and quality management ITSM Smart factory / MES software ERP systems | AL67: IT Information Technology (Hauke G.) | AM67: CIS Compliance & Information Security (David T.) | AN67: GRC IT-GRC (Erhan N.) | AO67: bridgingIT GmbH | AP67: Stuttgart | AQ67: David Turan
A68: 10275 | B68: D26BE8 | C68: https://app.matchical.com/Consulting/ConsultantDetail?ConsultantId=c6776445-040c-4c4b-a847-f54b1ec017b7 | D68: Ben Becker | E68: ben.becker@bridging-it.de | F68: 45474 | G68: 42186 | H68: 3 | I68: 0 | J68: 0 | L68: 44834 | M68: 45305 | N68: FALSE | O68: 20 | P68: 0 | Q68: 0 | R68: =ROUND(O68-P68,2) | S68: =ROUND(O68-Q68,2) | T68: =IFERROR(P68/O68,"") | U68: =IFERROR(Q68/O68,"") | V68: 108 | W68: 44 | X68: 16 | Y68: =ROUND(V68-W68,2) | Z68: =ROUND(V68-X68,2) | AA68: =IFERROR(W68/V68,"") | AB68: =IFERROR(X68/V68,"") | AC68: FALSE | AD68: FALSE | AE68: FALSE | AF68: No | AI68: TRUE | AJ68: 0 | AK68: Roche project. Extension is very likely. | AL68: ORG bIT | AM68: LSC - Life Science Cologne (Sascha B.) | AN68: CC Life Science Solutions (Sabine S.) | AO68: bridgingIT GmbH | AP68: Köln | AQ68: Sascha Beerhenke
A69: 10208 | B69: 37B4D2 | C69: https://app.matchical.com/Consulting/ConsultantDetail?ConsultantId=2af0bd12-3741-48ef-ba56-36724d5e8e23 | D69: Benjamin Dorp | E69: benjamin.dorp@bridging-it.de | F69: 45323 | G69: 37104 | H69: 6 | I69: 0 | J69: 1 | K69: 44563 | L69: 45691 | M69: 45838 | N69: FALSE | O69: 25 | P69: 39.4 | Q69: 22.19 | R69: =ROUND(O69-P69,2) | S69: =ROUND(O69-Q69,2) | T69: =IFERROR(P69/O69,"") | U69: =IFERROR(Q69/O69,"") | V69: 270 | W69: 65.6 | X69: 29.81 | Y69: =ROUND(V69-W69,2) | Z69: =ROUND(V69-X69,2) | AA69: =IFERROR(W69/V69,"") | AB69: =IFERROR(X69/V69,"") | AC69: FALSE | AD69: FALSE | AE69: FALSE | AF69: No | AI69: FALSE | AJ69: 0 | AK69: From March 1, deployed at REWE Digital; until then, at the Agile SPIE training sessions. | AL69: ORG bIT | AM69: AMC - Agility Masters Cologne (Severin E.) | AN69: BTC - Business Transformation Cologne (Anna S.) | AO69: bridgingIT GmbH | AP69: Köln | AQ69: Severin Etzbach
A70: 1199 | B70: 58EBAE | C70: https://app.matchical.com/Consulting/ConsultantDetail?ConsultantId=816bd6b8-8b72-4058-b556-9794d8d9a0fb | D70: Benjamin Gerlach | E70: benjamin.gerlach@bridging-it.de | F70: 41122 | G70: 40848 | H70: 11 | I70: 0 | J70: 1 | K70: 45199 | L70: 43466 | M70: 45229 | N70: FALSE | O70: 163 | P70: 340.38 | Q70: 162.79 | R70: =ROUND(O70-P70,2) | S70: =ROUND(O70-Q70,2) | T70: =IFERROR(P70/O70,"") | U70: =IFERROR(Q70/O70,"") | V70: 9 | W70: 7.75 | X70: 6.87 | Y70: =ROUND(V70-W70,2) | Z70: =ROUND(V70-X70,2) | AA70: =IFERROR(W70/V70,"") | AB70: =IFERROR(X70/V70,"") | AC70: FALSE | AD70: FALSE | AE70: FALSE | AF70: No | AI70: FALSE | AJ70: 0 | AL70: A&SE Analytics & Software Engineering (Philip R.) | AM70: DP Data Platforms (Martin K.) | AN70: A&DDS - Analytics & Data-driven Solutions (M. Hof) | AO70: bridgingIT GmbH | AP70: Mannheim | AQ70: Martin Klingenberg
A71: 10461 | B71: F02784 | C71: https://app.matchical.com/Consulting/ConsultantDetail?ConsultantId=d0b8b3e7-74af-4901-99da-e334ddb775c4 | D71: Benjamin Kaplan | E71: benjamin.kaplan@bridging-it.de | F71: 46023 | G71: 45444 | H71: 4 | I71: 0 | J71: 0 | L71: 45869 | M71: 46008 | N71: FALSE | O71: 2 | P71: 0 | Q71: 0 | R71: =ROUND(O71-P71,2) | S71: =ROUND(O71-Q71,2) | T71: =IFERROR(P71/O71,"") | U71: =IFERROR(Q71/O71,"") | V71: 19 | W71: 32.97 | X71: 19.02 | Y71: =ROUND(V71-W71,2) | Z71: =ROUND(V71-X71,2) | AA71: =IFERROR(W71/V71,"") | AB71: =IFERROR(X71/V71,"") | AC71: FALSE | AD71: FALSE | AE71: FALSE | AF71: No | AI71: TRUE | AJ71: 0 | AL71: ORG bIT | AM71: SE Software Engineering Frankfurt (Andreas M.) | AN71: ES Enterprise Solutions (Dominik H.) | AO71: bridgingIT GmbH | AP71: Frankfurt | AQ71: Andreas Morgenstern
A72: 8531 | B72: B565E9 | C72: https://app.matchical.com/Consulting/ConsultantDetail?ConsultantId=e10eded6-afe2-4056-81bd-332af82ff927 | D72: Benjamin Kühne | E72: benjamin.kuehne@crafting-it.de | F72: 43709 | G72: 36039 | H72: 8 | I72: 1 | J72: 1 | K72: 43709 | L72: 45292 | M72: 45657 | N72: FALSE | O72: 78 | P72: 130.78 | Q72: 71.89 | R72: =ROUND(O72-P72,2) | S72: =ROUND(O72-Q72,2) | T72: =IFERROR(P72/O72,"") | U72: =IFERROR(Q72/O72,"") | V72: 252 | W72: 0 | X72: 0 | Y72: =ROUND(V72-W72,2) | Z72: =ROUND(V72-X72,2) | AA72: =IFERROR(W72/V72,"") | AB72: =IFERROR(X72/V72,"") | AC72: FALSE | AD72: FALSE | AE72: FALSE | AF72: No | AI72: FALSE | AJ72: 0 | AL72: ORG cIT | AM72: cIT Development | AN72: cIT Service Delivery Magdeburg (Steffen A.) | AO72: craftingIT GmbH | AP72: Magdeburg | AQ72: Jennifer Saalfeld
A73: 10454 | B73: D57902 | C73: https://app.matchical.com/Consulting/ConsultantDetail?ConsultantId=c26478a3-16f2-4e69-9fdc-eb4396a2d889 | D73: Berkcan Dincer | E73: berkcan.dincer@bridging-it.de | F73: 46054 | G73: 42979 | H73: 3 | I73: 0 | J73: 1 | K73: 45382 | L73: 44742 | M73: 45351 | N73: FALSE | O73: 1 | P73: 0.73 | Q73: 0.73 | R73: =ROUND(O73-P73,2) | S73: =ROUND(O73-Q73,2) | T73: =IFERROR(P73/O73,"") | U73: =IFERROR(Q73/O73,"") | V73: 101 | W73: 53.27 | X73: 53.27 | Y73: =ROUND(V73-W73,2) | Z73: =ROUND(V73-X73,2) | AA73: =IFERROR(W73/V73,"") | AB73: =IFERROR(X73/V73,"") | AC73: FALSE | AD73: FALSE | AE73: FALSE | AF73: No | AI73: TRUE | AJ73: 0 | AL73: IT - Information Technology (Sebastian L.) | AM73: P&P - Processes & Platforms (Bernd O.) | AN73: P&DE - Platforms & Digital Ecosystems (David S.) | AO73: bridgingIT GmbH | AP73: Mannheim | AQ73: Bernd Opitz
A74: 1326 | B74: D1D8B1 | C74: https://app.matchical.com/Consulting/ConsultantDetail?ConsultantId=f46e8c4b-7bb8-4ca8-9400-9dd8b4f8b976 | D74: Bernd Opitz | E74: bernd.opitz@bridging-it.de | F74: 42370 | G74: 41579 | H74: 9 | I74: 0 | J74: 1 | K74: 44089 | L74: 44395 | M74: 44882 | N74: FALSE | O74: 122 | P74: 164 | Q74: 121 | R74: =ROUND(O74-P74,2) | S74: =ROUND(O74-Q74,2) | T74: =IFERROR(P74/O74,"") | U74: =IFERROR(Q74/O74,"") | V74: 26 | W74: 36 | X74: 21 | Y74: =ROUND(V74-W74,2) | Z74: =ROUND(V74-X74,2) | AA74: =IFERROR(W74/V74,"") | AB74: =IFERROR(X74/V74,"") | AC74: FALSE | AD74: FALSE | AE74: FALSE | AF74: No | AI74: FALSE | AJ74: 0 | AL74: IT - Information Technology (Sebastian L.) | AM74: P&P - Processes & Platforms (Bernd O.) | AN74: P&DE - Platforms & Digital Ecosystems (David S.) | AO74: bridgingIT GmbH | AP74: Mannheim | AQ74: David Schleweis
A75: 4145 | B75: E53BE0 | C75: https://app.matchical.com/Consulting/ConsultantDetail?ConsultantId=72b500fe-715e-49b2-abb5-d15e12fbb217 | D75: Bernhard Gebert | E75: bernhard.gebert@bridging-it.de | F75: 44743 | G75: 32387 | H75: 7 | I75: 0 | J75: 1 | K75: 45230 | L75: 44958 | M75: 45198 | N75: FALSE | O75: 44 | P75: 57.88 | Q75: 41.42 | R75: =ROUND(O75-P75,2) | S75: =ROUND(O75-Q75,2) | T75: =IFERROR(P75/O75,"") | U75: =IFERROR(Q75/O75,"") | V75: 406 | W75: 72 | X75: 72 | Y75: =ROUND(V75-W75,2) | Z75: =ROUND(V75-X75,2) | AA75: =IFERROR(W75/V75,"") | AB75: =IFERROR(X75/V75,"") | AC75: FALSE | AD75: FALSE | AE75: FALSE | AF75: Yes | AG75: 46113 | AI75: TRUE | AJ75: 2.5 | AK75: Bernhard is an experienced IT project manager in a traditional environment and, since 2020, also active in an agile context as a Scrum Master or Product Owner. Ideally, we are looking for a Scrum Master position in a scaled Agile environment with additional bIT involvement. | AL75: ORG bIT Bayern | AM75: Agile Innovation - AIN (Simon S.) | AN75: BAT Business Agility & Transformation (Marc S.) | AO75: bridgingIT GmbH | AP75: München | AQ75: Simon Sipple
A76: 5100 | B76: 03C03C | C76: https://app.matchical.com/Consulting/ConsultantDetail?ConsultantId=6e145a07-a171-4423-b165-7b1a38d3e2f5 | D76: Bernhard Ricken | E76: bernhard.ricken@bridging-it.de | F76: 44774 | G76: 33604 | H76: 21 | I76: 0 | J76: 1 | K76: 44851 | L76: 45597 | M76: 45746 | N76: FALSE | O76: 43 | P76: 88 | Q76: 41 | R76: =ROUND(O76-P76,2) | S76: =ROUND(O76-Q76,2) | T76: =IFERROR(P76/O76,"") | U76: =IFERROR(Q76/O76,"") | V76: 367 | W76: 614 | X76: 305 | Y76: =ROUND(V76-W76,2) | Z76: =ROUND(V76-X76,2) | AA76: =IFERROR(W76/V76,"") | AB76: =IFERROR(X76/V76,"") | AC76: FALSE | AD76: FALSE | AE76: FALSE | AF76: Yes | AG76: 46143 | AI76: FALSE | AJ76: 5 | AL76: ORG bIT | AM76: AAC - Advanced Automation Cologne (Claudia P.) | AN76: DPC - Datalytics & Process Cologne (Claudia P.) | AO76: bridgingIT GmbH | AP76: Köln | AQ76: Claudia Peters
A77: 8019 | B77: D13CED | C77: https://app.matchical.com/Consulting/ConsultantDetail?ConsultantId=b208234a-b5e6-4fb3-8354-7e00758d9ab3 | D77: Björn Decker | E77: bjoern.decker@crafting-it.de | F77: 41883 | G77: 38565 | H77: 10 | I77: 0 | J77: 0 | L77: 45474 | M77: 45657 | N77: FALSE | O77: 138 | P77: 84.96 | Q77: 15.76 | R77: =ROUND(O77-P77,2) | S77: =ROUND(O77-Q77,2) | T77: =IFERROR(P77/O77,"") | U77: =IFERROR(Q77/O77,"") | V77: 109 | W77: 0 | X77: 0 | Y77: =ROUND(V77-W77,2) | Z77: =ROUND(V77-X77,2) | AA77: =IFERROR(W77/V77,"") | AB77: =IFERROR(X77/V77,"") | AC77: FALSE | AD77: FALSE | AE77: FALSE | AF77: Yes | AG77: 45809 | AI77: TRUE | AJ77: 1.5 | AL77: ORG cIT | AM77: cIT AMS / GIS Services (Michael B.) | AN77: cIT Service Delivery Magdeburg (Steffen A.) | AO77: craftingIT GmbH | AP77: Magdeburg | AQ77: Michael Buchter
A78: 10447 | B78: 596316 | C78: https://app.matchical.com/Consulting/ConsultantDetail?ConsultantId=26401890-b8bb-4ff2-8f84-2fc1c93fb57e | D78: Björn Letmade | E78: bjoern.letmade@bridging-it.de | F78: 46082 | H78: 2 | I78: 0 | J78: 0 | L78: 45808 | M78: 45981 | N78: TRUE | O78: 0 | P78: 0 | Q78: 0 | R78: =ROUND(O78-P78,2) | S78: =ROUND(O78-Q78,2) | T78: =IFERROR(P78/O78,"") | U78: =IFERROR(Q78/O78,"") | V78: 1514 | W78: 42 | X78: 40 | Y78: =ROUND(V78-W78,2) | Z78: =ROUND(V78-X78,2) | AA78: =IFERROR(W78/V78,"") | AB78: =IFERROR(X78/V78,"") | AC78: FALSE | AD78: FALSE | AE78: FALSE | AF78: No | AI78: TRUE | AJ78: 0 | AL78: IT - Information Technology (HH) | AM78: CRM I - Platform Solutions & CRM (Fortunato D. D.) | AN78: BAA HH (Torben H.) | AO78: bridgingIT GmbH | AP78: Hamburg | AQ78: Fortunato Di Donato
A79: 2247 | B79: 9EDB57 | C79: https://app.matchical.com/Consulting/ConsultantDetail?ConsultantId=1146af42-eb61-4e77-b67d-c3469f16349d | D79: Bojan Jaksic | E79: bojan.jaksic@bridging-it.de | F79: 43586 | G79: 38810 | H79: 5 | I79: 0 | J79: 4 | K79: 43100 | L79: 42247 | M79: 43585 | N79: FALSE | O79: 82 | P79: 266.16 | Q79: 81.84 | R79: =ROUND(O79-P79,2) | S79: =ROUND(O79-Q79,2) | T79: =IFERROR(P79/O79,"") | U79: =IFERROR(Q79/O79,"") | V79: 157 | W79: 59.84 | X79: 41.83 | Y79: =ROUND(V79-W79,2) | Z79: =ROUND(V79-X79,2) | AA79: =IFERROR(W79/V79,"") | AB79: =IFERROR(X79/V79,"") | AC79: FALSE | AD79: FALSE | AE79: FALSE | AF79: No | AI79: FALSE | AJ79: 0 | AK79: Frontend-/Cross-Platform development (Angular/React) Software architectures Custom backend development | AL79: ES Enterprise Solutions (Gina H.) | AM79: IEM .Net II (Aleksandar B.) | AN79: IEJ Individualentwicklung JAVA (Dominik S.) | AO79: bridgingIT GmbH | AP79: Stuttgart | AQ79: Aleksandar Blagojevic
A80: 1312 | B80: D41F39 | C80: https://app.matchical.com/Consulting/ConsultantDetail?ConsultantId=d837acb2-4793-4b52-82fe-fec930285f72 | D80: Boris Bergner | E80: boris.bergner@bridging-it.de | F80: 42370 | G80: 38292 | H80: 14 | I80: 0 | J80: 4 | K80: 44098 | L80: 45962 | M80: 46022 | N80: FALSE | O80: 122 | P80: 305 | Q80: 121.79 | R80: =ROUND(O80-P80,2) | S80: =ROUND(O80-Q80,2) | T80: =IFERROR(P80/O80,"") | U80: =IFERROR(Q80/O80,"") | V80: 134 | W80: 70 | X80: 70 | Y80: =ROUND(V80-W80,2) | Z80: =ROUND(V80-X80,2) | AA80: =IFERROR(W80/V80,"") | AB80: =IFERROR(X80/V80,"") | AC80: FALSE | AD80: FALSE | AE80: FALSE | AF80: No | AI80: FALSE | AJ80: 0 | AL80: ORG bIT | AM80: QE Quality Engineering (Boris B.) | AN80: TH Transformation Hub (Ulrich W.) | AO80: bridgingIT GmbH | AP80: Frankfurt | AQ80: Ulrich Waltinger
A81: 10118 | B81: 731FD6 | C81: https://app.matchical.com/Consulting/ConsultantDetail?ConsultantId=9bbba85e-5b43-4c10-b9e8-ee12d6e93b89 | D81: Britta Manthée | E81: britta.manthee@bridging-it.de | F81: 45017 | G81: 40391 | H81: 8 | I81: 0 | J81: 0 | L81: 45382 | M81: 45776 | N81: FALSE | O81: 35 | P81: 74.77 | Q81: 34.83 | R81: =ROUND(O81-P81,2) | S81: =ROUND(O81-Q81,2) | T81: =IFERROR(P81/O81,"") | U81: =IFERROR(Q81/O81,"") | V81: 152 | W81: 78.1 | X81: 78.04 | Y81: =ROUND(V81-W81,2) | Z81: =ROUND(V81-X81,2) | AA81: =IFERROR(W81/V81,"") | AB81: =IFERROR(X81/V81,"") | AC81: FALSE | AD81: FALSE | AE81: FALSE | AF81: No | AI81: TRUE | AJ81: 0 | AK81: PO, project management, business analysis, PO coaching, business coaching | AL81: ORG bIT | AM81: AO Agile Organization (Katharina G.) | AN81: TH Transformation Hub (Ulrich W.) | AO81: bridgingIT GmbH | AP81: Frankfurt | AQ81: Katharina Gossen
A82: 7042 | B82: B2D719 | C82: https://app.matchical.com/Consulting/ConsultantDetail?ConsultantId=d12e690c-64d6-488a-8330-9403717ee828 | D82: Cansu Akdemir | E82: cansu.akdemir@bridging-it.de | F82: 44652 | G82: 44652 | H82: 8 | I82: 0 | J82: 0 | L82: 45522 | M82: 46070 | N82: FALSE | O82: 47 | P82: 85 | Q82: 46 | R82: =ROUND(O82-P82,2) | S82: =ROUND(O82-Q82,2) | T82: =IFERROR(P82/O82,"") | U82: =IFERROR(Q82/O82,"") | V82: 0 | W82: 0 | X82: 0 | Y82: =ROUND(V82-W82,2) | Z82: =ROUND(V82-X82,2) | AA82: =IFERROR(W82/V82,"") | AB82: =IFERROR(X82/V82,"") | AC82: FALSE | AD82: FALSE | AE82: FALSE | AF82: Yes | AG82: 46072 | AI82: TRUE | AJ82: 5 | AK82: Desire to switch projects Currently offered through a tender at Berliner Stadtwerke (80%-100%) | AL82: ORG bIT | AM82: A&PM Agility & Project Management (Lutz K.) | AN82: TH Transformation Hub BLN (Ulrich W.) | AO82: bridgingIT GmbH | AP82: Berlin | AQ82: Lutz Kempf
A83: 10094 | B83: 4398E3 | C83: https://app.matchical.com/Consulting/ConsultantDetail?ConsultantId=c91a7849-5fbd-4865-b716-cd3a65f5f867 | D83: Carina Zeiter | E83: carina.zeiter@bridging-it.de | F83: 45017 | G83: 43617 | H83: 8 | I83: 0 | J83: 1 | K83: 45747 | L83: 45046 | M83: 45960 | N83: FALSE | O83: 35 | P83: 58 | Q83: 34.83 | R83: =ROUND(O83-P83,2) | S83: =ROUND(O83-Q83,2) | T83: =IFERROR(P83/O83,"") | U83: =IFERROR(Q83/O83,"") | V83: 46 | W83: 66.91 | X83: 46 | Y83: =ROUND(V83-W83,2) | Z83: =ROUND(V83-X83,2) | AA83: =IFERROR(W83/V83,"") | AB83: =IFERROR(X83/V83,"") | AC83: FALSE | AD83: FALSE | AE83: FALSE | AF83: No | AI83: TRUE | AJ83: 0 | AL83: ORG bIT Bayern | AM83: Business Transformation (BT) (Stefan S.) | AN83: BAT Business Agility & Transformation (Marc S.) | AO83: bridgingIT GmbH | AP83: München | AQ83: Stefan Satzger
A84: 10404 | B84: 263682 | C84: https://app.matchical.com/Consulting/ConsultantDetail?ConsultantId=48090306-8597-43b0-8de8-cc764c0dad81 | D84: Carlo Knödler | E84: carlo.knoedler@bridging-it.de | F84: 45962 | G84: 44621 | H84: 5 | I84: 0 | J84: 0 | L84: 45961 | M84: 46022 | N84: FALSE | O84: 4 | P84: 1.97 | Q84: 1.97 | R84: =ROUND(O84-P84,2) | S84: =ROUND(O84-Q84,2) | T84: =IFERROR(P84/O84,"") | U84: =IFERROR(Q84/O84,"") | V84: 44 | W84: 42.03 | X84: 37.03 | Y84: =ROUND(V84-W84,2) | Z84: =ROUND(V84-X84,2) | AA84: =IFERROR(W84/V84,"") | AB84: =IFERROR(X84/V84,"") | AC84: FALSE | AD84: FALSE | AE84: FALSE | AF84: Yes | AG84: 46143 | AI84: TRUE | AJ84: 5 | AK84: Carlo is an experienced innovation manager, Product Owner, and project manager (small-scale, hybrid, agile). His strength lies in bridging the worlds of development and business. He is willing to travel — also happy to work in the Düsseldorf area. If applicable, a part-time project also makes sense, as we plan to place Carlo at SPIE in ARENA2036. | AL84: DO Digital Organizations (Michael H.) | AM84: BT Business Transform. II (Patrick D.) | AN84: BT Business Transformation (Julian D.) | AO84: bridgingIT GmbH | AP84: Stuttgart | AQ84: Patrick Dehner
A85: 2318 | B85: 264F66 | C85: https://app.matchical.com/Consulting/ConsultantDetail?ConsultantId=d56a1ffc-1098-47e9-ba04-7a5d1f7545e1 | D85: Carmen Deubelbeiss | E85: carmen.deubelbeiss@bridging-it.de | F85: 44835 | G85: 36526 | H85: 12 | I85: 0 | J85: 3 | K85: 38776 | L85: 45586 | M85: 46022 | N85: FALSE | O85: 41 | P85: 133.62 | Q85: 40.8 | R85: =ROUND(O85-P85,2) | S85: =ROUND(O85-Q85,2) | T85: =IFERROR(P85/O85,"") | U85: =IFERROR(Q85/O85,"") | V85: 273 | W85: 264.38 | X85: 185.59 | Y85: =ROUND(V85-W85,2) | Z85: =ROUND(V85-X85,2) | AA85: =IFERROR(W85/V85,"") | AB85: =IFERROR(X85/V85,"") | AC85: FALSE | AD85: FALSE | AE85: FALSE | AF85: No | AI85: TRUE | AJ85: 0 | AK85: Experienced project manager with international leadership experience. Delivery of complex IT transformation projects. The focus is on traditional and agile methodologies, as well as stakeholder, risk, and change management. | AL85: IT Information Technology (Hauke G.) | AM85: ITT IT-Transformation (Carmen D.) | AN85: ITM IT-Management (Jörg M.) | AO85: bridgingIT GmbH | AP85: Stuttgart | AQ85: Jörg Merz
A86: 1209 | B86: 4EF376 | C86: https://app.matchical.com/Consulting/ConsultantDetail?ConsultantId=4b5394a3-f6fa-49dd-99d1-2252e2521884 | D86: Carsten Christoph | E86: carsten.christoph@bridging-it.de | F86: 41183 | G86: 37987 | H86: 32 | I86: 0 | J86: 5 | K86: 43793 | L86: 45215 | M86: 45291 | N86: FALSE | O86: 161 | P86: 389.77 | Q86: 160.79 | R86: =ROUND(O86-P86,2) | S86: =ROUND(O86-Q86,2) | T86: =IFERROR(P86/O86,"") | U86: =IFERROR(Q86/O86,"") | V86: 105 | W86: 90.23 | X86: 68.4 | Y86: =ROUND(V86-W86,2) | Z86: =ROUND(V86-X86,2) | AA86: =IFERROR(W86/V86,"") | AB86: =IFERROR(X86/V86,"") | AC86: FALSE | AD86: FALSE | AE86: FALSE | AF86: No | AI86: FALSE | AJ86: 0 | AK86: Lead: Process digitization at Uniklinikum Ulm | AL86: DO Digital Organizations (Michael H.) | AM86: PD Process Digitalization (Hermann L.) | AN86: DP Digital Processes (Hermann L.) | AO86: bridgingIT GmbH | AP86: Stuttgart | AQ86: Hermann Löh
A87: 1285 | B87: ABB94D | C87: https://app.matchical.com/Consulting/ConsultantDetail?ConsultantId=8734ba8b-24ce-4601-b44d-c05e05814ea9 | D87: Carsten Juretzka | E87: carsten.juretzka@bridging-it.de | F87: 42036 | G87: 41974 | H87: 17 | I87: 0 | J87: 5 | K87: 41671 | L87: 44743 | M87: 44926 | N87: FALSE | O87: 133 | P87: 584.99 | Q87: 132.76 | R87: =ROUND(O87-P87,2) | S87: =ROUND(O87-Q87,2) | T87: =IFERROR(P87/O87,"") | U87: =IFERROR(Q87/O87,"") | V87: 2 | W87: 2.04 | X87: 0.75 | Y87: =ROUND(V87-W87,2) | Z87: =ROUND(V87-X87,2) | AA87: =IFERROR(W87/V87,"") | AB87: =IFERROR(X87/V87,"") | AC87: FALSE | AD87: FALSE | AE87: FALSE | AF87: No | AI87: FALSE | AJ87: 0 | AL87: IT - Information Technology (Sebastian L.) | AM87: CS Collaboration Solutions (Sebastian P.) | AN87: P&DE - Platforms & Digital Ecosystems (David S.) | AO87: bridgingIT GmbH | AP87: Mannheim | AQ87: Sebastian Poth
A88: 3127 | B88: F79411 | C88: https://app.matchical.com/Consulting/ConsultantDetail?ConsultantId=a5bc6907-1256-4673-9616-659aef794b54 | D88: Carsten Schindler | E88: carsten.schindler@bridging-it.de | F88: 42675 | G88: 40940 | H88: 28 | I88: 0 | J88: 0 | L88: 45596 | M88: 45746 | N88: FALSE | O88: 112 | P88: 184 | Q88: 106.33 | R88: =ROUND(O88-P88,2) | S88: =ROUND(O88-Q88,2) | T88: =IFERROR(P88/O88,"") | U88: =IFERROR(Q88/O88,"") | V88: 57 | W88: 38 | X88: 36 | Y88: =ROUND(V88-W88,2) | Z88: =ROUND(V88-X88,2) | AA88: =IFERROR(W88/V88,"") | AB88: =IFERROR(X88/V88,"") | AC88: FALSE | AD88: FALSE | AE88: FALSE | AF88: Yes | AG88: 46113 | AI88: TRUE | AJ88: 1.5 | AL88: ORG bIT | AM88: BABA - BA and Business Architectures (Carsten S.) | AN88: ABC Analysing Business & Collaboration (Edgar K.) | AO88: bridgingIT GmbH | AP88: Frankfurt | AQ88: Edgar Kauz
A89: 1132 | B89: ED553A | C89: https://app.matchical.com/Consulting/ConsultantDetail?ConsultantId=09d6bbc6-82e6-4998-a62f-9a24af3f8718 | D89: Carsten Triebel | E89: carsten.triebel@bridging-it.de | F89: 40391 | G89: 39448 | H89: 33 | I89: 0 | J89: 1 | K89: 45383 | L89: 45509 | M89: 45657 | N89: FALSE | O89: 187 | P89: 371.76 | Q89: 186.81 | R89: =ROUND(O89-P89,2) | S89: =ROUND(O89-Q89,2) | T89: =IFERROR(P89/O89,"") | U89: =IFERROR(Q89/O89,"") | V89: 31 | W89: 9.04 | X89: 8.15 | Y89: =ROUND(V89-W89,2) | Z89: =ROUND(V89-X89,2) | AA89: =IFERROR(W89/V89,"") | AB89: =IFERROR(X89/V89,"") | AC89: FALSE | AD89: FALSE | AE89: FALSE | AF89: No | AI89: FALSE | AJ89: 0 | AK89: @EnBW, BASF, Roche, 5 days per week | AL89: IT - Information Technology (Sebastian L.) | AM89: ISM Information Security Management (Carsten T.) | AN89: O&G - Organization & Governance (Carsten T.) | AO89: bridgingIT GmbH | AP89: Mannheim | AQ89: Sebastian Lenhard
A90: 10436 | B90: 185BD7 | C90: https://app.matchical.com/Consulting/ConsultantDetail?ConsultantId=de025ebe-2a58-4d71-9c63-7e8abfff83dd | D90: Chang Truong | E90: chang.truong@bridging-it.de | F90: 46054 | G90: 45170 | H90: 2 | I90: 0 | J90: 0 | L90: 45596 | M90: 45837 | N90: FALSE | O90: 1 | P90: 0 | Q90: 0 | R90: =ROUND(O90-P90,2) | S90: =ROUND(O90-Q90,2) | T90: =IFERROR(P90/O90,"") | U90: =IFERROR(Q90/O90,"") | V90: 29 | W90: 21.98 | X90: 21.98 | Y90: =ROUND(V90-W90,2) | Z90: =ROUND(V90-X90,2) | AA90: =IFERROR(W90/V90,"") | AB90: =IFERROR(X90/V90,"") | AC90: FALSE | AD90: FALSE | AE90: FALSE | AF90: No | AI90: TRUE | AJ90: 0 | AK90: UX Lead | AL90: IT - Information Technology (HH) | AM90: DAI - Data Analytics & KI (Julia Sch.) | AN90: ITC HH (Nicole F.) | AO90: bridgingIT GmbH | AP90: Hamburg | AQ90: Markus Stefan
A91: 10476 | B91: DFEE1A | C91: https://app.matchical.com/Consulting/ConsultantDetail?ConsultantId=2c251782-11ff-403b-be47-dd80560c014e | D91: Christian Breitenstrom | E91: christian.breitenstrom@bridging-it.de | F91: 46082 | H91: 0 | I91: 0 | J91: 0 | N91: TRUE | O91: 0 | P91: 0 | Q91: 0 | R91: =ROUND(O91-P91,2) | S91: =ROUND(O91-Q91,2) | T91: =IFERROR(P91/O91,"") | U91: =IFERROR(Q91/O91,"") | V91: 1514 | W91: 0 | X91: 0 | Y91: =ROUND(V91-W91,2) | Z91: =ROUND(V91-X91,2) | AA91: =IFERROR(W91/V91,"") | AB91: =IFERROR(X91/V91,"") | AC91: FALSE | AD91: FALSE | AE91: FALSE | AF91: Yes | AG91: 46082 | AI91: TRUE | AJ91: 5 | AL91: IT - Information Technology (Sebastian L.) | AM91: CS - Cyber Security (Jochen Ka.) | AN91: O&G - Organization & Governance (Carsten T.) | AO91: bridgingIT GmbH | AP91: Mannheim | AQ91: Jochen Kauba
A92: 1366 | B92: 5B6659 | C92: https://app.matchical.com/Consulting/ConsultantDetail?ConsultantId=8f17969e-9ddc-400c-aa5c-f49d42323461 | D92: Christian Ewen | E92: christian.ewen@bridging-it.de | F92: 42644 | G92: 41365 | H92: 20 | I92: 1 | J92: 3 | K92: 45199 | L92: 43830 | M92: 45746 | N92: FALSE | O92: 113 | P92: 308 | Q92: 112.79 | R92: =ROUND(O92-P92,2) | S92: =ROUND(O92-Q92,2) | T92: =IFERROR(P92/O92,"") | U92: =IFERROR(Q92/O92,"") | V92: 42 | W92: 81.97 | X92: 36.99 | Y92: =ROUND(V92-W92,2) | Z92: =ROUND(V92-X92,2) | AA92: =IFERROR(W92/V92,"") | AB92: =IFERROR(X92/V92,"") | AC92: FALSE | AD92: FALSE | AE92: FALSE | AF92: No | AI92: TRUE | AJ92: 0 | AL92: IT - Information Technology (Sebastian L.) | AM92: PAM Platform Architecture Management (David S.) | AN92: P&DE - Platforms & Digital Ecosystems (David S.) | AO92: bridgingIT GmbH | AP92: Mannheim | AQ92: David Schleweis
A93: 1116 | B93: 7B5FFB | C93: https://app.matchical.com/Consulting/ConsultantDetail?ConsultantId=14cb41a6-3a0a-41f6-99d6-3a11a6116b9a | D93: Christian Gitte | E93: christian.gitte@fastahead.com | F93: 40148 | G93: 36404 | H93: 12 | I93: 0 | J93: 1 | K93: 45824 | L93: 45716 | M93: 45960 | N93: FALSE | O93: 195 | P93: 141.92 | Q93: 107.92 | R93: =ROUND(O93-P93,2) | S93: =ROUND(O93-Q93,2) | T93: =IFERROR(P93/O93,"") | U93: =IFERROR(Q93/O93,"") | V93: 123 | W93: 9.08 | X93: 9.08 | Y93: =ROUND(V93-W93,2) | Z93: =ROUND(V93-X93,2) | AA93: =IFERROR(W93/V93,"") | AB93: =IFERROR(X93/V93,"") | AC93: FALSE | AD93: FALSE | AE93: FALSE | AF93: No | AI93: FALSE | AJ93: 0 | AK93: Remote / Karlsruhe and surrounding area ***From January 2025*** | AL93: ORG fastahead GmbH & Co. KG | AM93: Business-driven Architectures (Dr. C. Gitte) | AN93: fah Tim Thierfelder | AO93: fastahead GmbH & Co. KG | AP93: Mannheim | AQ93: Tim Thierfelder
A94: 10445 | B94: 548D7C | C94: https://app.matchical.com/Consulting/ConsultantDetail?ConsultantId=eecb8af4-bbb2-4e38-b609-457b332b9b3b | D94: Christian Graml | E94: christian.graml@bridging-it.de | F94: 46023 | G94: 43435 | H94: 2 | I94: 0 | J94: 0 | L94: 45473 | M94: 46021 | N94: FALSE | O94: 2 | P94: 0 | Q94: 0 | R94: =ROUND(O94-P94,2) | S94: =ROUND(O94-Q94,2) | T94: =IFERROR(P94/O94,"") | U94: =IFERROR(Q94/O94,"") | V94: 85 | W94: 64 | X94: 63 | Y94: =ROUND(V94-W94,2) | Z94: =ROUND(V94-X94,2) | AA94: =IFERROR(W94/V94,"") | AB94: =IFERROR(X94/V94,"") | AC94: FALSE | AD94: FALSE | AE94: FALSE | AF94: Yes | AG94: 46023 | AH94: 46387 | AI94: TRUE | AJ94: 5 | AL94: IT - Information Technology (HH) | AM94: CRM I - Platform Solutions & CRM (Fortunato D. D.) | AN94: BAA HH (Torben H.) | AO94: bridgingIT GmbH | AP94: Hamburg | AQ94: Fortunato Di Donato
A95: 10479 | B95: D2B125 | C95: https://app.matchical.com/Consulting/ConsultantDetail?ConsultantId=119334c6-cb7c-430c-8f95-0f36c9aa4911 | D95: Christian Ikier | E95: christian.ikier@bridging-it.de | F95: 46113 | H95: 0 | I95: 0 | J95: 0 | N95: TRUE | O95: 0 | P95: 0 | Q95: 0 | R95: =ROUND(O95-P95,2) | S95: =ROUND(O95-Q95,2) | T95: =IFERROR(P95/O95,"") | U95: =IFERROR(Q95/O95,"") | V95: 1515 | W95: 0 | X95: 0 | Y95: =ROUND(V95-W95,2) | Z95: =ROUND(V95-X95,2) | AA95: =IFERROR(W95/V95,"") | AB95: =IFERROR(X95/V95,"") | AC95: FALSE | AD95: FALSE | AE95: FALSE | AF95: Yes | AG95: 46113 | AI95: TRUE | AJ95: 5 | AL95: DO Digital Organizations (Michael H.) | AM95: BPE Business Process Excellence (Heidi F.) | AN95: BE Business Engineering (Heidi Foldenauer) | AO95: bridgingIT GmbH | AP95: Stuttgart | AQ95: Heidi Foldenauer
A96: 8665 | B96: 9C5A7E | C96: https://app.matchical.com/Consulting/ConsultantDetail?ConsultantId=5e0168a5-2ec8-4f32-9b63-aeacd2e36558 | D96: Christian Kobl | E96: christian.kobl@crafting-it.de | F96: 44197 | H96: 1 | I96: 0 | J96: 0 | L96: 45292 | M96: 45403 | N96: FALSE | O96: 62 | P96: 4 | Q96: 4 | R96: =ROUND(O96-P96,2) | S96: =ROUND(O96-Q96,2) | T96: =IFERROR(P96/O96,"") | U96: =IFERROR(Q96/O96,"") | V96: 1452 | W96: 0 | X96: 0 | Y96: =ROUND(V96-W96,2) | Z96: =ROUND(V96-X96,2) | AA96: =IFERROR(W96/V96,"") | AB96: =IFERROR(X96/V96,"") | AC96: FALSE | AD96: FALSE | AE96: FALSE | AF96: No | AI96: TRUE | AJ96: 0 | AL96: ORG cIT 2 | AM96: cIT Product Ownership Managed Services | AN96: cIT Services allgemein (Christian K.) | AO96: craftingIT GmbH | AP96: München | AQ96: Klaus Baumgärtner
A97: 1076 | B97: C792E8 | C97: https://app.matchical.com/Consulting/ConsultantDetail?ConsultantId=8275f11d-2bdf-4896-94ed-4c8f9d9591c3 | D97: Christian Will | E97: christian.will@bridging-it.de | F97: 39569 | G97: 35096 | H97: 13 | I97: 0 | J97: 2 | K97: 44108 | L97: 44562 | M97: 45106 | N97: FALSE | O97: 214 | P97: 178 | Q97: 101 | R97: =ROUND(O97-P97,2) | S97: =ROUND(O97-Q97,2) | T97: =IFERROR(P97/O97,"") | U97: =IFERROR(Q97/O97,"") | V97: 147 | W97: 0 | X97: 0 | Y97: =ROUND(V97-W97,2) | Z97: =ROUND(V97-X97,2) | AA97: =IFERROR(W97/V97,"") | AB97: =IFERROR(X97/V97,"") | AC97: FALSE | AD97: FALSE | AE97: FALSE | AF97: No | AI97: TRUE | AJ97: 0 | AK97: - Key skills: C# / .NET, Fullstack, architecture, Cloud (preferably Azure) | AL97: A&SE Analytics & Software Engineering (Philip R.) | AM97: NET .NET Software Engineering (Christian Wi.) | AN97: FUN Fullstack Ninjas (Stefan Z.) | AO97: bridgingIT GmbH | AP97: Mannheim | AQ97: Stefan Zilch
A98: 1214 | B98: F03DAE | C98: https://app.matchical.com/Consulting/ConsultantDetail?ConsultantId=e0c6d5c4-673d-49d7-aca3-75a9539000ec | D98: Christian Wolf | E98: christian.wolf@bridging-it.de | F98: 41306 | G98: 38353 | H98: 37 | I98: 0 | J98: 0 | L98: 45170 | M98: 45291 | N98: FALSE | O98: 157 | P98: 173.93 | Q98: 124.15 | R98: =ROUND(O98-P98,2) | S98: =ROUND(O98-Q98,2) | T98: =IFERROR(P98/O98,"") | U98: =IFERROR(Q98/O98,"") | V98: 97 | W98: 163.07 | X98: 78.1 | Y98: =ROUND(V98-W98,2) | Z98: =ROUND(V98-X98,2) | AA98: =IFERROR(W98/V98,"") | AB98: =IFERROR(X98/V98,"") | AC98: FALSE | AD98: FALSE | AE98: FALSE | AF98: No | AI98: TRUE | AJ98: 0 | AL98: IT - Information Technology (Sebastian L.) | AM98: ESM Enterprise Service Management (Christian Wo.) | AN98: C&DO - Cloud & DevOps (Sebastian L.) | AO98: bridgingIT GmbH | AP98: Mannheim | AQ98: Sebastian Lenhard
A99: 2160 | B99: ACD0B6 | C99: https://app.matchical.com/Consulting/ConsultantDetail?ConsultantId=ed7e6cc0-8d97-4a87-9b60-bff9f8c16312 | D99: Christian Zeh | E99: christian.zeh@bridging-it.de | F99: 42644 | G99: 32660 | H99: 15 | I99: 0 | J99: 2 | K99: 44652 | L99: 45201 | M99: 45688 | N99: FALSE | O99: 113 | P99: 209.85 | Q99: 109.58 | R99: =ROUND(O99-P99,2) | S99: =ROUND(O99-Q99,2) | T99: =IFERROR(P99/O99,"") | U99: =IFERROR(Q99/O99,"") | V99: 328 | W99: 17 | X99: 17 | Y99: =ROUND(V99-W99,2) | Z99: =ROUND(V99-X99,2) | AA99: =IFERROR(W99/V99,"") | AB99: =IFERROR(X99/V99,"") | AC99: FALSE | AD99: FALSE | AE99: FALSE | AF99: No | AI99: FALSE | AJ99: 0 | AK99: Merck K2, 90%, Hermann Löh, 12/10/2018 (high probability of extension) | AL99: DO Digital Organizations (Michael H.) | AM99: PD Process Digitalization (Hermann L.) | AN99: DP Digital Processes (Hermann L.) | AO99: bridgingIT GmbH | AP99: Stuttgart | AQ99: Hermann Löh
A100: 10060 | B100: C2068F | C100: https://app.matchical.com/Consulting/ConsultantDetail?ConsultantId=b662a0de-1154-4fe1-8c6e-f42698d06b57 | D100: Christine Klaus | E100: christine.klaus@bridging-it.de | F100: 44958 | G100: 40940 | H100: 5 | I100: 0 | J100: 0 | L100: 45291 | M100: 45442 | N100: FALSE | O100: 37 | P100: 18.95 | Q100: 16.55 | R100: =ROUND(O100-P100,2) | S100: =ROUND(O100-Q100,2) | T100: =IFERROR(P100/O100,"") | U100: =IFERROR(Q100/O100,"") | V100: 132 | W100: 101.05 | X100: 59.45 | Y100: =ROUND(V100-W100,2) | Z100: =ROUND(V100-X100,2) | AA100: =IFERROR(W100/V100,"") | AB100: =IFERROR(X100/V100,"") | AC100: FALSE | AD100: FALSE | AE100: FALSE | AF100: Yes | AG100: 46113 | AI100: TRUE | AJ100: 2.5 | AK100: BASF preliminary design until the end of March ’26. Extension likely. | AL100: ORG bIT | AM100: LSC - Life Science Cologne (Sascha B.) | AN100: CC Life Science Solutions (Sabine S.) | AO100: bridgingIT GmbH | AP100: Köln | AQ100: Sascha Beerhenke
...

Sheet Lists
A1: Metric_type | B1: Department | C1: Team | D1: Unit | E1: Legal_entity | F1: Location | G1: Lead | H1: Is_available | I1: Segment_dimension
A2: Weighted | B2: All | C2: All | D2: All | E2: All | F2: All | G2: All | H2: All | I2: Department
A3: Absolute | B3: A&SE Analytics & Software Engineering (Philip R.) | C3: A&PM Agility & Project Management (Lutz K.) | D3: A&DDS - Analytics & Data-driven Solutions (M. Hof) | E3: bridgingIT GmbH | F3: Berlin | G3: Aleksandar Blagojevic | H3: - | I3: Team
B4: BusDev | C4: AAC - Advanced Automation Cologne (Claudia P.) | D4: A&PM Agility & Project Management (Jan H.) | E4: craftingIT GmbH | F4: Frankfurt | G4: Alexander Jende | H4: No | I4: Unit
B5: DO Digital Organizations (Michael H.) | C5: AI Artificial Intelligence (Philip R.) | D5: A&SE Analytics & Software Engineering (Philip R.) | E5: fastahead GmbH & Co. KG | F5: Hamburg | G5: Anastasia Rettberg-Kluter | H5: Yes | I5: Legal entity
B6: ES Enterprise Solutions (Gina H.) | C6: AM IT-Architecture Management (Wilfried W.) | D6: ABC Analysing Business & Collab. BLN (Edgar K.) | F6: Karlsruhe | G6: Andreas Glasa | I6: Location
B7: ES Enterprise Solutions BLN (Gina H.) | C7: AMC - Agility Masters Cologne (Severin E.) | D7: ABC Analysing Business & Collaboration (Edgar K.) | F7: Köln | G7: Andreas Kernbach | I7: Lead
B8: Geschäftsleitung und Support | C8: AO Agile Organization (Katharina G.) | D8: BAA HH (Torben H.) | F8: Magdeburg | G8: Andreas Morgenstern
B9: IT - Information Technology (HH) | C9: AO Agile Organizations (Andreas G.) | D9: BAT Business Agility & Transformation (Marc S.) | F9: Mannheim | G9: Anna Schnorrenberger
B10: IT - Information Technology (Sebastian L.) | C10: AT Agile Transformation (Anna S.) | D10: BE Business Engineering (Heidi Foldenauer) | F10: München | G10: Arne Kunstmann
B11: IT Information Technology (Hauke G.) | C11: Agile Innovation - AIN (Simon S.) | D11: BPD Business Processes & Data Engineering(Arne K.) | F11: Nürnberg | G11: Barbara Vettel
B12: ORG bIT | C12: BA - Business Applications (Hamed S.) | D12: BT Business Transformation (Julian D.) | F12: Stuttgart | G12: Bastian Trauth
B13: ORG bIT Bayern | C13: BAA Business Analysis & Architecture (Viktor P.) | D13: BTC - Business Transformation Cologne (Anna S.) | G13: Bernd Opitz
B14: ORG cIT | C14: BAAM - Management (Torben H.) | D14: BW Expertenteams | G14: Boris Bergner
B15: ORG cIT 2 | C15: BABA - BA and Business Architectures (Carsten S.) | D15: C&DO - Cloud & DevOps (Sebastian L.) | G15: Carmen Deubelbeiss
B16: ORG fastahead GmbH & Co. KG | C16: BABC - BA and Business Complexity (Karola B.) | D16: CC Life Science Solutions (Sabine S.) | G16: Carsten Schindler
B17: POR BL | C17: BABC - BA and Business Complexity BLN (Karola B.) | D17: CEO | G17: Carsten Triebel
B18: Sales BL | C18: BAPO - BA and Product Ownership (Edgar K.) | D18: COO | G18: Christian Gitte
B19: T&A - Transformation & Agility (Arne K.) | C19: BPE Business Process Excellence (Heidi F.) | D19: Capability Management (Tim T.) | G19: Christian Kobl
B20: TPD cIT - BL Third Party Delivery (Christian K.) | C20: BT Business Transform. II (Patrick D.) | D20: DO Line Management (Michael H.) | G20: Christian Will
C21: BT Business Transform. III (Valerie L.) | D21: DP Digital Processes (Hermann L.) | G21: Christian Wolf
C22: BT Unit Management (Julian D.) | D22: DPC - Datalytics & Process Cologne (Claudia P.) | G22: Christoph Müller
C23: Banking (R. Weygand) | D23: ES Enterprise Solutions (Dominik H.) | G23: Christoph Wudtke
C24: Business Agility & Transformation - Management | D24: ES Line Management (Gina H.) | G24: Christopher Schweinsteiger
C25: Business Transformation (BT) (Stefan S.) | D25: FUN Fullstack Ninjas (Stefan Z.) | G25: Claudia Peters
C26: Business-driven Architectures (Dr. C. Gitte) | D26: Frank Wallner | G26: Clemens Lindner
C27: CC Content & Collaboration (Frank G.) | D27: GRC IT-GRC (Erhan N.) | G27: Dana Thüring
C28: CDC - Cloud & DevOps Cologne (Henning F.) | D28: IEJ Individualentwicklung JAVA (Dominik S.) | G28: Daniel Rheinwalt
C29: CDI Cloud DevOps & IT-Architecture (Tim J.) | D29: IT Information Technology (Sebastian L.) | G29: David Schleweis
C30: CG - Cloud Governance (Leyla V.) | D30: IT Line-Management (Hauke G.) | G30: David Turan
C31: CIS Compliance & Information Security (David T.) | D31: ITBLM - Management (Markus S.) | G31: Dean Herzog-Meijer
C32: CRM I - Platform Solutions & CRM (Fortunato D. D.) | D32: ITC HH (Nicole F.) | G32: Diana Gülker
... C67: IEM .Net II (Aleksandar B.) | D67: fah Tim Thierfelder | G67: Marc Schmitt
C68: IPM - IT PM (Peter T.) | G68: Marcel Kelle
C69: ISM Information Security Management (Carsten T.) | G69: Marita Dorscheid
C70: IT Line Management (Hauke G.) | G70: Markus Stefan
C71: IT-Strategy & EAM (D. Rheinwalt) | G71: Martin Klingenberg
C72: IT-Transition (D. Rheinwalt) | G72: Martin Kuck
C73: ITBLM - Management (Markus S.) | G73: Martin Redemsky
C74: ITCM - Management (Nicole F.) | G74: Martin Spörl
C75: ITM Unit Management (Jörg M.) | G75: Matthias Hetz
C76: ITPM IT Projectmanagement (Torsten R.) | G76: Michael Buchter
C77: ITS IT Security (Erhan N.) | G77: Michael Hagenlocher
C78: ITT IT Transition & Transformation (Michael M.) | G78: Michael Hof
C79: ITT IT-Transformation (Carmen D.) | G79: Michael Mohrbacher
... C126: SHH Standort Hamburg (Claudia P.) | G126: Wilfried Wessel
C127: SHH Standort Hamburg (Ulf L.)
C128: Sales Office EnBW
C129: Strategy and Transformation (P. Seelmeyer)
C130: Support Externe Partner
C131: TBC - Transforming Business Concepts (Bastian T.)
C132: TE - Transformation Enablement (Arne K.)
C133: TG Transformation Guidance (Clemens L.)
C134: TM - Transition Management (Christoph W.)
C135: Thomas Arens
C136: Tim Thierfelder
C137: User Experience Design
C138: Zentrales Sales Office (Miriam H.)
... C146: cIT TPM

Sheet Model
A1: Include | B1: Selected_ratio_since | C1: Selected_ratio_before | D1: Ongoing_age_months | E1: Availability_inconsistency | F1: Anomaly_flag | G1: Segment_value | H1: Low_coverage_flag | I1: Anomaly_score | J1: Candidate_segment | K1: Candidate_total | L1: Candidate_low | M1: Candidate_low_rate | N1: Candidate_rank_key | O1: Top_segment | P1: Top_low_rate | Q1: Top_count | R1: Rank_key | S1: Selected_since_included | T1: Selected_before_included | U1: Weighted_since_included | V1: Weighted_before_included
A2: =--(AND(OR(Dashboard!$B$4="All",Raw_data!$AL2=Dashboard!$B$4),OR(Dashboard!$B$5="All",Raw_data!$AM2=Dashboard!$B$5),OR(Dashboard!$B$6="All",Raw_data!$AN2=Dashboard!$B$6),OR(Dashboard!$B$7="All",Raw_data!$AO2=Dashboard!$B$7),OR(Dashboard!$B$8="All",Raw_data!$AP2=Dashboard!$B$8),OR(Dashboard!$B$9="All",Raw_data!$AQ2=Dashboard!$B$9),OR(Dashboard!$B$10="All",Raw_data!$AF2=Dashboard!$B$10),OR(Raw_data!$F2="",Raw_data!$F2<=TODAY()))) | B2: =IFERROR(IF(Dashboard!$B$3="Weighted",Raw_data!$U2,Raw_data!$T2),"") | C2: =IFERROR(IF(Dashboard!$B$3="Weighted",Raw_data!$AB2,Raw_data!$AA2),"") | D2: =IF(OR(Raw_data!$J2="",Raw_data!$J2<=0,Raw_data!$K2=""),"",IF(Raw_data!$K2>TODAY(),0,DATEDIF(Raw_data!$K2,TODAY(),"M"))) | E2: =--(AND(Raw_data!$AF2="No",OR(Raw_data!$AG2<>"",Raw_data!$AJ2>0,Raw_data!$AK2<>""))) | F2: =--(OR(AND(ISNUMBER(B2),B2<0.5,OR(D2>=24,Raw_data!$I2>0)),Raw_data!$AE2=TRUE)) | G2: =IF(Dashboard!$B$11="Department",Raw_data!$AL2,IF(Dashboard!$B$11="Team",Raw_data!$AM2,IF(Dashboard!$B$11="Unit",Raw_data!$AN2,IF(Dashboard!$B$11="Legal entity",Raw_data!$AO2,IF(Dashboard!$B$11="Location",Raw_data!$AP2,Raw_data!$AQ2))))) | H2: =--(AND(ISNUMBER(B2),B2<0.5)) | I2: =IFERROR(MAX(0,(0.5-B2)*100),0)+IF(D2>=24,20,0)+IF(Raw_data!$I2>0,20,0)+IF(Raw_data!$AE2=TRUE,10,0) | J2: =IFERROR(CHOOSE(MATCH(Dashboard!$B$11,{"Department","Team","Unit","Legal entity","Location","Lead"},0),INDEX(Lists!$B$3:$B$20,ROW()-1),INDEX(Lists!$C$3:$C$146,ROW()-1),INDEX(Lists!$D$3:$D$67,ROW()-1),INDEX(Lists!$E$3:$E$5,ROW()-1),INDEX(Lists!$F$3:$F$12,ROW()-1),INDEX(Lists!$G$3:$G$126,ROW()-1)),"") | K2: =IF(J2="","",SUMPRODUCT(($A$2:$A$636=1)*($G$2:$G$636=J2))) | L2: =IF(J2="","",SUMPRODUCT(($A$2:$A$636=1)*($G$2:$G$636=J2)*(ISNUMBER($B$2:$B$636))*($B$2:$B$636<0.5))) | M2: =IFERROR(L2/K2,"") | N2: =IF(K2="","",M2+K2/100000+ROW()/100000000) | O2: =IFERROR(INDEX($J$2:$J$1001,MATCH(LARGE($N$2:$N$1001,1),$N$2:$N$1001,0)),"") | P2: =IFERROR(INDEX($M$2:$M$1001,MATCH(LARGE($N$2:$N$1001,1),$N$2:$N$1001,0)),"") | Q2: =IFERROR(INDEX($K$2:$K$1001,MATCH(LARGE($N$2:$N$1001,1),$N$2:$N$1001,0)),"") | R2: =IF(A2=1,IFERROR(I2,0)+ROW()/100000000,-1E+99) | S2: =IF(A2=1,IFERROR(Raw_data!$T2,""),"") | T2: =IF(A2=1,IFERROR(Raw_data!$AA2,""),"") | U2: =IF(A2=1,IFERROR(Raw_data!$U2,""),"") | V2: =IF(A2=1,IFERROR(Raw_data!$AB2,""),"")
A3: =--(AND(OR(Dashboard!$B$4="All",Raw_data!$AL3=Dashboard!$B$4),OR(Dashboard!$B$5="All",Raw_data!$AM3=Dashboard!$B$5),OR(Dashboard!$B$6="All",Raw_data!$AN3=Dashboard!$B$6),OR(Dashboard!$B$7="All",Raw_data!$AO3=Dashboard!$B$7),OR(Dashboard!$B$8="All",Raw_data!$AP3=Dashboard!$B$8),OR(Dashboard!$B$9="All",Raw_data!$AQ3=Dashboard!$B$9),OR(Dashboard!$B$10="All",Raw_data!$AF3=Dashboard!$B$10),OR(Raw_data!$F3="",Raw_data!$F3<=TODAY()))) | B3: =IFERROR(IF(Dashboard!$B$3="Weighted",Raw_data!$U3,Raw_data!$T3),"") | C3: =IFERROR(IF(Dashboard!$B$3="Weighted",Raw_data!$AB3,Raw_data!$AA3),"") | D3: =IF(OR(Raw_data!$J3="",Raw_data!$J3<=0,Raw_data!$K3=""),"",IF(Raw_data!$K3>TODAY(),0,DATEDIF(Raw_data!$K3,TODAY(),"M"))) | E3: =--(AND(Raw_data!$AF3="No",OR(Raw_data!$AG3<>"",Raw_data!$AJ3>0,Raw_data!$AK3<>""))) | F3: =--(OR(AND(ISNUMBER(B3),B3<0.5,OR(D3>=24,Raw_data!$I3>0)),Raw_data!$AE3=TRUE)) | G3: =IF(Dashboard!$B$11="Department",Raw_data!$AL3,IF(Dashboard!$B$11="Team",Raw_data!$AM3,IF(Dashboard!$B$11="Unit",Raw_data!$AN3,IF(Dashboard!$B$11="Legal entity",Raw_data!$AO3,IF(Dashboard!$B$11="Location",Raw_data!$AP3,Raw_data!$AQ3))))) | H3: =--(AND(ISNUMBER(B3),B3<0.5)) | I3: =IFERROR(MAX(0,(0.5-B3)*100),0)+IF(D3>=24,20,0)+IF(Raw_data!$I3>0,20,0)+IF(Raw_data!$AE3=TRUE,10,0) | J3: =IFERROR(CHOOSE(MATCH(Dashboard!$B$11,{"Department","Team","Unit","Legal entity","Location","Lead"},0),INDEX(Lists!$B$3:$B$20,ROW()-1),INDEX(Lists!$C$3:$C$146,ROW()-1),INDEX(Lists!$D$3:$D$67,ROW()-1),INDEX(Lists!$E$3:$E$5,ROW()-1),INDEX(Lists!$F$3:$F$12,ROW()-1),INDEX(Lists!$G$3:$G$126,ROW()-1)),"") | K3: =IF(J3="","",SUMPRODUCT(($A$2:$A$636=1)*($G$2:$G$636=J3))) | L3: =IF(J3="","",SUMPRODUCT(($A$2:$A$636=1)*($G$2:$G$636=J3)*(ISNUMBER($B$2:$B$636))*($B$2:$B$636<0.5))) | M3: =IFERROR(L3/K3,"") | N3: =IF(K3="","",M3+K3/100000+ROW()/100000000) | O3: =IFERROR(INDEX($J$2:$J$1001,MATCH(LARGE($N$2:$N$1001,2),$N$2:$N$1001,0)),"") | P3: =IFERROR(INDEX($M$2:$M$1001,MATCH(LARGE($N$2:$N$1001,2),$N$2:$N$1001,0)),"") | Q3: =IFERROR(INDEX($K$2:$K$1001,MATCH(LARGE($N$2:$N$1001,2),$N$2:$N$1001,0)),"") | R3: =IF(A3=1,IFERROR(I3,0)+ROW()/100000000,-1E+99) | S3: =IF(A3=1,IFERROR(Raw_data!$T3,""),"") | T3: =IF(A3=1,IFERROR(Raw_data!$AA3,""),"") | U3: =IF(A3=1,IFERROR(Raw_data!$U3,""),"") | V3: =IF(A3=1,IFERROR(Raw_data!$AB3,""),"")
A4: =--(AND(OR(Dashboard!$B$4="All",Raw_data!$AL4=Dashboard!$B$4),OR(Dashboard!$B$5="All",Raw_data!$AM4=Dashboard!$B$5),OR(Dashboard!$B$6="All",Raw_data!$AN4=Dashboard!$B$6),OR(Dashboard!$B$7="All",Raw_data!$AO4=Dashboard!$B$7),OR(Dashboard!$B$8="All",Raw_data!$AP4=Dashboard!$B$8),OR(Dashboard!$B$9="All",Raw_data!$AQ4=Dashboard!$B$9),OR(Dashboard!$B$10="All",Raw_data!$AF4=Dashboard!$B$10),OR(Raw_data!$F4="",Raw_data!$F4<=TODAY()))) | B4: =IFERROR(IF(Dashboard!$B$3="Weighted",Raw_data!$U4,Raw_data!$T4),"") | C4: =IFERROR(IF(Dashboard!$B$3="Weighted",Raw_data!$AB4,Raw_data!$AA4),"") | D4: =IF(OR(Raw_data!$J4="",Raw_data!$J4<=0,Raw_data!$K4=""),"",IF(Raw_data!$K4>TODAY(),0,DATEDIF(Raw_data!$K4,TODAY(),"M"))) | E4: =--(AND(Raw_data!$AF4="No",OR(Raw_data!$AG4<>"",Raw_data!$AJ4>0,Raw_data!$AK4<>""))) | F4: =--(OR(AND(ISNUMBER(B4),B4<0.5,OR(D4>=24,Raw_data!$I4>0)),Raw_data!$AE4=TRUE)) | G4: =IF(Dashboard!$B$11="Department",Raw_data!$AL4,IF(Dashboard!$B$11="Team",Raw_data!$AM4,IF(Dashboard!$B$11="Unit",Raw_data!$AN4,IF(Dashboard!$B$11="Legal entity",Raw_data!$AO4,IF(Dashboard!$B$11="Location",Raw_data!$AP4,Raw_data!$AQ4))))) | H4: =--(AND(ISNUMBER(B4),B4<0.5)) | I4: =IFERROR(MAX(0,(0.5-B4)*100),0)+IF(D4>=24,20,0)+IF(Raw_data!$I4>0,20,0)+IF(Raw_data!$AE4=TRUE,10,0) | J4: =IFERROR(CHOOSE(MATCH(Dashboard!$B$11,{"Department","Team","Unit","Legal entity","Location","Lead"},0),INDEX(Lists!$B$3:$B$20,ROW()-1),INDEX(Lists!$C$3:$C$146,ROW()-1),INDEX(Lists!$D$3:$D$67,ROW()-1),INDEX(Lists!$E$3:$E$5,ROW()-1),INDEX(Lists!$F$3:$F$12,ROW()-1),INDEX(Lists!$G$3:$G$126,ROW()-1)),"") | K4: =IF(J4="","",SUMPRODUCT(($A$2:$A$636=1)*($G$2:$G$636=J4))) | L4: =IF(J4="","",SUMPRODUCT(($A$2:$A$636=1)*($G$2:$G$636=J4)*(ISNUMBER($B$2:$B$636))*($B$2:$B$636<0.5))) | M4: =IFERROR(L4/K4,"") | N4: =IF(K4="","",M4+K4/100000+ROW()/100000000) | O4: =IFERROR(INDEX($J$2:$J$1001,MATCH(LARGE($N$2:$N$1001,3),$N$2:$N$1001,0)),"") | P4: =IFERROR(INDEX($M$2:$M$1001,MATCH(LARGE($N$2:$N$1001,3),$N$2:$N$1001,0)),"") | Q4: =IFERROR(INDEX($K$2:$K$1001,MATCH(LARGE($N$2:$N$1001,3),$N$2:$N$1001,0)),"") | R4: =IF(A4=1,IFERROR(I4,0)+ROW()/100000000,-1E+99) | S4: =IF(A4=1,IFERROR(Raw_data!$T4,""),"") | T4: =IF(A4=1,IFERROR(Raw_data!$AA4,""),"") | U4: =IF(A4=1,IFERROR(Raw_data!$U4,""),"") | V4: =IF(A4=1,IFERROR(Raw_data!$AB4,""),"")
A5: =--(AND(OR(Dashboard!$B$4="All",Raw_data!$AL5=Dashboard!$B$4),OR(Dashboard!$B$5="All",Raw_data!$AM5=Dashboard!$B$5),OR(Dashboard!$B$6="All",Raw_data!$AN5=Dashboard!$B$6),OR(Dashboard!$B$7="All",Raw_data!$AO5=Dashboard!$B$7),OR(Dashboard!$B$8="All",Raw_data!$AP5=Dashboard!$B$8),OR(Dashboard!$B$9="All",Raw_data!$AQ5=Dashboard!$B$9),OR(Dashboard!$B$10="All",Raw_data!$AF5=Dashboard!$B$10),OR(Raw_data!$F5="",Raw_data!$F5<=TODAY()))) | B5: =IFERROR(IF(Dashboard!$B$3="Weighted",Raw_data!$U5,Raw_data!$T5),"") | C5: =IFERROR(IF(Dashboard!$B$3="Weighted",Raw_data!$AB5,Raw_data!$AA5),"") | D5: =IF(OR(Raw_data!$J5="",Raw_data!$J5<=0,Raw_data!$K5=""),"",IF(Raw_data!$K5>TODAY(),0,DATEDIF(Raw_data!$K5,TODAY(),"M"))) | E5: =--(AND(Raw_data!$AF5="No",OR(Raw_data!$AG5<>"",Raw_data!$AJ5>0,Raw_data!$AK5<>""))) | F5: =--(OR(AND(ISNUMBER(B5),B5<0.5,OR(D5>=24,Raw_data!$I5>0)),Raw_data!$AE5=TRUE)) | G5: =IF(Dashboard!$B$11="Department",Raw_data!$AL5,IF(Dashboard!$B$11="Team",Raw_data!$AM5,IF(Dashboard!$B$11="Unit",Raw_data!$AN5,IF(Dashboard!$B$11="Legal entity",Raw_data!$AO5,IF(Dashboard!$B$11="Location",Raw_data!$AP5,Raw_data!$AQ5))))) | H5: =--(AND(ISNUMBER(B5),B5<0.5)) | I5: =IFERROR(MAX(0,(0.5-B5)*100),0)+IF(D5>=24,20,0)+IF(Raw_data!$I5>0,20,0)+IF(Raw_data!$AE5=TRUE,10,0) | J5: =IFERROR(CHOOSE(MATCH(Dashboard!$B$11,{"Department","Team","Unit","Legal entity","Location","Lead"},0),INDEX(Lists!$B$3:$B$20,ROW()-1),INDEX(Lists!$C$3:$C$146,ROW()-1),INDEX(Lists!$D$3:$D$67,ROW()-1),INDEX(Lists!$E$3:$E$5,ROW()-1),INDEX(Lists!$F$3:$F$12,ROW()-1),INDEX(Lists!$G$3:$G$126,ROW()-1)),"") | K5: =IF(J5="","",SUMPRODUCT(($A$2:$A$636=1)*($G$2:$G$636=J5))) | L5: =IF(J5="","",SUMPRODUCT(($A$2:$A$636=1)*($G$2:$G$636=J5)*(ISNUMBER($B$2:$B$636))*($B$2:$B$636<0.5))) | M5: =IFERROR(L5/K5,"") | N5: =IF(K5="","",M5+K5/100000+ROW()/100000000) | O5: =IFERROR(INDEX($J$2:$J$1001,MATCH(LARGE($N$2:$N$1001,4),$N$2:$N$1001,0)),"") | P5: =IFERROR(INDEX($M$2:$M$1001,MATCH(LARGE($N$2:$N$1001,4),$N$2:$N$1001,0)),"") | Q5: =IFERROR(INDEX($K$2:$K$1001,MATCH(LARGE($N$2:$N$1001,4),$N$2:$N$1001,0)),"") | R5: =IF(A5=1,IFERROR(I5,0)+ROW()/100000000,-1E+99) | S5: =IF(A5=1,IFERROR(Raw_data!$T5,""),"") | T5: =IF(A5=1,IFERROR(Raw_data!$AA5,""),"") | U5: =IF(A5=1,IFERROR(Raw_data!$U5,""),"") | V5: =IF(A5=1,IFERROR(Raw_data!$AB5,""),"")
A6: =--(AND(OR(Dashboard!$B$4="All",Raw_data!$AL6=Dashboard!$B$4),OR(Dashboard!$B$5="All",Raw_data!$AM6=Dashboard!$B$5),OR(Dashboard!$B$6="All",Raw_data!$AN6=Dashboard!$B$6),OR(Dashboard!$B$7="All",Raw_data!$AO6=Dashboard!$B$7),OR(Dashboard!$B$8="All",Raw_data!$AP6=Dashboard!$B$8),OR(Dashboard!$B$9="All",Raw_data!$AQ6=Dashboard!$B$9),OR(Dashboard!$B$10="All",Raw_data!$AF6=Dashboard!$B$10),OR(Raw_data!$F6="",Raw_data!$F6<=TODAY()))) | B6: =IFERROR(IF(Dashboard!$B$3="Weighted",Raw_data!$U6,Raw_data!$T6),"") | C6: =IFERROR(IF(Dashboard!$B$3="Weighted",Raw_data!$AB6,Raw_data!$AA6),"") | D6: =IF(OR(Raw_data!$J6="",Raw_data!$J6<=0,Raw_data!$K6=""),"",IF(Raw_data!$K6>TODAY(),0,DATEDIF(Raw_data!$K6,TODAY(),"M"))) | E6: =--(AND(Raw_data!$AF6="No",OR(Raw_data!$AG6<>"",Raw_data!$AJ6>0,Raw_data!$AK6<>""))) | F6: =--(OR(AND(ISNUMBER(B6),B6<0.5,OR(D6>=24,Raw_data!$I6>0)),Raw_data!$AE6=TRUE)) | G6: =IF(Dashboard!$B$11="Department",Raw_data!$AL6,IF(Dashboard!$B$11="Team",Raw_data!$AM6,IF(Dashboard!$B$11="Unit",Raw_data!$AN6,IF(Dashboard!$B$11="Legal entity",Raw_data!$AO6,IF(Dashboard!$B$11="Location",Raw_data!$AP6,Raw_data!$AQ6))))) | H6: =--(AND(ISNUMBER(B6),B6<0.5)) | I6: =IFERROR(MAX(0,(0.5-B6)*100),0)+IF(D6>=24,20,0)+IF(Raw_data!$I6>0,20,0)+IF(Raw_data!$AE6=TRUE,10,0) | J6: =IFERROR(CHOOSE(MATCH(Dashboard!$B$11,{"Department","Team","Unit","Legal entity","Location","Lead"},0),INDEX(Lists!$B$3:$B$20,ROW()-1),INDEX(Lists!$C$3:$C$146,ROW()-1),INDEX(Lists!$D$3:$D$67,ROW()-1),INDEX(Lists!$E$3:$E$5,ROW()-1),INDEX(Lists!$F$3:$F$12,ROW()-1),INDEX(Lists!$G$3:$G$126,ROW()-1)),"") | K6: =IF(J6="","",SUMPRODUCT(($A$2:$A$636=1)*($G$2:$G$636=J6))) | L6: =IF(J6="","",SUMPRODUCT(($A$2:$A$636=1)*($G$2:$G$636=J6)*(ISNUMBER($B$2:$B$636))*($B$2:$B$636<0.5))) | M6: =IFERROR(L6/K6,"") | N6: =IF(K6="","",M6+K6/100000+ROW()/100000000) | O6: =IFERROR(INDEX($J$2:$J$1001,MATCH(LARGE($N$2:$N$1001,5),$N$2:$N$1001,0)),"") | P6: =IFERROR(INDEX($M$2:$M$1001,MATCH(LARGE($N$2:$N$1001,5),$N$2:$N$1001,0)),"") | Q6: =IFERROR(INDEX($K$2:$K$1001,MATCH(LARGE($N$2:$N$1001,5),$N$2:$N$1001,0)),"") | R6: =IF(A6=1,IFERROR(I6,0)+ROW()/100000000,-1E+99) | S6: =IF(A6=1,IFERROR(Raw_data!$T6,""),"") | T6: =IF(A6=1,IFERROR(Raw_data!$AA6,""),"") | U6: =IF(A6=1,IFERROR(Raw_data!$U6,""),"") | V6: =IF(A6=1,IFERROR(Raw_data!$AB6,""),"")
A7: =--(AND(OR(Dashboard!$B$4="All",Raw_data!$AL7=Dashboard!$B$4),OR(Dashboard!$B$5="All",Raw_data!$AM7=Dashboard!$B$5),OR(Dashboard!$B$6="All",Raw_data!$AN7=Dashboard!$B$6),OR(Dashboard!$B$7="All",Raw_data!$AO7=Dashboard!$B$7),OR(Dashboard!$B$8="All",Raw_data!$AP7=Dashboard!$B$8),OR(Dashboard!$B$9="All",Raw_data!$AQ7=Dashboard!$B$9),OR(Dashboard!$B$10="All",Raw_data!$AF7=Dashboard!$B$10),OR(Raw_data!$F7="",Raw_data!$F7<=TODAY()))) | B7: =IFERROR(IF(Dashboard!$B$3="Weighted",Raw_data!$U7,Raw_data!$T7),"") | C7: =IFERROR(IF(Dashboard!$B$3="Weighted",Raw_data!$AB7,Raw_data!$AA7),"") | D7: =IF(OR(Raw_data!$J7="",Raw_data!$J7<=0,Raw_data!$K7=""),"",IF(Raw_data!$K7>TODAY(),0,DATEDIF(Raw_data!$K7,TODAY(),"M"))) | E7: =--(AND(Raw_data!$AF7="No",OR(Raw_data!$AG7<>"",Raw_data!$AJ7>0,Raw_data!$AK7<>""))) | F7: =--(OR(AND(ISNUMBER(B7),B7<0.5,OR(D7>=24,Raw_data!$I7>0)),Raw_data!$AE7=TRUE)) | G7: =IF(Dashboard!$B$11="Department",Raw_data!$AL7,IF(Dashboard!$B$11="Team",Raw_data!$AM7,IF(Dashboard!$B$11="Unit",Raw_data!$AN7,IF(Dashboard!$B$11="Legal entity",Raw_data!$AO7,IF(Dashboard!$B$11="Location",Raw_data!$AP7,Raw_data!$AQ7))))) | H7: =--(AND(ISNUMBER(B7),B7<0.5)) | I7: =IFERROR(MAX(0,(0.5-B7)*100),0)+IF(D7>=24,20,0)+IF(Raw_data!$I7>0,20,0)+IF(Raw_data!$AE7=TRUE,10,0) | J7: =IFERROR(CHOOSE(MATCH(Dashboard!$B$11,{"Department","Team","Unit","Legal entity","Location","Lead"},0),INDEX(Lists!$B$3:$B$20,ROW()-1),INDEX(Lists!$C$3:$C$146,ROW()-1),INDEX(Lists!$D$3:$D$67,ROW()-1),INDEX(Lists!$E$3:$E$5,ROW()-1),INDEX(Lists!$F$3:$F$12,ROW()-1),INDEX(Lists!$G$3:$G$126,ROW()-1)),"") | K7: =IF(J7="","",SUMPRODUCT(($A$2:$A$636=1)*($G$2:$G$636=J7))) | L7: =IF(J7="","",SUMPRODUCT(($A$2:$A$636=1)*($G$2:$G$636=J7)*(ISNUMBER($B$2:$B$636))*($B$2:$B$636<0.5))) | M7: =IFERROR(L7/K7,"") | N7: =IF(K7="","",M7+K7/100000+ROW()/100000000) | O7: =IFERROR(INDEX($J$2:$J$1001,MATCH(LARGE($N$2:$N$1001,6),$N$2:$N$1001,0)),"") | P7: =IFERROR(INDEX($M$2:$M$1001,MATCH(LARGE($N$2:$N$1001,6),$N$2:$N$1001,0)),"") | Q7: =IFERROR(INDEX($K$2:$K$1001,MATCH(LARGE($N$2:$N$1001,6),$N$2:$N$1001,0)),"") | R7: =IF(A7=1,IFERROR(I7,0)+ROW()/100000000,-1E+99) | S7: =IF(A7=1,IFERROR(Raw_data!$T7,""),"") | T7: =IF(A7=1,IFERROR(Raw_data!$AA7,""),"") | U7: =IF(A7=1,IFERROR(Raw_data!$U7,""),"") | V7: =IF(A7=1,IFERROR(Raw_data!$AB7,""),"")
A8: =--(AND(OR(Dashboard!$B$4="All",Raw_data!$AL8=Dashboard!$B$4),OR(Dashboard!$B$5="All",Raw_data!$AM8=Dashboard!$B$5),OR(Dashboard!$B$6="All",Raw_data!$AN8=Dashboard!$B$6),OR(Dashboard!$B$7="All",Raw_data!$AO8=Dashboard!$B$7),OR(Dashboard!$B$8="All",Raw_data!$AP8=Dashboard!$B$8),OR(Dashboard!$B$9="All",Raw_data!$AQ8=Dashboard!$B$9),OR(Dashboard!$B$10="All",Raw_data!$AF8=Dashboard!$B$10),OR(Raw_data!$F8="",Raw_data!$F8<=TODAY()))) | B8: =IFERROR(IF(Dashboard!$B$3="Weighted",Raw_data!$U8,Raw_data!$T8),"") | C8: =IFERROR(IF(Dashboard!$B$3="Weighted",Raw_data!$AB8,Raw_data!$AA8),"") | D8: =IF(OR(Raw_data!$J8="",Raw_data!$J8<=0,Raw_data!$K8=""),"",IF(Raw_data!$K8>TODAY(),0,DATEDIF(Raw_data!$K8,TODAY(),"M"))) | E8: =--(AND(Raw_data!$AF8="No",OR(Raw_data!$AG8<>"",Raw_data!$AJ8>0,Raw_data!$AK8<>""))) | F8: =--(OR(AND(ISNUMBER(B8),B8<0.5,OR(D8>=24,Raw_data!$I8>0)),Raw_data!$AE8=TRUE)) | G8: =IF(Dashboard!$B$11="Department",Raw_data!$AL8,IF(Dashboard!$B$11="Team",Raw_data!$AM8,IF(Dashboard!$B$11="Unit",Raw_data!$AN8,IF(Dashboard!$B$11="Legal entity",Raw_data!$AO8,IF(Dashboard!$B$11="Location",Raw_data!$AP8,Raw_data!$AQ8))))) | H8: =--(AND(ISNUMBER(B8),B8<0.5)) | I8: =IFERROR(MAX(0,(0.5-B8)*100),0)+IF(D8>=24,20,0)+IF(Raw_data!$I8>0,20,0)+IF(Raw_data!$AE8=TRUE,10,0) | J8: =IFERROR(CHOOSE(MATCH(Dashboard!$B$11,{"Department","Team","Unit","Legal entity","Location","Lead"},0),INDEX(Lists!$B$3:$B$20,ROW()-1),INDEX(Lists!$C$3:$C$146,ROW()-1),INDEX(Lists!$D$3:$D$67,ROW()-1),INDEX(Lists!$E$3:$E$5,ROW()-1),INDEX(Lists!$F$3:$F$12,ROW()-1),INDEX(Lists!$G$3:$G$126,ROW()-1)),"") | K8: =IF(J8="","",SUMPRODUCT(($A$2:$A$636=1)*($G$2:$G$636=J8))) | L8: =IF(J8="","",SUMPRODUCT(($A$2:$A$636=1)*($G$2:$G$636=J8)*(ISNUMBER($B$2:$B$636))*($B$2:$B$636<0.5))) | M8: =IFERROR(L8/K8,"") | N8: =IF(K8="","",M8+K8/100000+ROW()/100000000) | O8: =IFERROR(INDEX($J$2:$J$1001,MATCH(LARGE($N$2:$N$1001,7),$N$2:$N$1001,0)),"") | P8: =IFERROR(INDEX($M$2:$M$1001,MATCH(LARGE($N$2:$N$1001,7),$N$2:$N$1001,0)),"") | Q8: =IFERROR(INDEX($K$2:$K$1001,MATCH(LARGE($N$2:$N$1001,7),$N$2:$N$1001,0)),"") | R8: =IF(A8=1,IFERROR(I8,0)+ROW()/100000000,-1E+99) | S8: =IF(A8=1,IFERROR(Raw_data!$T8,""),"") | T8: =IF(A8=1,IFERROR(Raw_data!$AA8,""),"") | U8: =IF(A8=1,IFERROR(Raw_data!$U8,""),"") | V8: =IF(A8=1,IFERROR(Raw_data!$AB8,""),"")
A9: =--(AND(OR(Dashboard!$B$4="All",Raw_data!$AL9=Dashboard!$B$4),OR(Dashboard!$B$5="All",Raw_data!$AM9=Dashboard!$B$5),OR(Dashboard!$B$6="All",Raw_data!$AN9=Dashboard!$B$6),OR(Dashboard!$B$7="All",Raw_data!$AO9=Dashboard!$B$7),OR(Dashboard!$B$8="All",Raw_data!$AP9=Dashboard!$B$8),OR(Dashboard!$B$9="All",Raw_data!$AQ9=Dashboard!$B$9),OR(Dashboard!$B$10="All",Raw_data!$AF9=Dashboard!$B$10),OR(Raw_data!$F9="",Raw_data!$F9<=TODAY()))) | B9: =IFERROR(IF(Dashboard!$B$3="Weighted",Raw_data!$U9,Raw_data!$T9),"") | C9: =IFERROR(IF(Dashboard!$B$3="Weighted",Raw_data!$AB9,Raw_data!$AA9),"") | D9: =IF(OR(Raw_data!$J9="",Raw_data!$J9<=0,Raw_data!$K9=""),"",IF(Raw_data!$K9>TODAY(),0,DATEDIF(Raw_data!$K9,TODAY(),"M"))) | E9: =--(AND(Raw_data!$AF9="No",OR(Raw_data!$AG9<>"",Raw_data!$AJ9>0,Raw_data!$AK9<>""))) | F9: =--(OR(AND(ISNUMBER(B9),B9<0.5,OR(D9>=24,Raw_data!$I9>0)),Raw_data!$AE9=TRUE)) | G9: =IF(Dashboard!$B$11="Department",Raw_data!$AL9,IF(Dashboard!$B$11="Team",Raw_data!$AM9,IF(Dashboard!$B$11="Unit",Raw_data!$AN9,IF(Dashboard!$B$11="Legal entity",Raw_data!$AO9,IF(Dashboard!$B$11="Location",Raw_data!$AP9,Raw_data!$AQ9))))) | H9: =--(AND(ISNUMBER(B9),B9<0.5)) | I9: =IFERROR(MAX(0,(0.5-B9)*100),0)+IF(D9>=24,20,0)+IF(Raw_data!$I9>0,20,0)+IF(Raw_data!$AE9=TRUE,10,0) | J9: =IFERROR(CHOOSE(MATCH(Dashboard!$B$11,{"Department","Team","Unit","Legal entity","Location","Lead"},0),INDEX(Lists!$B$3:$B$20,ROW()-1),INDEX(Lists!$C$3:$C$146,ROW()-1),INDEX(Lists!$D$3:$D$67,ROW()-1),INDEX(Lists!$E$3:$E$5,ROW()-1),INDEX(Lists!$F$3:$F$12,ROW()-1),INDEX(Lists!$G$3:$G$126,ROW()-1)),"") | K9: =IF(J9="","",SUMPRODUCT(($A$2:$A$636=1)*($G$2:$G$636=J9))) | L9: =IF(J9="","",SUMPRODUCT(($A$2:$A$636=1)*($G$2:$G$636=J9)*(ISNUMBER($B$2:$B$636))*($B$2:$B$636<0.5))) | M9: =IFERROR(L9/K9,"") | N9: =IF(K9="","",M9+K9/100000+ROW()/100000000) | O9: =IFERROR(INDEX($J$2:$J$1001,MATCH(LARGE($N$2:$N$1001,8),$N$2:$N$1001,0)),"") | P9: =IFERROR(INDEX($M$2:$M$1001,MATCH(LARGE($N$2:$N$1001,8),$N$2:$N$1001,0)),"") | Q9: =IFERROR(INDEX($K$2:$K$1001,MATCH(LARGE($N$2:$N$1001,8),$N$2:$N$1001,0)),"") | R9: =IF(A9=1,IFERROR(I9,0)+ROW()/100000000,-1E+99) | S9: =IF(A9=1,IFERROR(Raw_data!$T9,""),"") | T9: =IF(A9=1,IFERROR(Raw_data!$AA9,""),"") | U9: =IF(A9=1,IFERROR(Raw_data!$U9,""),"") | V9: =IF(A9=1,IFERROR(Raw_data!$AB9,""),"")
A10: =--(AND(OR(Dashboard!$B$4="All",Raw_data!$AL10=Dashboard!$B$4),OR(Dashboard!$B$5="All",Raw_data!$AM10=Dashboard!$B$5),OR(Dashboard!$B$6="All",Raw_data!$AN10=Dashboard!$B$6),OR(Dashboard!$B$7="All",Raw_data!$AO10=Dashboard!$B$7),OR(Dashboard!$B$8="All",Raw_data!$AP10=Dashboard!$B$8),OR(Dashboard!$B$9="All",Raw_data!$AQ10=Dashboard!$B$9),OR(Dashboard!$B$10="All",Raw_data!$AF10=Dashboard!$B$10),OR(Raw_data!$F10="",Raw_data!$F10<=TODAY()))) | B10: =IFERROR(IF(Dashboard!$B$3="Weighted",Raw_data!$U10,Raw_data!$T10),"") | C10: =IFERROR(IF(Dashboard!$B$3="Weighted",Raw_data!$AB10,Raw_data!$AA10),"") | D10: =IF(OR(Raw_data!$J10="",Raw_data!$J10<=0,Raw_data!$K10=""),"",IF(Raw_data!$K10>TODAY(),0,DATEDIF(Raw_data!$K10,TODAY(),"M"))) | E10: =--(AND(Raw_data!$AF10="No",OR(Raw_data!$AG10<>"",Raw_data!$AJ10>0,Raw_data!$AK10<>""))) | F10: =--(OR(AND(ISNUMBER(B10),B10<0.5,OR(D10>=24,Raw_data!$I10>0)),Raw_data!$AE10=TRUE)) | G10: =IF(Dashboard!$B$11="Department",Raw_data!$AL10,IF(Dashboard!$B$11="Team",Raw_data!$AM10,IF(Dashboard!$B$11="Unit",Raw_data!$AN10,IF(Dashboard!$B$11="Legal entity",Raw_data!$AO10,IF(Dashboard!$B$11="Location",Raw_data!$AP10,Raw_data!$AQ10))))) | H10: =--(AND(ISNUMBER(B10),B10<0.5)) | I10: =IFERROR(MAX(0,(0.5-B10)*100),0)+IF(D10>=24,20,0)+IF(Raw_data!$I10>0,20,0)+IF(Raw_data!$AE10=TRUE,10,0) | J10: =IFERROR(CHOOSE(MATCH(Dashboard!$B$11,{"Department","Team","Unit","Legal entity","Location","Lead"},0),INDEX(Lists!$B$3:$B$20,ROW()-1),INDEX(Lists!$C$3:$C$146,ROW()-1),INDEX(Lists!$D$3:$D$67,ROW()-1),INDEX(Lists!$E$3:$E$5,ROW()-1),INDEX(Lists!$F$3:$F$12,ROW()-1),INDEX(Lists!$G$3:$G$126,ROW()-1)),"") | K10: =IF(J10="","",SUMPRODUCT(($A$2:$A$636=1)*($G$2:$G$636=J10))) | L10: =IF(J10="","",SUMPRODUCT(($A$2:$A$636=1)*($G$2:$G$636=J10)*(ISNUMBER($B$2:$B$636))*($B$2:$B$636<0.5))) | M10: =IFERROR(L10/K10,"") | N10: =IF(K10="","",M10+K10/100000+ROW()/100000000) | O10: =IFERROR(INDEX($J$2:$J$1001,MATCH(LARGE($N$2:$N$1001,9),$N$2:$N$1001,0)),"") | P10: =IFERROR(INDEX($M$2:$M$1001,MATCH(LARGE($N$2:$N$1001,9),$N$2:$N$1001,0)),"") | Q10: =IFERROR(INDEX($K$2:$K$1001,MATCH(LARGE($N$2:$N$1001,9),$N$2:$N$1001,0)),"") | R10: =IF(A10=1,IFERROR(I10,0)+ROW()/100000000,-1E+99) | S10: =IF(A10=1,IFERROR(Raw_data!$T10,""),"") | T10: =IF(A10=1,IFERROR(Raw_data!$AA10,""),"") | U10: =IF(A10=1,IFERROR(Raw_data!$U10,""),"") | V10: =IF(A10=1,IFERROR(Raw_data!$AB10,""),"")
A11: =--(AND(OR(Dashboard!$B$4="All",Raw_data!$AL11=Dashboard!$B$4),OR(Dashboard!$B$5="All",Raw_data!$AM11=Dashboard!$B$5),OR(Dashboard!$B$6="All",Raw_data!$AN11=Dashboard!$B$6),OR(Dashboard!$B$7="All",Raw_data!$AO11=Dashboard!$B$7),OR(Dashboard!$B$8="All",Raw_data!$AP11=Dashboard!$B$8),OR(Dashboard!$B$9="All",Raw_data!$AQ11=Dashboard!$B$9),OR(Dashboard!$B$10="All",Raw_data!$AF11=Dashboard!$B$10),OR(Raw_data!$F11="",Raw_data!$F11<=TODAY()))) | B11: =IFERROR(IF(Dashboard!$B$3="Weighted",Raw_data!$U11,Raw_data!$T11),"") | C11: =IFERROR(IF(Dashboard!$B$3="Weighted",Raw_data!$AB11,Raw_data!$AA11),"") | D11: =IF(OR(Raw_data!$J11="",Raw_data!$J11<=0,Raw_data!$K11=""),"",IF(Raw_data!$K11>TODAY(),0,DATEDIF(Raw_data!$K11,TODAY(),"M"))) | E11: =--(AND(Raw_data!$AF11="No",OR(Raw_data!$AG11<>"",Raw_data!$AJ11>0,Raw_data!$AK11<>""))) | F11: =--(OR(AND(ISNUMBER(B11),B11<0.5,OR(D11>=24,Raw_data!$I11>0)),Raw_data!$AE11=TRUE)) | G11: =IF(Dashboard!$B$11="Department",Raw_data!$AL11,IF(Dashboard!$B$11="Team",Raw_data!$AM11,IF(Dashboard!$B$11="Unit",Raw_data!$AN11,IF(Dashboard!$B$11="Legal entity",Raw_data!$AO11,IF(Dashboard!$B$11="Location",Raw_data!$AP11,Raw_data!$AQ11))))) | H11: =--(AND(ISNUMBER(B11),B11<0.5)) | I11: =IFERROR(MAX(0,(0.5-B11)*100),0)+IF(D11>=24,20,0)+IF(Raw_data!$I11>0,20,0)+IF(Raw_data!$AE11=TRUE,10,0) | J11: =IFERROR(CHOOSE(MATCH(Dashboard!$B$11,{"Department","Team","Unit","Legal entity","Location","Lead"},0),INDEX(Lists!$B$3:$B$20,ROW()-1),INDEX(Lists!$C$3:$C$146,ROW()-1),INDEX(Lists!$D$3:$D$67,ROW()-1),INDEX(Lists!$E$3:$E$5,ROW()-1),INDEX(Lists!$F$3:$F$12,ROW()-1),INDEX(Lists!$G$3:$G$126,ROW()-1)),"") | K11: =IF(J11="","",SUMPRODUCT(($A$2:$A$636=1)*($G$2:$G$636=J11))) | L11: =IF(J11="","",SUMPRODUCT(($A$2:$A$636=1)*($G$2:$G$636=J11)*(ISNUMBER($B$2:$B$636))*($B$2:$B$636<0.5))) | M11: =IFERROR(L11/K11,"") | N11: =IF(K11="","",M11+K11/100000+ROW()/100000000) | O11: =IFERROR(INDEX($J$2:$J$1001,MATCH(LARGE($N$2:$N$1001,10),$N$2:$N$1001,0)),"") | P11: =IFERROR(INDEX($M$2:$M$1001,MATCH(LARGE($N$2:$N$1001,10),$N$2:$N$1001,0)),"") | Q11: =IFERROR(INDEX($K$2:$K$1001,MATCH(LARGE($N$2:$N$1001,10),$N$2:$N$1001,0)),"") | R11: =IF(A11=1,IFERROR(I11,0)+ROW()/100000000,-1E+99) | S11: =IF(A11=1,IFERROR(Raw_data!$T11,""),"") | T11: =IF(A11=1,IFERROR(Raw_data!$AA11,""),"") | U11: =IF(A11=1,IFERROR(Raw_data!$U11,""),"") | V11: =IF(A11=1,IFERROR(Raw_data!$AB11,""),"")
A12: =--(AND(OR(Dashboard!$B$4="All",Raw_data!$AL12=Dashboard!$B$4),OR(Dashboard!$B$5="All",Raw_data!$AM12=Dashboard!$B$5),OR(Dashboard!$B$6="All",Raw_data!$AN12=Dashboard!$B$6),OR(Dashboard!$B$7="All",Raw_data!$AO12=Dashboard!$B$7),OR(Dashboard!$B$8="All",Raw_data!$AP12=Dashboard!$B$8),OR(Dashboard!$B$9="All",Raw_data!$AQ12=Dashboard!$B$9),OR(Dashboard!$B$10="All",Raw_data!$AF12=Dashboard!$B$10),OR(Raw_data!$F12="",Raw_data!$F12<=TODAY()))) | B12: =IFERROR(IF(Dashboard!$B$3="Weighted",Raw_data!$U12,Raw_data!$T12),"") | C12: =IFERROR(IF(Dashboard!$B$3="Weighted",Raw_data!$AB12,Raw_data!$AA12),"") | D12: =IF(OR(Raw_data!$J12="",Raw_data!$J12<=0,Raw_data!$K12=""),"",IF(Raw_data!$K12>TODAY(),0,DATEDIF(Raw_data!$K12,TODAY(),"M"))) | E12: =--(AND(Raw_data!$AF12="No",OR(Raw_data!$AG12<>"",Raw_data!$AJ12>0,Raw_data!$AK12<>""))) | F12: =--(OR(AND(ISNUMBER(B12),B12<0.5,OR(D12>=24,Raw_data!$I12>0)),Raw_data!$AE12=TRUE)) | G12: =IF(Dashboard!$B$11="Department",Raw_data!$AL12,IF(Dashboard!$B$11="Team",Raw_data!$AM12,IF(Dashboard!$B$11="Unit",Raw_data!$AN12,IF(Dashboard!$B$11="Legal entity",Raw_data!$AO12,IF(Dashboard!$B$11="Location",Raw_data!$AP12,Raw_data!$AQ12))))) | H12: =--(AND(ISNUMBER(B12),B12<0.5)) | I12: =IFERROR(MAX(0,(0.5-B12)*100),0)+IF(D12>=24,20,0)+IF(Raw_data!$I12>0,20,0)+IF(Raw_data!$AE12=TRUE,10,0) | J12: =IFERROR(CHOOSE(MATCH(Dashboard!$B$11,{"Department","Team","Unit","Legal entity","Location","Lead"},0),INDEX(Lists!$B$3:$B$20,ROW()-1),INDEX(Lists!$C$3:$C$146,ROW()-1),INDEX(Lists!$D$3:$D$67,ROW()-1),INDEX(Lists!$E$3:$E$5,ROW()-1),INDEX(Lists!$F$3:$F$12,ROW()-1),INDEX(Lists!$G$3:$G$126,ROW()-1)),"") | K12: =IF(J12="","",SUMPRODUCT(($A$2:$A$636=1)*($G$2:$G$636=J12))) | L12: =IF(J12="","",SUMPRODUCT(($A$2:$A$636=1)*($G$2:$G$636=J12)*(ISNUMBER($B$2:$B$636))*($B$2:$B$636<0.5))) | M12: =IFERROR(L12/K12,"") | N12: =IF(K12="","",M12+K12/100000+ROW()/100000000) | R12: =IF(A12=1,IFERROR(I12,0)+ROW()/100000000,-1E+99) | S12: =IF(A12=1,IFERROR(Raw_data!$T12,""),"") | T12: =IF(A12=1,IFERROR(Raw_data!$AA12,""),"") | U12: =IF(A12=1,IFERROR(Raw_data!$U12,""),"") | V12: =IF(A12=1,IFERROR(Raw_data!$AB12,""),"")
A13: =--(AND(OR(Dashboard!$B$4="All",Raw_data!$AL13=Dashboard!$B$4),OR(Dashboard!$B$5="All",Raw_data!$AM13=Dashboard!$B$5),OR(Dashboard!$B$6="All",Raw_data!$AN13=Dashboard!$B$6),OR(Dashboard!$B$7="All",Raw_data!$AO13=Dashboard!$B$7),OR(Dashboard!$B$8="All",Raw_data!$AP13=Dashboard!$B$8),OR(Dashboard!$B$9="All",Raw_data!$AQ13=Dashboard!$B$9),OR(Dashboard!$B$10="All",Raw_data!$AF13=Dashboard!$B$10),OR(Raw_data!$F13="",Raw_data!$F13<=TODAY()))) | B13: =IFERROR(IF(Dashboard!$B$3="Weighted",Raw_data!$U13,Raw_data!$T13),"") | C13: =IFERROR(IF(Dashboard!$B$3="Weighted",Raw_data!$AB13,Raw_data!$AA13),"") | D13: =IF(OR(Raw_data!$J13="",Raw_data!$J13<=0,Raw_data!$K13=""),"",IF(Raw_data!$K13>TODAY(),0,DATEDIF(Raw_data!$K13,TODAY(),"M"))) | E13: =--(AND(Raw_data!$AF13="No",OR(Raw_data!$AG13<>"",Raw_data!$AJ13>0,Raw_data!$AK13<>""))) | F13: =--(OR(AND(ISNUMBER(B13),B13<0.5,OR(D13>=24,Raw_data!$I13>0)),Raw_data!$AE13=TRUE)) | G13: =IF(Dashboard!$B$11="Department",Raw_data!$AL13,IF(Dashboard!$B$11="Team",Raw_data!$AM13,IF(Dashboard!$B$11="Unit",Raw_data!$AN13,IF(Dashboard!$B$11="Legal entity",Raw_data!$AO13,IF(Dashboard!$B$11="Location",Raw_data!$AP13,Raw_data!$AQ13))))) | H13: =--(AND(ISNUMBER(B13),B13<0.5)) | I13: =IFERROR(MAX(0,(0.5-B13)*100),0)+IF(D13>=24,20,0)+IF(Raw_data!$I13>0,20,0)+IF(Raw_data!$AE13=TRUE,10,0) | J13: =IFERROR(CHOOSE(MATCH(Dashboard!$B$11,{"Department","Team","Unit","Legal entity","Location","Lead"},0),INDEX(Lists!$B$3:$B$20,ROW()-1),INDEX(Lists!$C$3:$C$146,ROW()-1),INDEX(Lists!$D$3:$D$67,ROW()-1),INDEX(Lists!$E$3:$E$5,ROW()-1),INDEX(Lists!$F$3:$F$12,ROW()-1),INDEX(Lists!$G$3:$G$126,ROW()-1)),"") | K13: =IF(J13="","",SUMPRODUCT(($A$2:$A$636=1)*($G$2:$G$636=J13))) | L13: =IF(J13="","",SUMPRODUCT(($A$2:$A$636=1)*($G$2:$G$636=J13)*(ISNUMBER($B$2:$B$636))*($B$2:$B$636<0.5))) | M13: =IFERROR(L13/K13,"") | N13: =IF(K13="","",M13+K13/100000+ROW()/100000000) | R13: =IF(A13=1,IFERROR(I13,0)+ROW()/100000000,-1E+99) | S13: =IF(A13=1,IFERROR(Raw_data!$T13,""),"") | T13: =IF(A13=1,IFERROR(Raw_data!$AA13,""),"") | U13: =IF(A13=1,IFERROR(Raw_data!$U13,""),"") | V13: =IF(A13=1,IFERROR(Raw_data!$AB13,""),"")
A14: =--(AND(OR(Dashboard!$B$4="All",Raw_data!$AL14=Dashboard!$B$4),OR(Dashboard!$B$5="All",Raw_data!$AM14=Dashboard!$B$5),OR(Dashboard!$B$6="All",Raw_data!$AN14=Dashboard!$B$6),OR(Dashboard!$B$7="All",Raw_data!$AO14=Dashboard!$B$7),OR(Dashboard!$B$8="All",Raw_data!$AP14=Dashboard!$B$8),OR(Dashboard!$B$9="All",Raw_data!$AQ14=Dashboard!$B$9),OR(Dashboard!$B$10="All",Raw_data!$AF14=Dashboard!$B$10),OR(Raw_data!$F14="",Raw_data!$F14<=TODAY()))) | B14: =IFERROR(IF(Dashboard!$B$3="Weighted",Raw_data!$U14,Raw_data!$T14),"") | C14: =IFERROR(IF(Dashboard!$B$3="Weighted",Raw_data!$AB14,Raw_data!$AA14),"") | D14: =IF(OR(Raw_data!$J14="",Raw_data!$J14<=0,Raw_data!$K14=""),"",IF(Raw_data!$K14>TODAY(),0,DATEDIF(Raw_data!$K14,TODAY(),"M"))) | E14: =--(AND(Raw_data!$AF14="No",OR(Raw_data!$AG14<>"",Raw_data!$AJ14>0,Raw_data!$AK14<>""))) | F14: =--(OR(AND(ISNUMBER(B14),B14<0.5,OR(D14>=24,Raw_data!$I14>0)),Raw_data!$AE14=TRUE)) | G14: =IF(Dashboard!$B$11="Department",Raw_data!$AL14,IF(Dashboard!$B$11="Team",Raw_data!$AM14,IF(Dashboard!$B$11="Unit",Raw_data!$AN14,IF(Dashboard!$B$11="Legal entity",Raw_data!$AO14,IF(Dashboard!$B$11="Location",Raw_data!$AP14,Raw_data!$AQ14))))) | H14: =--(AND(ISNUMBER(B14),B14<0.5)) | I14: =IFERROR(MAX(0,(0.5-B14)*100),0)+IF(D14>=24,20,0)+IF(Raw_data!$I14>0,20,0)+IF(Raw_data!$AE14=TRUE,10,0) | J14: =IFERROR(CHOOSE(MATCH(Dashboard!$B$11,{"Department","Team","Unit","Legal entity","Location","Lead"},0),INDEX(Lists!$B$3:$B$20,ROW()-1),INDEX(Lists!$C$3:$C$146,ROW()-1),INDEX(Lists!$D$3:$D$67,ROW()-1),INDEX(Lists!$E$3:$E$5,ROW()-1),INDEX(Lists!$F$3:$F$12,ROW()-1),INDEX(Lists!$G$3:$G$126,ROW()-1)),"") | K14: =IF(J14="","",SUMPRODUCT(($A$2:$A$636=1)*($G$2:$G$636=J14))) | L14: =IF(J14="","",SUMPRODUCT(($A$2:$A$636=1)*($G$2:$G$636=J14)*(ISNUMBER($B$2:$B$636))*($B$2:$B$636<0.5))) | M14: =IFERROR(L14/K14,"") | N14: =IF(K14="","",M14+K14/100000+ROW()/100000000) | R14: =IF(A14=1,IFERROR(I14,0)+ROW()/100000000,-1E+99) | S14: =IF(A14=1,IFERROR(Raw_data!$T14,""),"") | T14: =IF(A14=1,IFERROR(Raw_data!$AA14,""),"") | U14: =IF(A14=1,IFERROR(Raw_data!$U14,""),"") | V14: =IF(A14=1,IFERROR(Raw_data!$AB14,""),"")
A15: =--(AND(OR(Dashboard!$B$4="All",Raw_data!$AL15=Dashboard!$B$4),OR(Dashboard!$B$5="All",Raw_data!$AM15=Dashboard!$B$5),OR(Dashboard!$B$6="All",Raw_data!$AN15=Dashboard!$B$6),OR(Dashboard!$B$7="All",Raw_data!$AO15=Dashboard!$B$7),OR(Dashboard!$B$8="All",Raw_data!$AP15=Dashboard!$B$8),OR(Dashboard!$B$9="All",Raw_data!$AQ15=Dashboard!$B$9),OR(Dashboard!$B$10="All",Raw_data!$AF15=Dashboard!$B$10),OR(Raw_data!$F15="",Raw_data!$F15<=TODAY()))) | B15: =IFERROR(IF(Dashboard!$B$3="Weighted",Raw_data!$U15,Raw_data!$T15),"") | C15: =IFERROR(IF(Dashboard!$B$3="Weighted",Raw_data!$AB15,Raw_data!$AA15),"") | D15: =IF(OR(Raw_data!$J15="",Raw_data!$J15<=0,Raw_data!$K15=""),"",IF(Raw_data!$K15>TODAY(),0,DATEDIF(Raw_data!$K15,TODAY(),"M"))) | E15: =--(AND(Raw_data!$AF15="No",OR(Raw_data!$AG15<>"",Raw_data!$AJ15>0,Raw_data!$AK15<>""))) | F15: =--(OR(AND(ISNUMBER(B15),B15<0.5,OR(D15>=24,Raw_data!$I15>0)),Raw_data!$AE15=TRUE)) | G15: =IF(Dashboard!$B$11="Department",Raw_data!$AL15,IF(Dashboard!$B$11="Team",Raw_data!$AM15,IF(Dashboard!$B$11="Unit",Raw_data!$AN15,IF(Dashboard!$B$11="Legal entity",Raw_data!$AO15,IF(Dashboard!$B$11="Location",Raw_data!$AP15,Raw_data!$AQ15))))) | H15: =--(AND(ISNUMBER(B15),B15<0.5)) | I15: =IFERROR(MAX(0,(0.5-B15)*100),0)+IF(D15>=24,20,0)+IF(Raw_data!$I15>0,20,0)+IF(Raw_data!$AE15=TRUE,10,0) | J15: =IFERROR(CHOOSE(MATCH(Dashboard!$B$11,{"Department","Team","Unit","Legal entity","Location","Lead"},0),INDEX(Lists!$B$3:$B$20,ROW()-1),INDEX(Lists!$C$3:$C$146,ROW()-1),INDEX(Lists!$D$3:$D$67,ROW()-1),INDEX(Lists!$E$3:$E$5,ROW()-1),INDEX(Lists!$F$3:$F$12,ROW()-1),INDEX(Lists!$G$3:$G$126,ROW()-1)),"") | K15: =IF(J15="","",SUMPRODUCT(($A$2:$A$636=1)*($G$2:$G$636=J15))) | L15: =IF(J15="","",SUMPRODUCT(($A$2:$A$636=1)*($G$2:$G$636=J15)*(ISNUMBER($B$2:$B$636))*($B$2:$B$636<0.5))) | M15: =IFERROR(L15/K15,"") | N15: =IF(K15="","",M15+K15/100000+ROW()/100000000) | R15: =IF(A15=1,IFERROR(I15,0)+ROW()/100000000,-1E+99) | S15: =IF(A15=1,IFERROR(Raw_data!$T15,""),"") | T15: =IF(A15=1,IFERROR(Raw_data!$AA15,""),"") | U15: =IF(A15=1,IFERROR(Raw_data!$U15,""),"") | V15: =IF(A15=1,IFERROR(Raw_data!$AB15,""),"")
A16: =--(AND(OR(Dashboard!$B$4="All",Raw_data!$AL16=Dashboard!$B$4),OR(Dashboard!$B$5="All",Raw_data!$AM16=Dashboard!$B$5),OR(Dashboard!$B$6="All",Raw_data!$AN16=Dashboard!$B$6),OR(Dashboard!$B$7="All",Raw_data!$AO16=Dashboard!$B$7),OR(Dashboard!$B$8="All",Raw_data!$AP16=Dashboard!$B$8),OR(Dashboard!$B$9="All",Raw_data!$AQ16=Dashboard!$B$9),OR(Dashboard!$B$10="All",Raw_data!$AF16=Dashboard!$B$10),OR(Raw_data!$F16="",Raw_data!$F16<=TODAY()))) | B16: =IFERROR(IF(Dashboard!$B$3="Weighted",Raw_data!$U16,Raw_data!$T16),"") | C16: =IFERROR(IF(Dashboard!$B$3="Weighted",Raw_data!$AB16,Raw_data!$AA16),"") | D16: =IF(OR(Raw_data!$J16="",Raw_data!$J16<=0,Raw_data!$K16=""),"",IF(Raw_data!$K16>TODAY(),0,DATEDIF(Raw_data!$K16,TODAY(),"M"))) | E16: =--(AND(Raw_data!$AF16="No",OR(Raw_data!$AG16<>"",Raw_data!$AJ16>0,Raw_data!$AK16<>""))) | F16: =--(OR(AND(ISNUMBER(B16),B16<0.5,OR(D16>=24,Raw_data!$I16>0)),Raw_data!$AE16=TRUE)) | G16: =IF(Dashboard!$B$11="Department",Raw_data!$AL16,IF(Dashboard!$B$11="Team",Raw_data!$AM16,IF(Dashboard!$B$11="Unit",Raw_data!$AN16,IF(Dashboard!$B$11="Legal entity",Raw_data!$AO16,IF(Dashboard!$B$11="Location",Raw_data!$AP16,Raw_data!$AQ16))))) | H16: =--(AND(ISNUMBER(B16),B16<0.5)) | I16: =IFERROR(MAX(0,(0.5-B16)*100),0)+IF(D16>=24,20,0)+IF(Raw_data!$I16>0,20,0)+IF(Raw_data!$AE16=TRUE,10,0) | J16: =IFERROR(CHOOSE(MATCH(Dashboard!$B$11,{"Department","Team","Unit","Legal entity","Location","Lead"},0),INDEX(Lists!$B$3:$B$20,ROW()-1),INDEX(Lists!$C$3:$C$146,ROW()-1),INDEX(Lists!$D$3:$D$67,ROW()-1),INDEX(Lists!$E$3:$E$5,ROW()-1),INDEX(Lists!$F$3:$F$12,ROW()-1),INDEX(Lists!$G$3:$G$126,ROW()-1)),"") | K16: =IF(J16="","",SUMPRODUCT(($A$2:$A$636=1)*($G$2:$G$636=J16))) | L16: =IF(J16="","",SUMPRODUCT(($A$2:$A$636=1)*($G$2:$G$636=J16)*(ISNUMBER($B$2:$B$636))*($B$2:$B$636<0.5))) | M16: =IFERROR(L16/K16,"") | N16: =IF(K16="","",M16+K16/100000+ROW()/100000000) | R16: =IF(A16=1,IFERROR(I16,0)+ROW()/100000000,-1E+99) | S16: =IF(A16=1,IFERROR(Raw_data!$T16,""),"") | T16: =IF(A16=1,IFERROR(Raw_data!$AA16,""),"") | U16: =IF(A16=1,IFERROR(Raw_data!$U16,""),"") | V16: =IF(A16=1,IFERROR(Raw_data!$AB16,""),"")
A17: =--(AND(OR(Dashboard!$B$4="All",Raw_data!$AL17=Dashboard!$B$4),OR(Dashboard!$B$5="All",Raw_data!$AM17=Dashboard!$B$5),OR(Dashboard!$B$6="All",Raw_data!$AN17=Dashboard!$B$6),OR(Dashboard!$B$7="All",Raw_data!$AO17=Dashboard!$B$7),OR(Dashboard!$B$8="All",Raw_data!$AP17=Dashboard!$B$8),OR(Dashboard!$B$9="All",Raw_data!$AQ17=Dashboard!$B$9),OR(Dashboard!$B$10="All",Raw_data!$AF17=Dashboard!$B$10),OR(Raw_data!$F17="",Raw_data!$F17<=TODAY()))) | B17: =IFERROR(IF(Dashboard!$B$3="Weighted",Raw_data!$U17,Raw_data!$T17),"") | C17: =IFERROR(IF(Dashboard!$B$3="Weighted",Raw_data!$AB17,Raw_data!$AA17),"") | D17: =IF(OR(Raw_data!$J17="",Raw_data!$J17<=0,Raw_data!$K17=""),"",IF(Raw_data!$K17>TODAY(),0,DATEDIF(Raw_data!$K17,TODAY(),"M"))) | E17: =--(AND(Raw_data!$AF17="No",OR(Raw_data!$AG17<>"",Raw_data!$AJ17>0,Raw_data!$AK17<>""))) | F17: =--(OR(AND(ISNUMBER(B17),B17<0.5,OR(D17>=24,Raw_data!$I17>0)),Raw_data!$AE17=TRUE)) | G17: =IF(Dashboard!$B$11="Department",Raw_data!$AL17,IF(Dashboard!$B$11="Team",Raw_data!$AM17,IF(Dashboard!$B$11="Unit",Raw_data!$AN17,IF(Dashboard!$B$11="Legal entity",Raw_data!$AO17,IF(Dashboard!$B$11="Location",Raw_data!$AP17,Raw_data!$AQ17))))) | H17: =--(AND(ISNUMBER(B17),B17<0.5)) | I17: =IFERROR(MAX(0,(0.5-B17)*100),0)+IF(D17>=24,20,0)+IF(Raw_data!$I17>0,20,0)+IF(Raw_data!$AE17=TRUE,10,0) | J17: =IFERROR(CHOOSE(MATCH(Dashboard!$B$11,{"Department","Team","Unit","Legal entity","Location","Lead"},0),INDEX(Lists!$B$3:$B$20,ROW()-1),INDEX(Lists!$C$3:$C$146,ROW()-1),INDEX(Lists!$D$3:$D$67,ROW()-1),INDEX(Lists!$E$3:$E$5,ROW()-1),INDEX(Lists!$F$3:$F$12,ROW()-1),INDEX(Lists!$G$3:$G$126,ROW()-1)),"") | K17: =IF(J17="","",SUMPRODUCT(($A$2:$A$636=1)*($G$2:$G$636=J17))) | L17: =IF(J17="","",SUMPRODUCT(($A$2:$A$636=1)*($G$2:$G$636=J17)*(ISNUMBER($B$2:$B$636))*($B$2:$B$636<0.5))) | M17: =IFERROR(L17/K17,"") | N17: =IF(K17="","",M17+K17/100000+ROW()/100000000) | R17: =IF(A17=1,IFERROR(I17,0)+ROW()/100000000,-1E+99) | S17: =IF(A17=1,IFERROR(Raw_data!$T17,""),"") | T17: =IF(A17=1,IFERROR(Raw_data!$AA17,""),"") | U17: =IF(A17=1,IFERROR(Raw_data!$U17,""),"") | V17: =IF(A17=1,IFERROR(Raw_data!$AB17,""),"")
A18: =--(AND(OR(Dashboard!$B$4="All",Raw_data!$AL18=Dashboard!$B$4),OR(Dashboard!$B$5="All",Raw_data!$AM18=Dashboard!$B$5),OR(Dashboard!$B$6="All",Raw_data!$AN18=Dashboard!$B$6),OR(Dashboard!$B$7="All",Raw_data!$AO18=Dashboard!$B$7),OR(Dashboard!$B$8="All",Raw_data!$AP18=Dashboard!$B$8),OR(Dashboard!$B$9="All",Raw_data!$AQ18=Dashboard!$B$9),OR(Dashboard!$B$10="All",Raw_data!$AF18=Dashboard!$B$10),OR(Raw_data!$F18="",Raw_data!$F18<=TODAY()))) | B18: =IFERROR(IF(Dashboard!$B$3="Weighted",Raw_data!$U18,Raw_data!$T18),"") | C18: =IFERROR(IF(Dashboard!$B$3="Weighted",Raw_data!$AB18,Raw_data!$AA18),"") | D18: =IF(OR(Raw_data!$J18="",Raw_data!$J18<=0,Raw_data!$K18=""),"",IF(Raw_data!$K18>TODAY(),0,DATEDIF(Raw_data!$K18,TODAY(),"M"))) | E18: =--(AND(Raw_data!$AF18="No",OR(Raw_data!$AG18<>"",Raw_data!$AJ18>0,Raw_data!$AK18<>""))) | F18: =--(OR(AND(ISNUMBER(B18),B18<0.5,OR(D18>=24,Raw_data!$I18>0)),Raw_data!$AE18=TRUE)) | G18: =IF(Dashboard!$B$11="Department",Raw_data!$AL18,IF(Dashboard!$B$11="Team",Raw_data!$AM18,IF(Dashboard!$B$11="Unit",Raw_data!$AN18,IF(Dashboard!$B$11="Legal entity",Raw_data!$AO18,IF(Dashboard!$B$11="Location",Raw_data!$AP18,Raw_data!$AQ18))))) | H18: =--(AND(ISNUMBER(B18),B18<0.5)) | I18: =IFERROR(MAX(0,(0.5-B18)*100),0)+IF(D18>=24,20,0)+IF(Raw_data!$I18>0,20,0)+IF(Raw_data!$AE18=TRUE,10,0) | J18: =IFERROR(CHOOSE(MATCH(Dashboard!$B$11,{"Department","Team","Unit","Legal entity","Location","Lead"},0),INDEX(Lists!$B$3:$B$20,ROW()-1),INDEX(Lists!$C$3:$C$146,ROW()-1),INDEX(Lists!$D$3:$D$67,ROW()-1),INDEX(Lists!$E$3:$E$5,ROW()-1),INDEX(Lists!$F$3:$F$12,ROW()-1),INDEX(Lists!$G$3:$G$126,ROW()-1)),"") | K18: =IF(J18="","",SUMPRODUCT(($A$2:$A$636=1)*($G$2:$G$636=J18))) | L18: =IF(J18="","",SUMPRODUCT(($A$2:$A$636=1)*($G$2:$G$636=J18)*(ISNUMBER($B$2:$B$636))*($B$2:$B$636<0.5))) | M18: =IFERROR(L18/K18,"") | N18: =IF(K18="","",M18+K18/100000+ROW()/100000000) | R18: =IF(A18=1,IFERROR(I18,0)+ROW()/100000000,-1E+99) | S18: =IF(A18=1,IFERROR(Raw_data!$T18,""),"") | T18: =IF(A18=1,IFERROR(Raw_data!$AA18,""),"") | U18: =IF(A18=1,IFERROR(Raw_data!$U18,""),"") | V18: =IF(A18=1,IFERROR(Raw_data!$AB18,""),"")
A19: =--(AND(OR(Dashboard!$B$4="All",Raw_data!$AL19=Dashboard!$B$4),OR(Dashboard!$B$5="All",Raw_data!$AM19=Dashboard!$B$5),OR(Dashboard!$B$6="All",Raw_data!$AN19=Dashboard!$B$6),OR(Dashboard!$B$7="All",Raw_data!$AO19=Dashboard!$B$7),OR(Dashboard!$B$8="All",Raw_data!$AP19=Dashboard!$B$8),OR(Dashboard!$B$9="All",Raw_data!$AQ19=Dashboard!$B$9),OR(Dashboard!$B$10="All",Raw_data!$AF19=Dashboard!$B$10),OR(Raw_data!$F19="",Raw_data!$F19<=TODAY()))) | B19: =IFERROR(IF(Dashboard!$B$3="Weighted",Raw_data!$U19,Raw_data!$T19),"") | C19: =IFERROR(IF(Dashboard!$B$3="Weighted",Raw_data!$AB19,Raw_data!$AA19),"") | D19: =IF(OR(Raw_data!$J19="",Raw_data!$J19<=0,Raw_data!$K19=""),"",IF(Raw_data!$K19>TODAY(),0,DATEDIF(Raw_data!$K19,TODAY(),"M"))) | E19: =--(AND(Raw_data!$AF19="No",OR(Raw_data!$AG19<>"",Raw_data!$AJ19>0,Raw_data!$AK19<>""))) | F19: =--(OR(AND(ISNUMBER(B19),B19<0.5,OR(D19>=24,Raw_data!$I19>0)),Raw_data!$AE19=TRUE)) | G19: =IF(Dashboard!$B$11="Department",Raw_data!$AL19,IF(Dashboard!$B$11="Team",Raw_data!$AM19,IF(Dashboard!$B$11="Unit",Raw_data!$AN19,IF(Dashboard!$B$11="Legal entity",Raw_data!$AO19,IF(Dashboard!$B$11="Location",Raw_data!$AP19,Raw_data!$AQ19))))) | H19: =--(AND(ISNUMBER(B19),B19<0.5)) | I19: =IFERROR(MAX(0,(0.5-B19)*100),0)+IF(D19>=24,20,0)+IF(Raw_data!$I19>0,20,0)+IF(Raw_data!$AE19=TRUE,10,0) | J19: =IFERROR(CHOOSE(MATCH(Dashboard!$B$11,{"Department","Team","Unit","Legal entity","Location","Lead"},0),INDEX(Lists!$B$3:$B$20,ROW()-1),INDEX(Lists!$C$3:$C$146,ROW()-1),INDEX(Lists!$D$3:$D$67,ROW()-1),INDEX(Lists!$E$3:$E$5,ROW()-1),INDEX(Lists!$F$3:$F$12,ROW()-1),INDEX(Lists!$G$3:$G$126,ROW()-1)),"") | K19: =IF(J19="","",SUMPRODUCT(($A$2:$A$636=1)*($G$2:$G$636=J19))) | L19: =IF(J19="","",SUMPRODUCT(($A$2:$A$636=1)*($G$2:$G$636=J19)*(ISNUMBER($B$2:$B$636))*($B$2:$B$636<0.5))) | M19: =IFERROR(L19/K19,"") | N19: =IF(K19="","",M19+K19/100000+ROW()/100000000) | R19: =IF(A19=1,IFERROR(I19,0)+ROW()/100000000,-1E+99) | S19: =IF(A19=1,IFERROR(Raw_data!$T19,""),"") | T19: =IF(A19=1,IFERROR(Raw_data!$AA19,""),"") | U19: =IF(A19=1,IFERROR(Raw_data!$U19,""),"") | V19: =IF(A19=1,IFERROR(Raw_data!$AB19,""),"")
A20: =--(AND(OR(Dashboard!$B$4="All",Raw_data!$AL20=Dashboard!$B$4),OR(Dashboard!$B$5="All",Raw_data!$AM20=Dashboard!$B$5),OR(Dashboard!$B$6="All",Raw_data!$AN20=Dashboard!$B$6),OR(Dashboard!$B$7="All",Raw_data!$AO20=Dashboard!$B$7),OR(Dashboard!$B$8="All",Raw_data!$AP20=Dashboard!$B$8),OR(Dashboard!$B$9="All",Raw_data!$AQ20=Dashboard!$B$9),OR(Dashboard!$B$10="All",Raw_data!$AF20=Dashboard!$B$10),OR(Raw_data!$F20="",Raw_data!$F20<=TODAY()))) | B20: =IFERROR(IF(Dashboard!$B$3="Weighted",Raw_data!$U20,Raw_data!$T20),"") | C20: =IFERROR(IF(Dashboard!$B$3="Weighted",Raw_data!$AB20,Raw_data!$AA20),"") | D20: =IF(OR(Raw_data!$J20="",Raw_data!$J20<=0,Raw_data!$K20=""),"",IF(Raw_data!$K20>TODAY(),0,DATEDIF(Raw_data!$K20,TODAY(),"M"))) | E20: =--(AND(Raw_data!$AF20="No",OR(Raw_data!$AG20<>"",Raw_data!$AJ20>0,Raw_data!$AK20<>""))) | F20: =--(OR(AND(ISNUMBER(B20),B20<0.5,OR(D20>=24,Raw_data!$I20>0)),Raw_data!$AE20=TRUE)) | G20: =IF(Dashboard!$B$11="Department",Raw_data!$AL20,IF(Dashboard!$B$11="Team",Raw_data!$AM20,IF(Dashboard!$B$11="Unit",Raw_data!$AN20,IF(Dashboard!$B$11="Legal entity",Raw_data!$AO20,IF(Dashboard!$B$11="Location",Raw_data!$AP20,Raw_data!$AQ20))))) | H20: =--(AND(ISNUMBER(B20),B20<0.5)) | I20: =IFERROR(MAX(0,(0.5-B20)*100),0)+IF(D20>=24,20,0)+IF(Raw_data!$I20>0,20,0)+IF(Raw_data!$AE20=TRUE,10,0) | J20: =IFERROR(CHOOSE(MATCH(Dashboard!$B$11,{"Department","Team","Unit","Legal entity","Location","Lead"},0),INDEX(Lists!$B$3:$B$20,ROW()-1),INDEX(Lists!$C$3:$C$146,ROW()-1),INDEX(Lists!$D$3:$D$67,ROW()-1),INDEX(Lists!$E$3:$E$5,ROW()-1),INDEX(Lists!$F$3:$F$12,ROW()-1),INDEX(Lists!$G$3:$G$126,ROW()-1)),"") | K20: =IF(J20="","",SUMPRODUCT(($A$2:$A$636=1)*($G$2:$G$636=J20))) | L20: =IF(J20="","",SUMPRODUCT(($A$2:$A$636=1)*($G$2:$G$636=J20)*(ISNUMBER($B$2:$B$636))*($B$2:$B$636<0.5))) | M20: =IFERROR(L20/K20,"") | N20: =IF(K20="","",M20+K20/100000+ROW()/100000000) | R20: =IF(A20=1,IFERROR(I20,0)+ROW()/100000000,-1E+99) | S20: =IF(A20=1,IFERROR(Raw_data!$T20,""),"") | T20: =IF(A20=1,IFERROR(Raw_data!$AA20,""),"") | U20: =IF(A20=1,IFERROR(Raw_data!$U20,""),"") | V20: =IF(A20=1,IFERROR(Raw_data!$AB20,""),"")
A21: =--(AND(OR(Dashboard!$B$4="All",Raw_data!$AL21=Dashboard!$B$4),OR(Dashboard!$B$5="All",Raw_data!$AM21=Dashboard!$B$5),OR(Dashboard!$B$6="All",Raw_data!$AN21=Dashboard!$B$6),OR(Dashboard!$B$7="All",Raw_data!$AO21=Dashboard!$B$7),OR(Dashboard!$B$8="All",Raw_data!$AP21=Dashboard!$B$8),OR(Dashboard!$B$9="All",Raw_data!$AQ21=Dashboard!$B$9),OR(Dashboard!$B$10="All",Raw_data!$AF21=Dashboard!$B$10),OR(Raw_data!$F21="",Raw_data!$F21<=TODAY()))) | B21: =IFERROR(IF(Dashboard!$B$3="Weighted",Raw_data!$U21,Raw_data!$T21),"") | C21: =IFERROR(IF(Dashboard!$B$3="Weighted",Raw_data!$AB21,Raw_data!$AA21),"") | D21: =IF(OR(Raw_data!$J21="",Raw_data!$J21<=0,Raw_data!$K21=""),"",IF(Raw_data!$K21>TODAY(),0,DATEDIF(Raw_data!$K21,TODAY(),"M"))) | E21: =--(AND(Raw_data!$AF21="No",OR(Raw_data!$AG21<>"",Raw_data!$AJ21>0,Raw_data!$AK21<>""))) | F21: =--(OR(AND(ISNUMBER(B21),B21<0.5,OR(D21>=24,Raw_data!$I21>0)),Raw_data!$AE21=TRUE)) | G21: =IF(Dashboard!$B$11="Department",Raw_data!$AL21,IF(Dashboard!$B$11="Team",Raw_data!$AM21,IF(Dashboard!$B$11="Unit",Raw_data!$AN21,IF(Dashboard!$B$11="Legal entity",Raw_data!$AO21,IF(Dashboard!$B$11="Location",Raw_data!$AP21,Raw_data!$AQ21))))) | H21: =--(AND(ISNUMBER(B21),B21<0.5)) | I21: =IFERROR(MAX(0,(0.5-B21)*100),0)+IF(D21>=24,20,0)+IF(Raw_data!$I21>0,20,0)+IF(Raw_data!$AE21=TRUE,10,0) | J21: =IFERROR(CHOOSE(MATCH(Dashboard!$B$11,{"Department","Team","Unit","Legal entity","Location","Lead"},0),INDEX(Lists!$B$3:$B$20,ROW()-1),INDEX(Lists!$C$3:$C$146,ROW()-1),INDEX(Lists!$D$3:$D$67,ROW()-1),INDEX(Lists!$E$3:$E$5,ROW()-1),INDEX(Lists!$F$3:$F$12,ROW()-1),INDEX(Lists!$G$3:$G$126,ROW()-1)),"") | K21: =IF(J21="","",SUMPRODUCT(($A$2:$A$636=1)*($G$2:$G$636=J21))) | L21: =IF(J21="","",SUMPRODUCT(($A$2:$A$636=1)*($G$2:$G$636=J21)*(ISNUMBER($B$2:$B$636))*($B$2:$B$636<0.5))) | M21: =IFERROR(L21/K21,"") | N21: =IF(K21="","",M21+K21/100000+ROW()/100000000) | R21: =IF(A21=1,IFERROR(I21,0)+ROW()/100000000,-1E+99) | S21: =IF(A21=1,IFERROR(Raw_data!$T21,""),"") | T21: =IF(A21=1,IFERROR(Raw_data!$AA21,""),"") | U21: =IF(A21=1,IFERROR(Raw_data!$U21,""),"") | V21: =IF(A21=1,IFERROR(Raw_data!$AB21,""),"")
A22: =--(AND(OR(Dashboard!$B$4="All",Raw_data!$AL22=Dashboard!$B$4),OR(Dashboard!$B$5="All",Raw_data!$AM22=Dashboard!$B$5),OR(Dashboard!$B$6="All",Raw_data!$AN22=Dashboard!$B$6),OR(Dashboard!$B$7="All",Raw_data!$AO22=Dashboard!$B$7),OR(Dashboard!$B$8="All",Raw_data!$AP22=Dashboard!$B$8),OR(Dashboard!$B$9="All",Raw_data!$AQ22=Dashboard!$B$9),OR(Dashboard!$B$10="All",Raw_data!$AF22=Dashboard!$B$10),OR(Raw_data!$F22="",Raw_data!$F22<=TODAY()))) | B22: =IFERROR(IF(Dashboard!$B$3="Weighted",Raw_data!$U22,Raw_data!$T22),"") | C22: =IFERROR(IF(Dashboard!$B$3="Weighted",Raw_data!$AB22,Raw_data!$AA22),"") | D22: =IF(OR(Raw_data!$J22="",Raw_data!$J22<=0,Raw_data!$K22=""),"",IF(Raw_data!$K22>TODAY(),0,DATEDIF(Raw_data!$K22,TODAY(),"M"))) | E22: =--(AND(Raw_data!$AF22="No",OR(Raw_data!$AG22<>"",Raw_data!$AJ22>0,Raw_data!$AK22<>""))) | F22: =--(OR(AND(ISNUMBER(B22),B22<0.5,OR(D22>=24,Raw_data!$I22>0)),Raw_data!$AE22=TRUE)) | G22: =IF(Dashboard!$B$11="Department",Raw_data!$AL22,IF(Dashboard!$B$11="Team",Raw_data!$AM22,IF(Dashboard!$B$11="Unit",Raw_data!$AN22,IF(Dashboard!$B$11="Legal entity",Raw_data!$AO22,IF(Dashboard!$B$11="Location",Raw_data!$AP22,Raw_data!$AQ22))))) | H22: =--(AND(ISNUMBER(B22),B22<0.5)) | I22: =IFERROR(MAX(0,(0.5-B22)*100),0)+IF(D22>=24,20,0)+IF(Raw_data!$I22>0,20,0)+IF(Raw_data!$AE22=TRUE,10,0) | J22: =IFERROR(CHOOSE(MATCH(Dashboard!$B$11,{"Department","Team","Unit","Legal entity","Location","Lead"},0),INDEX(Lists!$B$3:$B$20,ROW()-1),INDEX(Lists!$C$3:$C$146,ROW()-1),INDEX(Lists!$D$3:$D$67,ROW()-1),INDEX(Lists!$E$3:$E$5,ROW()-1),INDEX(Lists!$F$3:$F$12,ROW()-1),INDEX(Lists!$G$3:$G$126,ROW()-1)),"") | K22: =IF(J22="","",SUMPRODUCT(($A$2:$A$636=1)*($G$2:$G$636=J22))) | L22: =IF(J22="","",SUMPRODUCT(($A$2:$A$636=1)*($G$2:$G$636=J22)*(ISNUMBER($B$2:$B$636))*($B$2:$B$636<0.5))) | M22: =IFERROR(L22/K22,"") | N22: =IF(K22="","",M22+K22/100000+ROW()/100000000) | R22: =IF(A22=1,IFERROR(I22,0)+ROW()/100000000,-1E+99) | S22: =IF(A22=1,IFERROR(Raw_data!$T22,""),"") | T22: =IF(A22=1,IFERROR(Raw_data!$AA22,""),"") | U22: =IF(A22=1,IFERROR(Raw_data!$U22,""),"") | V22: =IF(A22=1,IFERROR(Raw_data!$AB22,""),"")
A23: =--(AND(OR(Dashboard!$B$4="All",Raw_data!$AL23=Dashboard!$B$4),OR(Dashboard!$B$5="All",Raw_data!$AM23=Dashboard!$B$5),OR(Dashboard!$B$6="All",Raw_data!$AN23=Dashboard!$B$6),OR(Dashboard!$B$7="All",Raw_data!$AO23=Dashboard!$B$7),OR(Dashboard!$B$8="All",Raw_data!$AP23=Dashboard!$B$8),OR(Dashboard!$B$9="All",Raw_data!$AQ23=Dashboard!$B$9),OR(Dashboard!$B$10="All",Raw_data!$AF23=Dashboard!$B$10),OR(Raw_data!$F23="",Raw_data!$F23<=TODAY()))) | B23: =IFERROR(IF(Dashboard!$B$3="Weighted",Raw_data!$U23,Raw_data!$T23),"") | C23: =IFERROR(IF(Dashboard!$B$3="Weighted",Raw_data!$AB23,Raw_data!$AA23),"") | D23: =IF(OR(Raw_data!$J23="",Raw_data!$J23<=0,Raw_data!$K23=""),"",IF(Raw_data!$K23>TODAY(),0,DATEDIF(Raw_data!$K23,TODAY(),"M"))) | E23: =--(AND(Raw_data!$AF23="No",OR(Raw_data!$AG23<>"",Raw_data!$AJ23>0,Raw_data!$AK23<>""))) | F23: =--(OR(AND(ISNUMBER(B23),B23<0.5,OR(D23>=24,Raw_data!$I23>0)),Raw_data!$AE23=TRUE)) | G23: =IF(Dashboard!$B$11="Department",Raw_data!$AL23,IF(Dashboard!$B$11="Team",Raw_data!$AM23,IF(Dashboard!$B$11="Unit",Raw_data!$AN23,IF(Dashboard!$B$11="Legal entity",Raw_data!$AO23,IF(Dashboard!$B$11="Location",Raw_data!$AP23,Raw_data!$AQ23))))) | H23: =--(AND(ISNUMBER(B23),B23<0.5)) | I23: =IFERROR(MAX(0,(0.5-B23)*100),0)+IF(D23>=24,20,0)+IF(Raw_data!$I23>0,20,0)+IF(Raw_data!$AE23=TRUE,10,0) | J23: =IFERROR(CHOOSE(MATCH(Dashboard!$B$11,{"Department","Team","Unit","Legal entity","Location","Lead"},0),INDEX(Lists!$B$3:$B$20,ROW()-1),INDEX(Lists!$C$3:$C$146,ROW()-1),INDEX(Lists!$D$3:$D$67,ROW()-1),INDEX(Lists!$E$3:$E$5,ROW()-1),INDEX(Lists!$F$3:$F$12,ROW()-1),INDEX(Lists!$G$3:$G$126,ROW()-1)),"") | K23: =IF(J23="","",SUMPRODUCT(($A$2:$A$636=1)*($G$2:$G$636=J23))) | L23: =IF(J23="","",SUMPRODUCT(($A$2:$A$636=1)*($G$2:$G$636=J23)*(ISNUMBER($B$2:$B$636))*($B$2:$B$636<0.5))) | M23: =IFERROR(L23/K23,"") | N23: =IF(K23="","",M23+K23/100000+ROW()/100000000) | R23: =IF(A23=1,IFERROR(I23,0)+ROW()/100000000,-1E+99) | S23: =IF(A23=1,IFERROR(Raw_data!$T23,""),"") | T23: =IF(A23=1,IFERROR(Raw_data!$AA23,""),"") | U23: =IF(A23=1,IFERROR(Raw_data!$U23,""),"") | V23: =IF(A23=1,IFERROR(Raw_data!$AB23,""),"")
... A636: =--(AND(OR(Dashboard!$B$4="All",Raw_data!$AL636=Dashboard!$B$4),OR(Dashboard!$B$5="All",Raw_data!$AM636=Dashboard!$B$5),OR(Dashboard!$B$6="All",Raw_data!$AN636=Dashboard!$B$6),OR(Dashboard!$B$7="All",Raw_data!$AO636=Dashboard!$B$7),OR(Dashboard!$B$8="All",Raw_data!$AP636=Dashboard!$B$8),OR(Dashboard!$B$9="All",Raw_data!$AQ636=Dashboard!$B$9),OR(Dashboard!$B$10="All",Raw_data!$AF636=Dashboard!$B$10),OR(Raw_data!$F636="",Raw_data!$F636<=TODAY()))) | B636: =IFERROR(IF(Dashboard!$B$3="Weighted",Raw_data!$U636,Raw_data!$T636),"") | C636: =IFERROR(IF(Dashboard!$B$3="Weighted",Raw_data!$AB636,Raw_data!$AA636),"") | D636: =IF(OR(Raw_data!$J636="",Raw_data!$J636<=0,Raw_data!$K636=""),"",IF(Raw_data!$K636>TODAY(),0,DATEDIF(Raw_data!$K636,TODAY(),"M"))) | E636: =--(AND(Raw_data!$AF636="No",OR(Raw_data!$AG636<>"",Raw_data!$AJ636>0,Raw_data!$AK636<>""))) | F636: =--(OR(AND(ISNUMBER(B636),B636<0.5,OR(D636>=24,Raw_data!$I636>0)),Raw_data!$AE636=TRUE)) | G636: =IF(Dashboard!$B$11="Department",Raw_data!$AL636,IF(Dashboard!$B$11="Team",Raw_data!$AM636,IF(Dashboard!$B$11="Unit",Raw_data!$AN636,IF(Dashboard!$B$11="Legal entity",Raw_data!$AO636,IF(Dashboard!$B$11="Location",Raw_data!$AP636,Raw_data!$AQ636))))) | H636: =--(AND(ISNUMBER(B636),B636<0.5)) | I636: =IFERROR(MAX(0,(0.5-B636)*100),0)+IF(D636>=24,20,0)+IF(Raw_data!$I636>0,20,0)+IF(Raw_data!$AE636=TRUE,10,0) | J636: =IFERROR(CHOOSE(MATCH(Dashboard!$B$11,{"Department","Team","Unit","Legal entity","Location","Lead"},0),INDEX(Lists!$B$3:$B$20,ROW()-1),INDEX(Lists!$C$3:$C$146,ROW()-1),INDEX(Lists!$D$3:$D$67,ROW()-1),INDEX(Lists!$E$3:$E$5,ROW()-1),INDEX(Lists!$F$3:$F$12,ROW()-1),INDEX(Lists!$G$3:$G$126,ROW()-1)),"") | K636: =IF(J636="","",SUMPRODUCT(($A$2:$A$636=1)*($G$2:$G$636=J636))) | L636: =IF(J636="","",SUMPRODUCT(($A$2:$A$636=1)*($G$2:$G$636=J636)*(ISNUMBER($B$2:$B$636))*($B$2:$B$636<0.5))) | M636: =IFERROR(L636/K636,"") | N636: =IF(K636="","",M636+K636/100000+ROW()/100000000) | R636: =IF(A636=1,IFERROR(I636,0)+ROW()/100000000,-1E+99) | S636: =IF(A636=1,IFERROR(Raw_data!$T636,""),"") | T636: =IF(A636=1,IFERROR(Raw_data!$AA636,""),"") | U636: =IF(A636=1,IFERROR(Raw_data!$U636,""),"") | V636: =IF(A636=1,IFERROR(Raw_data!$AB636,""),"")
J637: =IFERROR(CHOOSE(MATCH(Dashboard!$B$11,{"Department","Team","Unit","Legal entity","Location","Lead"},0),INDEX(Lists!$B$3:$B$20,ROW()-1),INDEX(Lists!$C$3:$C$146,ROW()-1),INDEX(Lists!$D$3:$D$67,ROW()-1),INDEX(Lists!$E$3:$E$5,ROW()-1),INDEX(Lists!$F$3:$F$12,ROW()-1),INDEX(Lists!$G$3:$G$126,ROW()-1)),"") | K637: =IF(J637="","",SUMPRODUCT(($A$2:$A$636=1)*($G$2:$G$636=J637))) | L637: =IF(J637="","",SUMPRODUCT(($A$2:$A$636=1)*($G$2:$G$636=J637)*(ISNUMBER($B$2:$B$636))*($B$2:$B$636<0.5))) | M637: =IFERROR(L637/K637,"") | N637: =IF(K637="","",M637+K637/100000+ROW()/100000000)
J638: =IFERROR(CHOOSE(MATCH(Dashboard!$B$11,{"Department","Team","Unit","Legal entity","Location","Lead"},0),INDEX(Lists!$B$3:$B$20,ROW()-1),INDEX(Lists!$C$3:$C$146,ROW()-1),INDEX(Lists!$D$3:$D$67,ROW()-1),INDEX(Lists!$E$3:$E$5,ROW()-1),INDEX(Lists!$F$3:$F$12,ROW()-1),INDEX(Lists!$G$3:$G$126,ROW()-1)),"") | K638: =IF(J638="","",SUMPRODUCT(($A$2:$A$636=1)*($G$2:$G$636=J638))) | L638: =IF(J638="","",SUMPRODUCT(($A$2:$A$636=1)*($G$2:$G$636=J638)*(ISNUMBER($B$2:$B$636))*($B$2:$B$636<0.5))) | M638: =IFERROR(L638/K638,"") | N638: =IF(K638="","",M638+K638/100000+ROW()/100000000)
J639: =IFERROR(CHOOSE(MATCH(Dashboard!$B$11,{"Department","Team","Unit","Legal entity","Location","Lead"},0),INDEX(Lists!$B$3:$B$20,ROW()-1),INDEX(Lists!$C$3:$C$146,ROW()-1),INDEX(Lists!$D$3:$D$67,ROW()-1),INDEX(Lists!$E$3:$E$5,ROW()-1),INDEX(Lists!$F$3:$F$12,ROW()-1),INDEX(Lists!$G$3:$G$126,ROW()-1)),"") | K639: =IF(J639="","",SUMPRODUCT(($A$2:$A$636=1)*($G$2:$G$636=J639))) | L639: =IF(J639="","",SUMPRODUCT(($A$2:$A$636=1)*($G$2:$G$636=J639)*(ISNUMBER($B$2:$B$636))*($B$2:$B$636<0.5))) | M639: =IFERROR(L639/K639,"") | N639: =IF(K639="","",M639+K639/100000+ROW()/100000000)
J640: =IFERROR(CHOOSE(MATCH(Dashboard!$B$11,{"Department","Team","Unit","Legal entity","Location","Lead"},0),INDEX(Lists!$B$3:$B$20,ROW()-1),INDEX(Lists!$C$3:$C$146,ROW()-1),INDEX(Lists!$D$3:$D$67,ROW()-1),INDEX(Lists!$E$3:$E$5,ROW()-1),INDEX(Lists!$F$3:$F$12,ROW()-1),INDEX(Lists!$G$3:$G$126,ROW()-1)),"") | K640: =IF(J640="","",SUMPRODUCT(($A$2:$A$636=1)*($G$2:$G$636=J640))) | L640: =IF(J640="","",SUMPRODUCT(($A$2:$A$636=1)*($G$2:$G$636=J640)*(ISNUMBER($B$2:$B$636))*($B$2:$B$636<0.5))) | M640: =IFERROR(L640/K640,"") | N640: =IF(K640="","",M640+K640/100000+ROW()/100000000)
J641: =IFERROR(CHOOSE(MATCH(Dashboard!$B$11,{"Department","Team","Unit","Legal entity","Location","Lead"},0),INDEX(Lists!$B$3:$B$20,ROW()-1),INDEX(Lists!$C$3:$C$146,ROW()-1),INDEX(Lists!$D$3:$D$67,ROW()-1),INDEX(Lists!$E$3:$E$5,ROW()-1),INDEX(Lists!$F$3:$F$12,ROW()-1),INDEX(Lists!$G$3:$G$126,ROW()-1)),"") | K641: =IF(J641="","",SUMPRODUCT(($A$2:$A$636=1)*($G$2:$G$636=J641))) | L641: =IF(J641="","",SUMPRODUCT(($A$2:$A$636=1)*($G$2:$G$636=J641)*(ISNUMBER($B$2:$B$636))*($B$2:$B$636<0.5))) | M641: =IFERROR(L641/K641,"") | N641: =IF(K641="","",M641+K641/100000+ROW()/100000000)
J642: =IFERROR(CHOOSE(MATCH(Dashboard!$B$11,{"Department","Team","Unit","Legal entity","Location","Lead"},0),INDEX(Lists!$B$3:$B$20,ROW()-1),INDEX(Lists!$C$3:$C$146,ROW()-1),INDEX(Lists!$D$3:$D$67,ROW()-1),INDEX(Lists!$E$3:$E$5,ROW()-1),INDEX(Lists!$F$3:$F$12,ROW()-1),INDEX(Lists!$G$3:$G$126,ROW()-1)),"") | K642: =IF(J642="","",SUMPRODUCT(($A$2:$A$636=1)*($G$2:$G$636=J642))) | L642: =IF(J642="","",SUMPRODUCT(($A$2:$A$636=1)*($G$2:$G$636=J642)*(ISNUMBER($B$2:$B$636))*($B$2:$B$636<0.5))) | M642: =IFERROR(L642/K642,"") | N642: =IF(K642="","",M642+K642/100000+ROW()/100000000)
J643: =IFERROR(CHOOSE(MATCH(Dashboard!$B$11,{"Department","Team","Unit","Legal entity","Location","Lead"},0),INDEX(Lists!$B$3:$B$20,ROW()-1),INDEX(Lists!$C$3:$C$146,ROW()-1),INDEX(Lists!$D$3:$D$67,ROW()-1),INDEX(Lists!$E$3:$E$5,ROW()-1),INDEX(Lists!$F$3:$F$12,ROW()-1),INDEX(Lists!$G$3:$G$126,ROW()-1)),"") | K643: =IF(J643="","",SUMPRODUCT(($A$2:$A$636=1)*($G$2:$G$636=J643))) | L643: =IF(J643="","",SUMPRODUCT(($A$2:$A$636=1)*($G$2:$G$636=J643)*(ISNUMBER($B$2:$B$636))*($B$2:$B$636<0.5))) | M643: =IFERROR(L643/K643,"") | N643: =IF(K643="","",M643+K643/100000+ROW()/100000000)
J644: =IFERROR(CHOOSE(MATCH(Dashboard!$B$11,{"Department","Team","Unit","Legal entity","Location","Lead"},0),INDEX(Lists!$B$3:$B$20,ROW()-1),INDEX(Lists!$C$3:$C$146,ROW()-1),INDEX(Lists!$D$3:$D$67,ROW()-1),INDEX(Lists!$E$3:$E$5,ROW()-1),INDEX(Lists!$F$3:$F$12,ROW()-1),INDEX(Lists!$G$3:$G$126,ROW()-1)),"") | K644: =IF(J644="","",SUMPRODUCT(($A$2:$A$636=1)*($G$2:$G$636=J644))) | L644: =IF(J644="","",SUMPRODUCT(($A$2:$A$636=1)*($G$2:$G$636=J644)*(ISNUMBER($B$2:$B$636))*($B$2:$B$636<0.5))) | M644: =IFERROR(L644/K644,"") | N644: =IF(K644="","",M644+K644/100000+ROW()/100000000)
J645: =IFERROR(CHOOSE(MATCH(Dashboard!$B$11,{"Department","Team","Unit","Legal entity","Location","Lead"},0),INDEX(Lists!$B$3:$B$20,ROW()-1),INDEX(Lists!$C$3:$C$146,ROW()-1),INDEX(Lists!$D$3:$D$67,ROW()-1),INDEX(Lists!$E$3:$E$5,ROW()-1),INDEX(Lists!$F$3:$F$12,ROW()-1),INDEX(Lists!$G$3:$G$126,ROW()-1)),"") | K645: =IF(J645="","",SUMPRODUCT(($A$2:$A$636=1)*($G$2:$G$636=J645))) | L645: =IF(J645="","",SUMPRODUCT(($A$2:$A$636=1)*($G$2:$G$636=J645)*(ISNUMBER($B$2:$B$636))*($B$2:$B$636<0.5))) | M645: =IFERROR(L645/K645,"") | N645: =IF(K645="","",M645+K645/100000+ROW()/100000000)
J646: =IFERROR(CHOOSE(MATCH(Dashboard!$B$11,{"Department","Team","Unit","Legal entity","Location","Lead"},0),INDEX(Lists!$B$3:$B$20,ROW()-1),INDEX(Lists!$C$3:$C$146,ROW()-1),INDEX(Lists!$D$3:$D$67,ROW()-1),INDEX(Lists!$E$3:$E$5,ROW()-1),INDEX(Lists!$F$3:$F$12,ROW()-1),INDEX(Lists!$G$3:$G$126,ROW()-1)),"") | K646: =IF(J646="","",SUMPRODUCT(($A$2:$A$636=1)*($G$2:$G$636=J646))) | L646: =IF(J646="","",SUMPRODUCT(($A$2:$A$636=1)*($G$2:$G$636=J646)*(ISNUMBER($B$2:$B$636))*($B$2:$B$636<0.5))) | M646: =IFERROR(L646/K646,"") | N646: =IF(K646="","",M646+K646/100000+ROW()/100000000)
J647: =IFERROR(CHOOSE(MATCH(Dashboard!$B$11,{"Department","Team","Unit","Legal entity","Location","Lead"},0),INDEX(Lists!$B$3:$B$20,ROW()-1),INDEX(Lists!$C$3:$C$146,ROW()-1),INDEX(Lists!$D$3:$D$67,ROW()-1),INDEX(Lists!$E$3:$E$5,ROW()-1),INDEX(Lists!$F$3:$F$12,ROW()-1),INDEX(Lists!$G$3:$G$126,ROW()-1)),"") | K647: =IF(J647="","",SUMPRODUCT(($A$2:$A$636=1)*($G$2:$G$636=J647))) | L647: =IF(J647="","",SUMPRODUCT(($A$2:$A$636=1)*($G$2:$G$636=J647)*(ISNUMBER($B$2:$B$636))*($B$2:$B$636<0.5))) | M647: =IFERROR(L647/K647,"") | N647: =IF(K647="","",M647+K647/100000+ROW()/100000000)
J648: =IFERROR(CHOOSE(MATCH(Dashboard!$B$11,{"Department","Team","Unit","Legal entity","Location","Lead"},0),INDEX(Lists!$B$3:$B$20,ROW()-1),INDEX(Lists!$C$3:$C$146,ROW()-1),INDEX(Lists!$D$3:$D$67,ROW()-1),INDEX(Lists!$E$3:$E$5,ROW()-1),INDEX(Lists!$F$3:$F$12,ROW()-1),INDEX(Lists!$G$3:$G$126,ROW()-1)),"") | K648: =IF(J648="","",SUMPRODUCT(($A$2:$A$636=1)*($G$2:$G$636=J648))) | L648: =IF(J648="","",SUMPRODUCT(($A$2:$A$636=1)*($G$2:$G$636=J648)*(ISNUMBER($B$2:$B$636))*($B$2:$B$636<0.5))) | M648: =IFERROR(L648/K648,"") | N648: =IF(K648="","",M648+K648/100000+ROW()/100000000)
... J1001: =IFERROR(CHOOSE(MATCH(Dashboard!$B$11,{"Department","Team","Unit","Legal entity","Location","Lead"},0),INDEX(Lists!$B$3:$B$20,ROW()-1),INDEX(Lists!$C$3:$C$146,ROW()-1),INDEX(Lists!$D$3:$D$67,ROW()-1),INDEX(Lists!$E$3:$E$5,ROW()-1),INDEX(Lists!$F$3:$F$12,ROW()-1),INDEX(Lists!$G$3:$G$126,ROW()-1)),"") | K1001: =IF(J1001="","",SUMPRODUCT(($A$2:$A$636=1)*($G$2:$G$636=J1001))) | L1001: =IF(J1001="","",SUMPRODUCT(($A$2:$A$636=1)*($G$2:$G$636=J1001)*(ISNUMBER($B$2:$B$636))*($B$2:$B$636<0.5))) | M1001: =IFERROR(L1001/K1001,"") | N1001: =IF(K1001="","",M1001+K1001/100000+ROW()/100000000)

Sheet Dashboard
A1: Internal Consultant Data Quality Dashboard
A3: Metric_type | B3: Weighted | D3: Selected metric | E3: =B3
A4: Department | B4: All
A5: Team | B5: All | D5: Consultants (filtered) | E5: =SUM(Model!$A$2:$A$636) | H5: Ongoing >=24 months | I5: =SUMPRODUCT((Model!$A$2:$A$636=1)*(Raw_data!$J$2:$J$636>0)*(Model!$D$2:$D$636>=24))
A6: Unit | B6: All | D6: Weighted median since entry | E6: =IFERROR(MEDIAN(Model!$U$2:$U$636),"") | H6: Invalid-date consultants | I6: =SUMPRODUCT((Model!$A$2:$A$636=1)*(Raw_data!$I$2:$I$636>0))
A7: Legal_entity | B7: All | D7: Absolute median since entry | E7: =IFERROR(MEDIAN(Model!$S$2:$S$636),"") | H7: Anomaly consultants | I7: =SUMPRODUCT((Model!$A$2:$A$636=1)*(Model!$F$2:$F$636=1))
A8: Location | B8: All | D8: Weighted median before entry | E8: =IFERROR(MEDIAN(Model!$V$2:$V$636),"")
A9: Lead | B9: All | D9: Absolute median before entry | E9: =IFERROR(MEDIAN(Model!$T$2:$T$636),"")
A10: Is_available | B10: All
A11: Segment_dimension | B11: Department
A13: Coverage since entry bands | B13: Consultants | D13: Coverage before entry bands | E13: Consultants | H13: Ongoing age buckets | I13: Consultants
A14: <0.3 | B14: =SUMPRODUCT((Model!$A$2:$A$636=1)*(Model!$B$2:$B$636<0.3)*(ISNUMBER(Model!$B$2:$B$636))) | D14: <0.3 | E14: =SUMPRODUCT((Model!$A$2:$A$636=1)*(Model!$C$2:$C$636<0.3)*(ISNUMBER(Model!$C$2:$C$636))) | H14: <12m | I14: =SUMPRODUCT((Model!$A$2:$A$636=1)*(Raw_data!$J$2:$J$636>0)*(Model!$D$2:$D$636<>"")*(Model!$D$2:$D$636<12))
A15: 0.3-0.49 | B15: =SUMPRODUCT((Model!$A$2:$A$636=1)*(Model!$B$2:$B$636>=0.3)*(Model!$B$2:$B$636<0.5)) | D15: 0.3-0.49 | E15: =SUMPRODUCT((Model!$A$2:$A$636=1)*(Model!$C$2:$C$636>=0.3)*(Model!$C$2:$C$636<0.5)) | H15: 12-24m | I15: =SUMPRODUCT((Model!$A$2:$A$636=1)*(Raw_data!$J$2:$J$636>0)*(Model!$D$2:$D$636>=12)*(Model!$D$2:$D$636<24))
A16: 0.5-0.79 | B16: =SUMPRODUCT((Model!$A$2:$A$636=1)*(Model!$B$2:$B$636>=0.5)*(Model!$B$2:$B$636<0.8)) | D16: 0.5-0.79 | E16: =SUMPRODUCT((Model!$A$2:$A$636=1)*(Model!$C$2:$C$636>=0.5)*(Model!$C$2:$C$636<0.8)) | H16: >24m | I16: =SUMPRODUCT((Model!$A$2:$A$636=1)*(Raw_data!$J$2:$J$636>0)*(Model!$D$2:$D$636>=24))
A17: >=0.8 | B17: =SUMPRODUCT((Model!$A$2:$A$636=1)*(ISNUMBER(Model!$B$2:$B$636))*(Model!$B$2:$B$636>=0.8)) | D17: >=0.8 | E17: =SUMPRODUCT((Model!$A$2:$A$636=1)*(ISNUMBER(Model!$C$2:$C$636))*(Model!$C$2:$C$636>=0.8))
A21: Segment hotspot (Top 10 by low coverage rate)
A22: Segment | B22: Low coverage rate | C22: Consultants
A23: =Model!$O$2 | B23: =Model!$P$2 | C23: =Model!$Q$2 | X23: =IF(LEN(A23)<=26,A23,LEFT(A23,23)&"...")
A24: =Model!$O$3 | B24: =Model!$P$3 | C24: =Model!$Q$3 | X24: =IF(LEN(A24)<=26,A24,LEFT(A24,23)&"...")
A25: =Model!$O$4 | B25: =Model!$P$4 | C25: =Model!$Q$4 | X25: =IF(LEN(A25)<=26,A25,LEFT(A25,23)&"...")
A26: =Model!$O$5 | B26: =Model!$P$5 | C26: =Model!$Q$5 | X26: =IF(LEN(A26)<=26,A26,LEFT(A26,23)&"...")
A27: =Model!$O$6 | B27: =Model!$P$6 | C27: =Model!$Q$6 | X27: =IF(LEN(A27)<=26,A27,LEFT(A27,23)&"...")
A28: =Model!$O$7 | B28: =Model!$P$7 | C28: =Model!$Q$7 | X28: =IF(LEN(A28)<=26,A28,LEFT(A28,23)&"...")
A29: =Model!$O$8 | B29: =Model!$P$8 | C29: =Model!$Q$8 | X29: =IF(LEN(A29)<=26,A29,LEFT(A29,23)&"...")
A30: =Model!$O$9 | B30: =Model!$P$9 | C30: =Model!$Q$9 | X30: =IF(LEN(A30)<=26,A30,LEFT(A30,23)&"...")
A31: =Model!$O$10 | B31: =Model!$P$10 | C31: =Model!$Q$10 | X31: =IF(LEN(A31)<=26,A31,LEFT(A31,23)&"...")
A32: =Model!$O$11 | B32: =Model!$P$11 | C32: =Model!$Q$11 | X32: =IF(LEN(A32)<=26,A32,LEFT(A32,23)&"...")
A35: Filtered consultant list (anomaly-first order)
A36: Full_name | B36: Entry_date | C36: Url | D36: Department | E36: Team | F36: Lead | G36: Total_engagements | H36: Since_ratio | I36: Before_ratio | J36: Ongoing_age_m | K36: rank_key
A37: =IF($K37="","",INDEX(Raw_data!$D$2:$D$636,MATCH($K37,Model!$R$2:$R$636,0))) | B37: =IF($K37="","",INDEX(Raw_data!$F$2:$F$636,MATCH($K37,Model!$R$2:$R$636,0))) | C37: =IF($K37="","",HYPERLINK(INDEX(Raw_data!$C$2:$C$636,MATCH($K37,Model!$R$2:$R$636,0)),INDEX(Raw_data!$C$2:$C$636,MATCH($K37,Model!$R$2:$R$636,0)))) | D37: =IF($K37="","",INDEX(Raw_data!$AL$2:$AL$636,MATCH($K37,Model!$R$2:$R$636,0))) | E37: =IF($K37="","",INDEX(Raw_data!$AM$2:$AM$636,MATCH($K37,Model!$R$2:$R$636,0))) | F37: =IF($K37="","",INDEX(Raw_data!$AQ$2:$AQ$636,MATCH($K37,Model!$R$2:$R$636,0))) | G37: =IF($K37="","",INDEX(Raw_data!$H$2:$H$636,MATCH($K37,Model!$R$2:$R$636,0))) | H37: =IF($K37="","",INDEX(Model!$B$2:$B$636,MATCH($K37,Model!$R$2:$R$636,0))) | I37: =IF($K37="","",INDEX(Model!$C$2:$C$636,MATCH($K37,Model!$R$2:$R$636,0))) | J37: =IF($K37="","",INDEX(Model!$D$2:$D$636,MATCH($K37,Model!$R$2:$R$636,0))) | K37: =IF(1<=$E$5,LARGE(Model!$R$2:$R$636,1),"")
A38: =IF($K38="","",INDEX(Raw_data!$D$2:$D$636,MATCH($K38,Model!$R$2:$R$636,0))) | B38: =IF($K38="","",INDEX(Raw_data!$F$2:$F$636,MATCH($K38,Model!$R$2:$R$636,0))) | C38: =IF($K38="","",HYPERLINK(INDEX(Raw_data!$C$2:$C$636,MATCH($K38,Model!$R$2:$R$636,0)),INDEX(Raw_data!$C$2:$C$636,MATCH($K38,Model!$R$2:$R$636,0)))) | D38: =IF($K38="","",INDEX(Raw_data!$AL$2:$AL$636,MATCH($K38,Model!$R$2:$R$636,0))) | E38: =IF($K38="","",INDEX(Raw_data!$AM$2:$AM$636,MATCH($K38,Model!$R$2:$R$636,0))) | F38: =IF($K38="","",INDEX(Raw_data!$AQ$2:$AQ$636,MATCH($K38,Model!$R$2:$R$636,0))) | G38: =IF($K38="","",INDEX(Raw_data!$H$2:$H$636,MATCH($K38,Model!$R$2:$R$636,0))) | H38: =IF($K38="","",INDEX(Model!$B$2:$B$636,MATCH($K38,Model!$R$2:$R$636,0))) | I38: =IF($K38="","",INDEX(Model!$C$2:$C$636,MATCH($K38,Model!$R$2:$R$636,0))) | J38: =IF($K38="","",INDEX(Model!$D$2:$D$636,MATCH($K38,Model!$R$2:$R$636,0))) | K38: =IF(2<=$E$5,LARGE(Model!$R$2:$R$636,2),"")
A39: =IF($K39="","",INDEX(Raw_data!$D$2:$D$636,MATCH($K39,Model!$R$2:$R$636,0))) | B39: =IF($K39="","",INDEX(Raw_data!$F$2:$F$636,MATCH($K39,Model!$R$2:$R$636,0))) | C39: =IF($K39="","",HYPERLINK(INDEX(Raw_data!$C$2:$C$636,MATCH($K39,Model!$R$2:$R$636,0)),INDEX(Raw_data!$C$2:$C$636,MATCH($K39,Model!$R$2:$R$636,0)))) | D39: =IF($K39="","",INDEX(Raw_data!$AL$2:$AL$636,MATCH($K39,Model!$R$2:$R$636,0))) | E39: =IF($K39="","",INDEX(Raw_data!$AM$2:$AM$636,MATCH($K39,Model!$R$2:$R$636,0))) | F39: =IF($K39="","",INDEX(Raw_data!$AQ$2:$AQ$636,MATCH($K39,Model!$R$2:$R$636,0))) | G39: =IF($K39="","",INDEX(Raw_data!$H$2:$H$636,MATCH($K39,Model!$R$2:$R$636,0))) | H39: =IF($K39="","",INDEX(Model!$B$2:$B$636,MATCH($K39,Model!$R$2:$R$636,0))) | I39: =IF($K39="","",INDEX(Model!$C$2:$C$636,MATCH($K39,Model!$R$2:$R$636,0))) | J39: =IF($K39="","",INDEX(Model!$D$2:$D$636,MATCH($K39,Model!$R$2:$R$636,0))) | K39: =IF(3<=$E$5,LARGE(Model!$R$2:$R$636,3),"")
A40: =IF($K40="","",INDEX(Raw_data!$D$2:$D$636,MATCH($K40,Model!$R$2:$R$636,0))) | B40: =IF($K40="","",INDEX(Raw_data!$F$2:$F$636,MATCH($K40,Model!$R$2:$R$636,0))) | C40: =IF($K40="","",HYPERLINK(INDEX(Raw_data!$C$2:$C$636,MATCH($K40,Model!$R$2:$R$636,0)),INDEX(Raw_data!$C$2:$C$636,MATCH($K40,Model!$R$2:$R$636,0)))) | D40: =IF($K40="","",INDEX(Raw_data!$AL$2:$AL$636,MATCH($K40,Model!$R$2:$R$636,0))) | E40: =IF($K40="","",INDEX(Raw_data!$AM$2:$AM$636,MATCH($K40,Model!$R$2:$R$636,0))) | F40: =IF($K40="","",INDEX(Raw_data!$AQ$2:$AQ$636,MATCH($K40,Model!$R$2:$R$636,0))) | G40: =IF($K40="","",INDEX(Raw_data!$H$2:$H$636,MATCH($K40,Model!$R$2:$R$636,0))) | H40: =IF($K40="","",INDEX(Model!$B$2:$B$636,MATCH($K40,Model!$R$2:$R$636,0))) | I40: =IF($K40="","",INDEX(Model!$C$2:$C$636,MATCH($K40,Model!$R$2:$R$636,0))) | J40: =IF($K40="","",INDEX(Model!$D$2:$D$636,MATCH($K40,Model!$R$2:$R$636,0))) | K40: =IF(4<=$E$5,LARGE(Model!$R$2:$R$636,4),"")
A41: =IF($K41="","",INDEX(Raw_data!$D$2:$D$636,MATCH($K41,Model!$R$2:$R$636,0))) | B41: =IF($K41="","",INDEX(Raw_data!$F$2:$F$636,MATCH($K41,Model!$R$2:$R$636,0))) | C41: =IF($K41="","",HYPERLINK(INDEX(Raw_data!$C$2:$C$636,MATCH($K41,Model!$R$2:$R$636,0)),INDEX(Raw_data!$C$2:$C$636,MATCH($K41,Model!$R$2:$R$636,0)))) | D41: =IF($K41="","",INDEX(Raw_data!$AL$2:$AL$636,MATCH($K41,Model!$R$2:$R$636,0))) | E41: =IF($K41="","",INDEX(Raw_data!$AM$2:$AM$636,MATCH($K41,Model!$R$2:$R$636,0))) | F41: =IF($K41="","",INDEX(Raw_data!$AQ$2:$AQ$636,MATCH($K41,Model!$R$2:$R$636,0))) | G41: =IF($K41="","",INDEX(Raw_data!$H$2:$H$636,MATCH($K41,Model!$R$2:$R$636,0))) | H41: =IF($K41="","",INDEX(Model!$B$2:$B$636,MATCH($K41,Model!$R$2:$R$636,0))) | I41: =IF($K41="","",INDEX(Model!$C$2:$C$636,MATCH($K41,Model!$R$2:$R$636,0))) | J41: =IF($K41="","",INDEX(Model!$D$2:$D$636,MATCH($K41,Model!$R$2:$R$636,0))) | K41: =IF(5<=$E$5,LARGE(Model!$R$2:$R$636,5),"")
A42: =IF($K42="","",INDEX(Raw_data!$D$2:$D$636,MATCH($K42,Model!$R$2:$R$636,0))) | B42: =IF($K42="","",INDEX(Raw_data!$F$2:$F$636,MATCH($K42,Model!$R$2:$R$636,0))) | C42: =IF($K42="","",HYPERLINK(INDEX(Raw_data!$C$2:$C$636,MATCH($K42,Model!$R$2:$R$636,0)),INDEX(Raw_data!$C$2:$C$636,MATCH($K42,Model!$R$2:$R$636,0)))) | D42: =IF($K42="","",INDEX(Raw_data!$AL$2:$AL$636,MATCH($K42,Model!$R$2:$R$636,0))) | E42: =IF($K42="","",INDEX(Raw_data!$AM$2:$AM$636,MATCH($K42,Model!$R$2:$R$636,0))) | F42: =IF($K42="","",INDEX(Raw_data!$AQ$2:$AQ$636,MATCH($K42,Model!$R$2:$R$636,0))) | G42: =IF($K42="","",INDEX(Raw_data!$H$2:$H$636,MATCH($K42,Model!$R$2:$R$636,0))) | H42: =IF($K42="","",INDEX(Model!$B$2:$B$636,MATCH($K42,Model!$R$2:$R$636,0))) | I42: =IF($K42="","",INDEX(Model!$C$2:$C$636,MATCH($K42,Model!$R$2:$R$636,0))) | J42: =IF($K42="","",INDEX(Model!$D$2:$D$636,MATCH($K42,Model!$R$2:$R$636,0))) | K42: =IF(6<=$E$5,LARGE(Model!$R$2:$R$636,6),"")
A43: =IF($K43="","",INDEX(Raw_data!$D$2:$D$636,MATCH($K43,Model!$R$2:$R$636,0))) | B43: =IF($K43="","",INDEX(Raw_data!$F$2:$F$636,MATCH($K43,Model!$R$2:$R$636,0))) | C43: =IF($K43="","",HYPERLINK(INDEX(Raw_data!$C$2:$C$636,MATCH($K43,Model!$R$2:$R$636,0)),INDEX(Raw_data!$C$2:$C$636,MATCH($K43,Model!$R$2:$R$636,0)))) | D43: =IF($K43="","",INDEX(Raw_data!$AL$2:$AL$636,MATCH($K43,Model!$R$2:$R$636,0))) | E43: =IF($K43="","",INDEX(Raw_data!$AM$2:$AM$636,MATCH($K43,Model!$R$2:$R$636,0))) | F43: =IF($K43="","",INDEX(Raw_data!$AQ$2:$AQ$636,MATCH($K43,Model!$R$2:$R$636,0))) | G43: =IF($K43="","",INDEX(Raw_data!$H$2:$H$636,MATCH($K43,Model!$R$2:$R$636,0))) | H43: =IF($K43="","",INDEX(Model!$B$2:$B$636,MATCH($K43,Model!$R$2:$R$636,0))) | I43: =IF($K43="","",INDEX(Model!$C$2:$C$636,MATCH($K43,Model!$R$2:$R$636,0))) | J43: =IF($K43="","",INDEX(Model!$D$2:$D$636,MATCH($K43,Model!$R$2:$R$636,0))) | K43: =IF(7<=$E$5,LARGE(Model!$R$2:$R$636,7),"")
A44: =IF($K44="","",INDEX(Raw_data!$D$2:$D$636,MATCH($K44,Model!$R$2:$R$636,0))) | B44: =IF($K44="","",INDEX(Raw_data!$F$2:$F$636,MATCH($K44,Model!$R$2:$R$636,0))) | C44: =IF($K44="","",HYPERLINK(INDEX(Raw_data!$C$2:$C$636,MATCH($K44,Model!$R$2:$R$636,0)),INDEX(Raw_data!$C$2:$C$636,MATCH($K44,Model!$R$2:$R$636,0)))) | D44: =IF($K44="","",INDEX(Raw_data!$AL$2:$AL$636,MATCH($K44,Model!$R$2:$R$636,0))) | E44: =IF($K44="","",INDEX(Raw_data!$AM$2:$AM$636,MATCH($K44,Model!$R$2:$R$636,0))) | F44: =IF($K44="","",INDEX(Raw_data!$AQ$2:$AQ$636,MATCH($K44,Model!$R$2:$R$636,0))) | G44: =IF($K44="","",INDEX(Raw_data!$H$2:$H$636,MATCH($K44,Model!$R$2:$R$636,0))) | H44: =IF($K44="","",INDEX(Model!$B$2:$B$636,MATCH($K44,Model!$R$2:$R$636,0))) | I44: =IF($K44="","",INDEX(Model!$C$2:$C$636,MATCH($K44,Model!$R$2:$R$636,0))) | J44: =IF($K44="","",INDEX(Model!$D$2:$D$636,MATCH($K44,Model!$R$2:$R$636,0))) | K44: =IF(8<=$E$5,LARGE(Model!$R$2:$R$636,8),"")
A45: =IF($K45="","",INDEX(Raw_data!$D$2:$D$636,MATCH($K45,Model!$R$2:$R$636,0))) | B45: =IF($K45="","",INDEX(Raw_data!$F$2:$F$636,MATCH($K45,Model!$R$2:$R$636,0))) | C45: =IF($K45="","",HYPERLINK(INDEX(Raw_data!$C$2:$C$636,MATCH($K45,Model!$R$2:$R$636,0)),INDEX(Raw_data!$C$2:$C$636,MATCH($K45,Model!$R$2:$R$636,0)))) | D45: =IF($K45="","",INDEX(Raw_data!$AL$2:$AL$636,MATCH($K45,Model!$R$2:$R$636,0))) | E45: =IF($K45="","",INDEX(Raw_data!$AM$2:$AM$636,MATCH($K45,Model!$R$2:$R$636,0))) | F45: =IF($K45="","",INDEX(Raw_data!$AQ$2:$AQ$636,MATCH($K45,Model!$R$2:$R$636,0))) | G45: =IF($K45="","",INDEX(Raw_data!$H$2:$H$636,MATCH($K45,Model!$R$2:$R$636,0))) | H45: =IF($K45="","",INDEX(Model!$B$2:$B$636,MATCH($K45,Model!$R$2:$R$636,0))) | I45: =IF($K45="","",INDEX(Model!$C$2:$C$636,MATCH($K45,Model!$R$2:$R$636,0))) | J45: =IF($K45="","",INDEX(Model!$D$2:$D$636,MATCH($K45,Model!$R$2:$R$636,0))) | K45: =IF(9<=$E$5,LARGE(Model!$R$2:$R$636,9),"")
A46: =IF($K46="","",INDEX(Raw_data!$D$2:$D$636,MATCH($K46,Model!$R$2:$R$636,0))) | B46: =IF($K46="","",INDEX(Raw_data!$F$2:$F$636,MATCH($K46,Model!$R$2:$R$636,0))) | C46: =IF($K46="","",HYPERLINK(INDEX(Raw_data!$C$2:$C$636,MATCH($K46,Model!$R$2:$R$636,0)),INDEX(Raw_data!$C$2:$C$636,MATCH($K46,Model!$R$2:$R$636,0)))) | D46: =IF($K46="","",INDEX(Raw_data!$AL$2:$AL$636,MATCH($K46,Model!$R$2:$R$636,0))) | E46: =IF($K46="","",INDEX(Raw_data!$AM$2:$AM$636,MATCH($K46,Model!$R$2:$R$636,0))) | F46: =IF($K46="","",INDEX(Raw_data!$AQ$2:$AQ$636,MATCH($K46,Model!$R$2:$R$636,0))) | G46: =IF($K46="","",INDEX(Raw_data!$H$2:$H$636,MATCH($K46,Model!$R$2:$R$636,0))) | H46: =IF($K46="","",INDEX(Model!$B$2:$B$636,MATCH($K46,Model!$R$2:$R$636,0))) | I46: =IF($K46="","",INDEX(Model!$C$2:$C$636,MATCH($K46,Model!$R$2:$R$636,0))) | J46: =IF($K46="","",INDEX(Model!$D$2:$D$636,MATCH($K46,Model!$R$2:$R$636,0))) | K46: =IF(10<=$E$5,LARGE(Model!$R$2:$R$636,10),"")
A47: =IF($K47="","",INDEX(Raw_data!$D$2:$D$636,MATCH($K47,Model!$R$2:$R$636,0))) | B47: =IF($K47="","",INDEX(Raw_data!$F$2:$F$636,MATCH($K47,Model!$R$2:$R$636,0))) | C47: =IF($K47="","",HYPERLINK(INDEX(Raw_data!$C$2:$C$636,MATCH($K47,Model!$R$2:$R$636,0)),INDEX(Raw_data!$C$2:$C$636,MATCH($K47,Model!$R$2:$R$636,0)))) | D47: =IF($K47="","",INDEX(Raw_data!$AL$2:$AL$636,MATCH($K47,Model!$R$2:$R$636,0))) | E47: =IF($K47="","",INDEX(Raw_data!$AM$2:$AM$636,MATCH($K47,Model!$R$2:$R$636,0))) | F47: =IF($K47="","",INDEX(Raw_data!$AQ$2:$AQ$636,MATCH($K47,Model!$R$2:$R$636,0))) | G47: =IF($K47="","",INDEX(Raw_data!$H$2:$H$636,MATCH($K47,Model!$R$2:$R$636,0))) | H47: =IF($K47="","",INDEX(Model!$B$2:$B$636,MATCH($K47,Model!$R$2:$R$636,0))) | I47: =IF($K47="","",INDEX(Model!$C$2:$C$636,MATCH($K47,Model!$R$2:$R$636,0))) | J47: =IF($K47="","",INDEX(Model!$D$2:$D$636,MATCH($K47,Model!$R$2:$R$636,0))) | K47: =IF(11<=$E$5,LARGE(Model!$R$2:$R$636,11),"")
A48: =IF($K48="","",INDEX(Raw_data!$D$2:$D$636,MATCH($K48,Model!$R$2:$R$636,0))) | B48: =IF($K48="","",INDEX(Raw_data!$F$2:$F$636,MATCH($K48,Model!$R$2:$R$636,0))) | C48: =IF($K48="","",HYPERLINK(INDEX(Raw_data!$C$2:$C$636,MATCH($K48,Model!$R$2:$R$636,0)),INDEX(Raw_data!$C$2:$C$636,MATCH($K48,Model!$R$2:$R$636,0)))) | D48: =IF($K48="","",INDEX(Raw_data!$AL$2:$AL$636,MATCH($K48,Model!$R$2:$R$636,0))) | E48: =IF($K48="","",INDEX(Raw_data!$AM$2:$AM$636,MATCH($K48,Model!$R$2:$R$636,0))) | F48: =IF($K48="","",INDEX(Raw_data!$AQ$2:$AQ$636,MATCH($K48,Model!$R$2:$R$636,0))) | G48: =IF($K48="","",INDEX(Raw_data!$H$2:$H$636,MATCH($K48,Model!$R$2:$R$636,0))) | H48: =IF($K48="","",INDEX(Model!$B$2:$B$636,MATCH($K48,Model!$R$2:$R$636,0))) | I48: =IF($K48="","",INDEX(Model!$C$2:$C$636,MATCH($K48,Model!$R$2:$R$636,0))) | J48: =IF($K48="","",INDEX(Model!$D$2:$D$636,MATCH($K48,Model!$R$2:$R$636,0))) | K48: =IF(12<=$E$5,LARGE(Model!$R$2:$R$636,12),"")
A49: =IF($K49="","",INDEX(Raw_data!$D$2:$D$636,MATCH($K49,Model!$R$2:$R$636,0))) | B49: =IF($K49="","",INDEX(Raw_data!$F$2:$F$636,MATCH($K49,Model!$R$2:$R$636,0))) | C49: =IF($K49="","",HYPERLINK(INDEX(Raw_data!$C$2:$C$636,MATCH($K49,Model!$R$2:$R$636,0)),INDEX(Raw_data!$C$2:$C$636,MATCH($K49,Model!$R$2:$R$636,0)))) | D49: =IF($K49="","",INDEX(Raw_data!$AL$2:$AL$636,MATCH($K49,Model!$R$2:$R$636,0))) | E49: =IF($K49="","",INDEX(Raw_data!$AM$2:$AM$636,MATCH($K49,Model!$R$2:$R$636,0))) | F49: =IF($K49="","",INDEX(Raw_data!$AQ$2:$AQ$636,MATCH($K49,Model!$R$2:$R$636,0))) | G49: =IF($K49="","",INDEX(Raw_data!$H$2:$H$636,MATCH($K49,Model!$R$2:$R$636,0))) | H49: =IF($K49="","",INDEX(Model!$B$2:$B$636,MATCH($K49,Model!$R$2:$R$636,0))) | I49: =IF($K49="","",INDEX(Model!$C$2:$C$636,MATCH($K49,Model!$R$2:$R$636,0))) | J49: =IF($K49="","",INDEX(Model!$D$2:$D$636,MATCH($K49,Model!$R$2:$R$636,0))) | K49: =IF(13<=$E$5,LARGE(Model!$R$2:$R$636,13),"")
A50: =IF($K50="","",INDEX(Raw_data!$D$2:$D$636,MATCH($K50,Model!$R$2:$R$636,0))) | B50: =IF($K50="","",INDEX(Raw_data!$F$2:$F$636,MATCH($K50,Model!$R$2:$R$636,0))) | C50: =IF($K50="","",HYPERLINK(INDEX(Raw_data!$C$2:$C$636,MATCH($K50,Model!$R$2:$R$636,0)),INDEX(Raw_data!$C$2:$C$636,MATCH($K50,Model!$R$2:$R$636,0)))) | D50: =IF($K50="","",INDEX(Raw_data!$AL$2:$AL$636,MATCH($K50,Model!$R$2:$R$636,0))) | E50: =IF($K50="","",INDEX(Raw_data!$AM$2:$AM$636,MATCH($K50,Model!$R$2:$R$636,0))) | F50: =IF($K50="","",INDEX(Raw_data!$AQ$2:$AQ$636,MATCH($K50,Model!$R$2:$R$636,0))) | G50: =IF($K50="","",INDEX(Raw_data!$H$2:$H$636,MATCH($K50,Model!$R$2:$R$636,0))) | H50: =IF($K50="","",INDEX(Model!$B$2:$B$636,MATCH($K50,Model!$R$2:$R$636,0))) | I50: =IF($K50="","",INDEX(Model!$C$2:$C$636,MATCH($K50,Model!$R$2:$R$636,0))) | J50: =IF($K50="","",INDEX(Model!$D$2:$D$636,MATCH($K50,Model!$R$2:$R$636,0))) | K50: =IF(14<=$E$5,LARGE(Model!$R$2:$R$636,14),"")
A51: =IF($K51="","",INDEX(Raw_data!$D$2:$D$636,MATCH($K51,Model!$R$2:$R$636,0))) | B51: =IF($K51="","",INDEX(Raw_data!$F$2:$F$636,MATCH($K51,Model!$R$2:$R$636,0))) | C51: =IF($K51="","",HYPERLINK(INDEX(Raw_data!$C$2:$C$636,MATCH($K51,Model!$R$2:$R$636,0)),INDEX(Raw_data!$C$2:$C$636,MATCH($K51,Model!$R$2:$R$636,0)))) | D51: =IF($K51="","",INDEX(Raw_data!$AL$2:$AL$636,MATCH($K51,Model!$R$2:$R$636,0))) | E51: =IF($K51="","",INDEX(Raw_data!$AM$2:$AM$636,MATCH($K51,Model!$R$2:$R$636,0))) | F51: =IF($K51="","",INDEX(Raw_data!$AQ$2:$AQ$636,MATCH($K51,Model!$R$2:$R$636,0))) | G51: =IF($K51="","",INDEX(Raw_data!$H$2:$H$636,MATCH($K51,Model!$R$2:$R$636,0))) | H51: =IF($K51="","",INDEX(Model!$B$2:$B$636,MATCH($K51,Model!$R$2:$R$636,0))) | I51: =IF($K51="","",INDEX(Model!$C$2:$C$636,MATCH($K51,Model!$R$2:$R$636,0))) | J51: =IF($K51="","",INDEX(Model!$D$2:$D$636,MATCH($K51,Model!$R$2:$R$636,0))) | K51: =IF(15<=$E$5,LARGE(Model!$R$2:$R$636,15),"")
A52: =IF($K52="","",INDEX(Raw_data!$D$2:$D$636,MATCH($K52,Model!$R$2:$R$636,0))) | B52: =IF($K52="","",INDEX(Raw_data!$F$2:$F$636,MATCH($K52,Model!$R$2:$R$636,0))) | C52: =IF($K52="","",HYPERLINK(INDEX(Raw_data!$C$2:$C$636,MATCH($K52,Model!$R$2:$R$636,0)),INDEX(Raw_data!$C$2:$C$636,MATCH($K52,Model!$R$2:$R$636,0)))) | D52: =IF($K52="","",INDEX(Raw_data!$AL$2:$AL$636,MATCH($K52,Model!$R$2:$R$636,0))) | E52: =IF($K52="","",INDEX(Raw_data!$AM$2:$AM$636,MATCH($K52,Model!$R$2:$R$636,0))) | F52: =IF($K52="","",INDEX(Raw_data!$AQ$2:$AQ$636,MATCH($K52,Model!$R$2:$R$636,0))) | G52: =IF($K52="","",INDEX(Raw_data!$H$2:$H$636,MATCH($K52,Model!$R$2:$R$636,0))) | H52: =IF($K52="","",INDEX(Model!$B$2:$B$636,MATCH($K52,Model!$R$2:$R$636,0))) | I52: =IF($K52="","",INDEX(Model!$C$2:$C$636,MATCH($K52,Model!$R$2:$R$636,0))) | J52: =IF($K52="","",INDEX(Model!$D$2:$D$636,MATCH($K52,Model!$R$2:$R$636,0))) | K52: =IF(16<=$E$5,LARGE(Model!$R$2:$R$636,16),"")
A53: =IF($K53="","",INDEX(Raw_data!$D$2:$D$636,MATCH($K53,Model!$R$2:$R$636,0))) | B53: =IF($K53="","",INDEX(Raw_data!$F$2:$F$636,MATCH($K53,Model!$R$2:$R$636,0))) | C53: =IF($K53="","",HYPERLINK(INDEX(Raw_data!$C$2:$C$636,MATCH($K53,Model!$R$2:$R$636,0)),INDEX(Raw_data!$C$2:$C$636,MATCH($K53,Model!$R$2:$R$636,0)))) | D53: =IF($K53="","",INDEX(Raw_data!$AL$2:$AL$636,MATCH($K53,Model!$R$2:$R$636,0))) | E53: =IF($K53="","",INDEX(Raw_data!$AM$2:$AM$636,MATCH($K53,Model!$R$2:$R$636,0))) | F53: =IF($K53="","",INDEX(Raw_data!$AQ$2:$AQ$636,MATCH($K53,Model!$R$2:$R$636,0))) | G53: =IF($K53="","",INDEX(Raw_data!$H$2:$H$636,MATCH($K53,Model!$R$2:$R$636,0))) | H53: =IF($K53="","",INDEX(Model!$B$2:$B$636,MATCH($K53,Model!$R$2:$R$636,0))) | I53: =IF($K53="","",INDEX(Model!$C$2:$C$636,MATCH($K53,Model!$R$2:$R$636,0))) | J53: =IF($K53="","",INDEX(Model!$D$2:$D$636,MATCH($K53,Model!$R$2:$R$636,0))) | K53: =IF(17<=$E$5,LARGE(Model!$R$2:$R$636,17),"")
A54: =IF($K54="","",INDEX(Raw_data!$D$2:$D$636,MATCH($K54,Model!$R$2:$R$636,0))) | B54: =IF($K54="","",INDEX(Raw_data!$F$2:$F$636,MATCH($K54,Model!$R$2:$R$636,0))) | C54: =IF($K54="","",HYPERLINK(INDEX(Raw_data!$C$2:$C$636,MATCH($K54,Model!$R$2:$R$636,0)),INDEX(Raw_data!$C$2:$C$636,MATCH($K54,Model!$R$2:$R$636,0)))) | D54: =IF($K54="","",INDEX(Raw_data!$AL$2:$AL$636,MATCH($K54,Model!$R$2:$R$636,0))) | E54: =IF($K54="","",INDEX(Raw_data!$AM$2:$AM$636,MATCH($K54,Model!$R$2:$R$636,0))) | F54: =IF($K54="","",INDEX(Raw_data!$AQ$2:$AQ$636,MATCH($K54,Model!$R$2:$R$636,0))) | G54: =IF($K54="","",INDEX(Raw_data!$H$2:$H$636,MATCH($K54,Model!$R$2:$R$636,0))) | H54: =IF($K54="","",INDEX(Model!$B$2:$B$636,MATCH($K54,Model!$R$2:$R$636,0))) | I54: =IF($K54="","",INDEX(Model!$C$2:$C$636,MATCH($K54,Model!$R$2:$R$636,0))) | J54: =IF($K54="","",INDEX(Model!$D$2:$D$636,MATCH($K54,Model!$R$2:$R$636,0))) | K54: =IF(18<=$E$5,LARGE(Model!$R$2:$R$636,18),"")
A55: =IF($K55="","",INDEX(Raw_data!$D$2:$D$636,MATCH($K55,Model!$R$2:$R$636,0))) | B55: =IF($K55="","",INDEX(Raw_data!$F$2:$F$636,MATCH($K55,Model!$R$2:$R$636,0))) | C55: =IF($K55="","",HYPERLINK(INDEX(Raw_data!$C$2:$C$636,MATCH($K55,Model!$R$2:$R$636,0)),INDEX(Raw_data!$C$2:$C$636,MATCH($K55,Model!$R$2:$R$636,0)))) | D55: =IF($K55="","",INDEX(Raw_data!$AL$2:$AL$636,MATCH($K55,Model!$R$2:$R$636,0))) | E55: =IF($K55="","",INDEX(Raw_data!$AM$2:$AM$636,MATCH($K55,Model!$R$2:$R$636,0))) | F55: =IF($K55="","",INDEX(Raw_data!$AQ$2:$AQ$636,MATCH($K55,Model!$R$2:$R$636,0))) | G55: =IF($K55="","",INDEX(Raw_data!$H$2:$H$636,MATCH($K55,Model!$R$2:$R$636,0))) | H55: =IF($K55="","",INDEX(Model!$B$2:$B$636,MATCH($K55,Model!$R$2:$R$636,0))) | I55: =IF($K55="","",INDEX(Model!$C$2:$C$636,MATCH($K55,Model!$R$2:$R$636,0))) | J55: =IF($K55="","",INDEX(Model!$D$2:$D$636,MATCH($K55,Model!$R$2:$R$636,0))) | K55: =IF(19<=$E$5,LARGE(Model!$R$2:$R$636,19),"")
A56: =IF($K56="","",INDEX(Raw_data!$D$2:$D$636,MATCH($K56,Model!$R$2:$R$636,0))) | B56: =IF($K56="","",INDEX(Raw_data!$F$2:$F$636,MATCH($K56,Model!$R$2:$R$636,0))) | C56: =IF($K56="","",HYPERLINK(INDEX(Raw_data!$C$2:$C$636,MATCH($K56,Model!$R$2:$R$636,0)),INDEX(Raw_data!$C$2:$C$636,MATCH($K56,Model!$R$2:$R$636,0)))) | D56: =IF($K56="","",INDEX(Raw_data!$AL$2:$AL$636,MATCH($K56,Model!$R$2:$R$636,0))) | E56: =IF($K56="","",INDEX(Raw_data!$AM$2:$AM$636,MATCH($K56,Model!$R$2:$R$636,0))) | F56: =IF($K56="","",INDEX(Raw_data!$AQ$2:$AQ$636,MATCH($K56,Model!$R$2:$R$636,0))) | G56: =IF($K56="","",INDEX(Raw_data!$H$2:$H$636,MATCH($K56,Model!$R$2:$R$636,0))) | H56: =IF($K56="","",INDEX(Model!$B$2:$B$636,MATCH($K56,Model!$R$2:$R$636,0))) | I56: =IF($K56="","",INDEX(Model!$C$2:$C$636,MATCH($K56,Model!$R$2:$R$636,0))) | J56: =IF($K56="","",INDEX(Model!$D$2:$D$636,MATCH($K56,Model!$R$2:$R$636,0))) | K56: =IF(20<=$E$5,LARGE(Model!$R$2:$R$636,20),"")
A57: =IF($K57="","",INDEX(Raw_data!$D$2:$D$636,MATCH($K57,Model!$R$2:$R$636,0))) | B57: =IF($K57="","",INDEX(Raw_data!$F$2:$F$636,MATCH($K57,Model!$R$2:$R$636,0))) | C57: =IF($K57="","",HYPERLINK(INDEX(Raw_data!$C$2:$C$636,MATCH($K57,Model!$R$2:$R$636,0)),INDEX(Raw_data!$C$2:$C$636,MATCH($K57,Model!$R$2:$R$636,0)))) | D57: =IF($K57="","",INDEX(Raw_data!$AL$2:$AL$636,MATCH($K57,Model!$R$2:$R$636,0))) | E57: =IF($K57="","",INDEX(Raw_data!$AM$2:$AM$636,MATCH($K57,Model!$R$2:$R$636,0))) | F57: =IF($K57="","",INDEX(Raw_data!$AQ$2:$AQ$636,MATCH($K57,Model!$R$2:$R$636,0))) | G57: =IF($K57="","",INDEX(Raw_data!$H$2:$H$636,MATCH($K57,Model!$R$2:$R$636,0))) | H57: =IF($K57="","",INDEX(Model!$B$2:$B$636,MATCH($K57,Model!$R$2:$R$636,0))) | I57: =IF($K57="","",INDEX(Model!$C$2:$C$636,MATCH($K57,Model!$R$2:$R$636,0))) | J57: =IF($K57="","",INDEX(Model!$D$2:$D$636,MATCH($K57,Model!$R$2:$R$636,0))) | K57: =IF(21<=$E$5,LARGE(Model!$R$2:$R$636,21),"")
A58: =IF($K58="","",INDEX(Raw_data!$D$2:$D$636,MATCH($K58,Model!$R$2:$R$636,0))) | B58: =IF($K58="","",INDEX(Raw_data!$F$2:$F$636,MATCH($K58,Model!$R$2:$R$636,0))) | C58: =IF($K58="","",HYPERLINK(INDEX(Raw_data!$C$2:$C$636,MATCH($K58,Model!$R$2:$R$636,0)),INDEX(Raw_data!$C$2:$C$636,MATCH($K58,Model!$R$2:$R$636,0)))) | D58: =IF($K58="","",INDEX(Raw_data!$AL$2:$AL$636,MATCH($K58,Model!$R$2:$R$636,0))) | E58: =IF($K58="","",INDEX(Raw_data!$AM$2:$AM$636,MATCH($K58,Model!$R$2:$R$636,0))) | F58: =IF($K58="","",INDEX(Raw_data!$AQ$2:$AQ$636,MATCH($K58,Model!$R$2:$R$636,0))) | G58: =IF($K58="","",INDEX(Raw_data!$H$2:$H$636,MATCH($K58,Model!$R$2:$R$636,0))) | H58: =IF($K58="","",INDEX(Model!$B$2:$B$636,MATCH($K58,Model!$R$2:$R$636,0))) | I58: =IF($K58="","",INDEX(Model!$C$2:$C$636,MATCH($K58,Model!$R$2:$R$636,0))) | J58: =IF($K58="","",INDEX(Model!$D$2:$D$636,MATCH($K58,Model!$R$2:$R$636,0))) | K58: =IF(22<=$E$5,LARGE(Model!$R$2:$R$636,22),"")
A59: =IF($K59="","",INDEX(Raw_data!$D$2:$D$636,MATCH($K59,Model!$R$2:$R$636,0))) | B59: =IF($K59="","",INDEX(Raw_data!$F$2:$F$636,MATCH($K59,Model!$R$2:$R$636,0))) | C59: =IF($K59="","",HYPERLINK(INDEX(Raw_data!$C$2:$C$636,MATCH($K59,Model!$R$2:$R$636,0)),INDEX(Raw_data!$C$2:$C$636,MATCH($K59,Model!$R$2:$R$636,0)))) | D59: =IF($K59="","",INDEX(Raw_data!$AL$2:$AL$636,MATCH($K59,Model!$R$2:$R$636,0))) | E59: =IF($K59="","",INDEX(Raw_data!$AM$2:$AM$636,MATCH($K59,Model!$R$2:$R$636,0))) | F59: =IF($K59="","",INDEX(Raw_data!$AQ$2:$AQ$636,MATCH($K59,Model!$R$2:$R$636,0))) | G59: =IF($K59="","",INDEX(Raw_data!$H$2:$H$636,MATCH($K59,Model!$R$2:$R$636,0))) | H59: =IF($K59="","",INDEX(Model!$B$2:$B$636,MATCH($K59,Model!$R$2:$R$636,0))) | I59: =IF($K59="","",INDEX(Model!$C$2:$C$636,MATCH($K59,Model!$R$2:$R$636,0))) | J59: =IF($K59="","",INDEX(Model!$D$2:$D$636,MATCH($K59,Model!$R$2:$R$636,0))) | K59: =IF(23<=$E$5,LARGE(Model!$R$2:$R$636,23),"")
A60: =IF($K60="","",INDEX(Raw_data!$D$2:$D$636,MATCH($K60,Model!$R$2:$R$636,0))) | B60: =IF($K60="","",INDEX(Raw_data!$F$2:$F$636,MATCH($K60,Model!$R$2:$R$636,0))) | C60: =IF($K60="","",HYPERLINK(INDEX(Raw_data!$C$2:$C$636,MATCH($K60,Model!$R$2:$R$636,0)),INDEX(Raw_data!$C$2:$C$636,MATCH($K60,Model!$R$2:$R$636,0)))) | D60: =IF($K60="","",INDEX(Raw_data!$AL$2:$AL$636,MATCH($K60,Model!$R$2:$R$636,0))) | E60: =IF($K60="","",INDEX(Raw_data!$AM$2:$AM$636,MATCH($K60,Model!$R$2:$R$636,0))) | F60: =IF($K60="","",INDEX(Raw_data!$AQ$2:$AQ$636,MATCH($K60,Model!$R$2:$R$636,0))) | G60: =IF($K60="","",INDEX(Raw_data!$H$2:$H$636,MATCH($K60,Model!$R$2:$R$636,0))) | H60: =IF($K60="","",INDEX(Model!$B$2:$B$636,MATCH($K60,Model!$R$2:$R$636,0))) | I60: =IF($K60="","",INDEX(Model!$C$2:$C$636,MATCH($K60,Model!$R$2:$R$636,0))) | J60: =IF($K60="","",INDEX(Model!$D$2:$D$636,MATCH($K60,Model!$R$2:$R$636,0))) | K60: =IF(24<=$E$5,LARGE(Model!$R$2:$R$636,24),"")
A61: =IF($K61="","",INDEX(Raw_data!$D$2:$D$636,MATCH($K61,Model!$R$2:$R$636,0))) | B61: =IF($K61="","",INDEX(Raw_data!$F$2:$F$636,MATCH($K61,Model!$R$2:$R$636,0))) | C61: =IF($K61="","",HYPERLINK(INDEX(Raw_data!$C$2:$C$636,MATCH($K61,Model!$R$2:$R$636,0)),INDEX(Raw_data!$C$2:$C$636,MATCH($K61,Model!$R$2:$R$636,0)))) | D61: =IF($K61="","",INDEX(Raw_data!$AL$2:$AL$636,MATCH($K61,Model!$R$2:$R$636,0))) | E61: =IF($K61="","",INDEX(Raw_data!$AM$2:$AM$636,MATCH($K61,Model!$R$2:$R$636,0))) | F61: =IF($K61="","",INDEX(Raw_data!$AQ$2:$AQ$636,MATCH($K61,Model!$R$2:$R$636,0))) | G61: =IF($K61="","",INDEX(Raw_data!$H$2:$H$636,MATCH($K61,Model!$R$2:$R$636,0))) | H61: =IF($K61="","",INDEX(Model!$B$2:$B$636,MATCH($K61,Model!$R$2:$R$636,0))) | I61: =IF($K61="","",INDEX(Model!$C$2:$C$636,MATCH($K61,Model!$R$2:$R$636,0))) | J61: =IF($K61="","",INDEX(Model!$D$2:$D$636,MATCH($K61,Model!$R$2:$R$636,0))) | K61: =IF(25<=$E$5,LARGE(Model!$R$2:$R$636,25),"")
A62: =IF($K62="","",INDEX(Raw_data!$D$2:$D$636,MATCH($K62,Model!$R$2:$R$636,0))) | B62: =IF($K62="","",INDEX(Raw_data!$F$2:$F$636,MATCH($K62,Model!$R$2:$R$636,0))) | C62: =IF($K62="","",HYPERLINK(INDEX(Raw_data!$C$2:$C$636,MATCH($K62,Model!$R$2:$R$636,0)),INDEX(Raw_data!$C$2:$C$636,MATCH($K62,Model!$R$2:$R$636,0)))) | D62: =IF($K62="","",INDEX(Raw_data!$AL$2:$AL$636,MATCH($K62,Model!$R$2:$R$636,0))) | E62: =IF($K62="","",INDEX(Raw_data!$AM$2:$AM$636,MATCH($K62,Model!$R$2:$R$636,0))) | F62: =IF($K62="","",INDEX(Raw_data!$AQ$2:$AQ$636,MATCH($K62,Model!$R$2:$R$636,0))) | G62: =IF($K62="","",INDEX(Raw_data!$H$2:$H$636,MATCH($K62,Model!$R$2:$R$636,0))) | H62: =IF($K62="","",INDEX(Model!$B$2:$B$636,MATCH($K62,Model!$R$2:$R$636,0))) | I62: =IF($K62="","",INDEX(Model!$C$2:$C$636,MATCH($K62,Model!$R$2:$R$636,0))) | J62: =IF($K62="","",INDEX(Model!$D$2:$D$636,MATCH($K62,Model!$R$2:$R$636,0))) | K62: =IF(26<=$E$5,LARGE(Model!$R$2:$R$636,26),"")
A63: =IF($K63="","",INDEX(Raw_data!$D$2:$D$636,MATCH($K63,Model!$R$2:$R$636,0))) | B63: =IF($K63="","",INDEX(Raw_data!$F$2:$F$636,MATCH($K63,Model!$R$2:$R$636,0))) | C63: =IF($K63="","",HYPERLINK(INDEX(Raw_data!$C$2:$C$636,MATCH($K63,Model!$R$2:$R$636,0)),INDEX(Raw_data!$C$2:$C$636,MATCH($K63,Model!$R$2:$R$636,0)))) | D63: =IF($K63="","",INDEX(Raw_data!$AL$2:$AL$636,MATCH($K63,Model!$R$2:$R$636,0))) | E63: =IF($K63="","",INDEX(Raw_data!$AM$2:$AM$636,MATCH($K63,Model!$R$2:$R$636,0))) | F63: =IF($K63="","",INDEX(Raw_data!$AQ$2:$AQ$636,MATCH($K63,Model!$R$2:$R$636,0))) | G63: =IF($K63="","",INDEX(Raw_data!$H$2:$H$636,MATCH($K63,Model!$R$2:$R$636,0))) | H63: =IF($K63="","",INDEX(Model!$B$2:$B$636,MATCH($K63,Model!$R$2:$R$636,0))) | I63: =IF($K63="","",INDEX(Model!$C$2:$C$636,MATCH($K63,Model!$R$2:$R$636,0))) | J63: =IF($K63="","",INDEX(Model!$D$2:$D$636,MATCH($K63,Model!$R$2:$R$636,0))) | K63: =IF(27<=$E$5,LARGE(Model!$R$2:$R$636,27),"")
A64: =IF($K64="","",INDEX(Raw_data!$D$2:$D$636,MATCH($K64,Model!$R$2:$R$636,0))) | B64: =IF($K64="","",INDEX(Raw_data!$F$2:$F$636,MATCH($K64,Model!$R$2:$R$636,0))) | C64: =IF($K64="","",HYPERLINK(INDEX(Raw_data!$C$2:$C$636,MATCH($K64,Model!$R$2:$R$636,0)),INDEX(Raw_data!$C$2:$C$636,MATCH($K64,Model!$R$2:$R$636,0)))) | D64: =IF($K64="","",INDEX(Raw_data!$AL$2:$AL$636,MATCH($K64,Model!$R$2:$R$636,0))) | E64: =IF($K64="","",INDEX(Raw_data!$AM$2:$AM$636,MATCH($K64,Model!$R$2:$R$636,0))) | F64: =IF($K64="","",INDEX(Raw_data!$AQ$2:$AQ$636,MATCH($K64,Model!$R$2:$R$636,0))) | G64: =IF($K64="","",INDEX(Raw_data!$H$2:$H$636,MATCH($K64,Model!$R$2:$R$636,0))) | H64: =IF($K64="","",INDEX(Model!$B$2:$B$636,MATCH($K64,Model!$R$2:$R$636,0))) | I64: =IF($K64="","",INDEX(Model!$C$2:$C$636,MATCH($K64,Model!$R$2:$R$636,0))) | J64: =IF($K64="","",INDEX(Model!$D$2:$D$636,MATCH($K64,Model!$R$2:$R$636,0))) | K64: =IF(28<=$E$5,LARGE(Model!$R$2:$R$636,28),"")
A65: =IF($K65="","",INDEX(Raw_data!$D$2:$D$636,MATCH($K65,Model!$R$2:$R$636,0))) | B65: =IF($K65="","",INDEX(Raw_data!$F$2:$F$636,MATCH($K65,Model!$R$2:$R$636,0))) | C65: =IF($K65="","",HYPERLINK(INDEX(Raw_data!$C$2:$C$636,MATCH($K65,Model!$R$2:$R$636,0)),INDEX(Raw_data!$C$2:$C$636,MATCH($K65,Model!$R$2:$R$636,0)))) | D65: =IF($K65="","",INDEX(Raw_data!$AL$2:$AL$636,MATCH($K65,Model!$R$2:$R$636,0))) | E65: =IF($K65="","",INDEX(Raw_data!$AM$2:$AM$636,MATCH($K65,Model!$R$2:$R$636,0))) | F65: =IF($K65="","",INDEX(Raw_data!$AQ$2:$AQ$636,MATCH($K65,Model!$R$2:$R$636,0))) | G65: =IF($K65="","",INDEX(Raw_data!$H$2:$H$636,MATCH($K65,Model!$R$2:$R$636,0))) | H65: =IF($K65="","",INDEX(Model!$B$2:$B$636,MATCH($K65,Model!$R$2:$R$636,0))) | I65: =IF($K65="","",INDEX(Model!$C$2:$C$636,MATCH($K65,Model!$R$2:$R$636,0))) | J65: =IF($K65="","",INDEX(Model!$D$2:$D$636,MATCH($K65,Model!$R$2:$R$636,0))) | K65: =IF(29<=$E$5,LARGE(Model!$R$2:$R$636,29),"")
A66: =IF($K66="","",INDEX(Raw_data!$D$2:$D$636,MATCH($K66,Model!$R$2:$R$636,0))) | B66: =IF($K66="","",INDEX(Raw_data!$F$2:$F$636,MATCH($K66,Model!$R$2:$R$636,0))) | C66: =IF($K66="","",HYPERLINK(INDEX(Raw_data!$C$2:$C$636,MATCH($K66,Model!$R$2:$R$636,0)),INDEX(Raw_data!$C$2:$C$636,MATCH($K66,Model!$R$2:$R$636,0)))) | D66: =IF($K66="","",INDEX(Raw_data!$AL$2:$AL$636,MATCH($K66,Model!$R$2:$R$636,0))) | E66: =IF($K66="","",INDEX(Raw_data!$AM$2:$AM$636,MATCH($K66,Model!$R$2:$R$636,0))) | F66: =IF($K66="","",INDEX(Raw_data!$AQ$2:$AQ$636,MATCH($K66,Model!$R$2:$R$636,0))) | G66: =IF($K66="","",INDEX(Raw_data!$H$2:$H$636,MATCH($K66,Model!$R$2:$R$636,0))) | H66: =IF($K66="","",INDEX(Model!$B$2:$B$636,MATCH($K66,Model!$R$2:$R$636,0))) | I66: =IF($K66="","",INDEX(Model!$C$2:$C$636,MATCH($K66,Model!$R$2:$R$636,0))) | J66: =IF($K66="","",INDEX(Model!$D$2:$D$636,MATCH($K66,Model!$R$2:$R$636,0))) | K66: =IF(30<=$E$5,LARGE(Model!$R$2:$R$636,30),"")
A67: =IF($K67="","",INDEX(Raw_data!$D$2:$D$636,MATCH($K67,Model!$R$2:$R$636,0))) | B67: =IF($K67="","",INDEX(Raw_data!$F$2:$F$636,MATCH($K67,Model!$R$2:$R$636,0))) | C67: =IF($K67="","",HYPERLINK(INDEX(Raw_data!$C$2:$C$636,MATCH($K67,Model!$R$2:$R$636,0)),INDEX(Raw_data!$C$2:$C$636,MATCH($K67,Model!$R$2:$R$636,0)))) | D67: =IF($K67="","",INDEX(Raw_data!$AL$2:$AL$636,MATCH($K67,Model!$R$2:$R$636,0))) | E67: =IF($K67="","",INDEX(Raw_data!$AM$2:$AM$636,MATCH($K67,Model!$R$2:$R$636,0))) | F67: =IF($K67="","",INDEX(Raw_data!$AQ$2:$AQ$636,MATCH($K67,Model!$R$2:$R$636,0))) | G67: =IF($K67="","",INDEX(Raw_data!$H$2:$H$636,MATCH($K67,Model!$R$2:$R$636,0))) | H67: =IF($K67="","",INDEX(Model!$B$2:$B$636,MATCH($K67,Model!$R$2:$R$636,0))) | I67: =IF($K67="","",INDEX(Model!$C$2:$C$636,MATCH($K67,Model!$R$2:$R$636,0))) | J67: =IF($K67="","",INDEX(Model!$D$2:$D$636,MATCH($K67,Model!$R$2:$R$636,0))) | K67: =IF(31<=$E$5,LARGE(Model!$R$2:$R$636,31),"")
A68: =IF($K68="","",INDEX(Raw_data!$D$2:$D$636,MATCH($K68,Model!$R$2:$R$636,0))) | B68: =IF($K68="","",INDEX(Raw_data!$F$2:$F$636,MATCH($K68,Model!$R$2:$R$636,0))) | C68: =IF($K68="","",HYPERLINK(INDEX(Raw_data!$C$2:$C$636,MATCH($K68,Model!$R$2:$R$636,0)),INDEX(Raw_data!$C$2:$C$636,MATCH($K68,Model!$R$2:$R$636,0)))) | D68: =IF($K68="","",INDEX(Raw_data!$AL$2:$AL$636,MATCH($K68,Model!$R$2:$R$636,0))) | E68: =IF($K68="","",INDEX(Raw_data!$AM$2:$AM$636,MATCH($K68,Model!$R$2:$R$636,0))) | F68: =IF($K68="","",INDEX(Raw_data!$AQ$2:$AQ$636,MATCH($K68,Model!$R$2:$R$636,0))) | G68: =IF($K68="","",INDEX(Raw_data!$H$2:$H$636,MATCH($K68,Model!$R$2:$R$636,0))) | H68: =IF($K68="","",INDEX(Model!$B$2:$B$636,MATCH($K68,Model!$R$2:$R$636,0))) | I68: =IF($K68="","",INDEX(Model!$C$2:$C$636,MATCH($K68,Model!$R$2:$R$636,0))) | J68: =IF($K68="","",INDEX(Model!$D$2:$D$636,MATCH($K68,Model!$R$2:$R$636,0))) | K68: =IF(32<=$E$5,LARGE(Model!$R$2:$R$636,32),"")
A69: =IF($K69="","",INDEX(Raw_data!$D$2:$D$636,MATCH($K69,Model!$R$2:$R$636,0))) | B69: =IF($K69="","",INDEX(Raw_data!$F$2:$F$636,MATCH($K69,Model!$R$2:$R$636,0))) | C69: =IF($K69="","",HYPERLINK(INDEX(Raw_data!$C$2:$C$636,MATCH($K69,Model!$R$2:$R$636,0)),INDEX(Raw_data!$C$2:$C$636,MATCH($K69,Model!$R$2:$R$636,0)))) | D69: =IF($K69="","",INDEX(Raw_data!$AL$2:$AL$636,MATCH($K69,Model!$R$2:$R$636,0))) | E69: =IF($K69="","",INDEX(Raw_data!$AM$2:$AM$636,MATCH($K69,Model!$R$2:$R$636,0))) | F69: =IF($K69="","",INDEX(Raw_data!$AQ$2:$AQ$636,MATCH($K69,Model!$R$2:$R$636,0))) | G69: =IF($K69="","",INDEX(Raw_data!$H$2:$H$636,MATCH($K69,Model!$R$2:$R$636,0))) | H69: =IF($K69="","",INDEX(Model!$B$2:$B$636,MATCH($K69,Model!$R$2:$R$636,0))) | I69: =IF($K69="","",INDEX(Model!$C$2:$C$636,MATCH($K69,Model!$R$2:$R$636,0))) | J69: =IF($K69="","",INDEX(Model!$D$2:$D$636,MATCH($K69,Model!$R$2:$R$636,0))) | K69: =IF(33<=$E$5,LARGE(Model!$R$2:$R$636,33),"")
A70: =IF($K70="","",INDEX(Raw_data!$D$2:$D$636,MATCH($K70,Model!$R$2:$R$636,0))) | B70: =IF($K70="","",INDEX(Raw_data!$F$2:$F$636,MATCH($K70,Model!$R$2:$R$636,0))) | C70: =IF($K70="","",HYPERLINK(INDEX(Raw_data!$C$2:$C$636,MATCH($K70,Model!$R$2:$R$636,0)),INDEX(Raw_data!$C$2:$C$636,MATCH($K70,Model!$R$2:$R$636,0)))) | D70: =IF($K70="","",INDEX(Raw_data!$AL$2:$AL$636,MATCH($K70,Model!$R$2:$R$636,0))) | E70: =IF($K70="","",INDEX(Raw_data!$AM$2:$AM$636,MATCH($K70,Model!$R$2:$R$636,0))) | F70: =IF($K70="","",INDEX(Raw_data!$AQ$2:$AQ$636,MATCH($K70,Model!$R$2:$R$636,0))) | G70: =IF($K70="","",INDEX(Raw_data!$H$2:$H$636,MATCH($K70,Model!$R$2:$R$636,0))) | H70: =IF($K70="","",INDEX(Model!$B$2:$B$636,MATCH($K70,Model!$R$2:$R$636,0))) | I70: =IF($K70="","",INDEX(Model!$C$2:$C$636,MATCH($K70,Model!$R$2:$R$636,0))) | J70: =IF($K70="","",INDEX(Model!$D$2:$D$636,MATCH($K70,Model!$R$2:$R$636,0))) | K70: =IF(34<=$E$5,LARGE(Model!$R$2:$R$636,34),"")
A71: =IF($K71="","",INDEX(Raw_data!$D$2:$D$636,MATCH($K71,Model!$R$2:$R$636,0))) | B71: =IF($K71="","",INDEX(Raw_data!$F$2:$F$636,MATCH($K71,Model!$R$2:$R$636,0))) | C71: =IF($K71="","",HYPERLINK(INDEX(Raw_data!$C$2:$C$636,MATCH($K71,Model!$R$2:$R$636,0)),INDEX(Raw_data!$C$2:$C$636,MATCH($K71,Model!$R$2:$R$636,0)))) | D71: =IF($K71="","",INDEX(Raw_data!$AL$2:$AL$636,MATCH($K71,Model!$R$2:$R$636,0))) | E71: =IF($K71="","",INDEX(Raw_data!$AM$2:$AM$636,MATCH($K71,Model!$R$2:$R$636,0))) | F71: =IF($K71="","",INDEX(Raw_data!$AQ$2:$AQ$636,MATCH($K71,Model!$R$2:$R$636,0))) | G71: =IF($K71="","",INDEX(Raw_data!$H$2:$H$636,MATCH($K71,Model!$R$2:$R$636,0))) | H71: =IF($K71="","",INDEX(Model!$B$2:$B$636,MATCH($K71,Model!$R$2:$R$636,0))) | I71: =IF($K71="","",INDEX(Model!$C$2:$C$636,MATCH($K71,Model!$R$2:$R$636,0))) | J71: =IF($K71="","",INDEX(Model!$D$2:$D$636,MATCH($K71,Model!$R$2:$R$636,0))) | K71: =IF(35<=$E$5,LARGE(Model!$R$2:$R$636,35),"")
A72: =IF($K72="","",INDEX(Raw_data!$D$2:$D$636,MATCH($K72,Model!$R$2:$R$636,0))) | B72: =IF($K72="","",INDEX(Raw_data!$F$2:$F$636,MATCH($K72,Model!$R$2:$R$636,0))) | C72: =IF($K72="","",HYPERLINK(INDEX(Raw_data!$C$2:$C$636,MATCH($K72,Model!$R$2:$R$636,0)),INDEX(Raw_data!$C$2:$C$636,MATCH($K72,Model!$R$2:$R$636,0)))) | D72: =IF($K72="","",INDEX(Raw_data!$AL$2:$AL$636,MATCH($K72,Model!$R$2:$R$636,0))) | E72: =IF($K72="","",INDEX(Raw_data!$AM$2:$AM$636,MATCH($K72,Model!$R$2:$R$636,0))) | F72: =IF($K72="","",INDEX(Raw_data!$AQ$2:$AQ$636,MATCH($K72,Model!$R$2:$R$636,0))) | G72: =IF($K72="","",INDEX(Raw_data!$H$2:$H$636,MATCH($K72,Model!$R$2:$R$636,0))) | H72: =IF($K72="","",INDEX(Model!$B$2:$B$636,MATCH($K72,Model!$R$2:$R$636,0))) | I72: =IF($K72="","",INDEX(Model!$C$2:$C$636,MATCH($K72,Model!$R$2:$R$636,0))) | J72: =IF($K72="","",INDEX(Model!$D$2:$D$636,MATCH($K72,Model!$R$2:$R$636,0))) | K72: =IF(36<=$E$5,LARGE(Model!$R$2:$R$636,36),"")
A73: =IF($K73="","",INDEX(Raw_data!$D$2:$D$636,MATCH($K73,Model!$R$2:$R$636,0))) | B73: =IF($K73="","",INDEX(Raw_data!$F$2:$F$636,MATCH($K73,Model!$R$2:$R$636,0))) | C73: =IF($K73="","",HYPERLINK(INDEX(Raw_data!$C$2:$C$636,MATCH($K73,Model!$R$2:$R$636,0)),INDEX(Raw_data!$C$2:$C$636,MATCH($K73,Model!$R$2:$R$636,0)))) | D73: =IF($K73="","",INDEX(Raw_data!$AL$2:$AL$636,MATCH($K73,Model!$R$2:$R$636,0))) | E73: =IF($K73="","",INDEX(Raw_data!$AM$2:$AM$636,MATCH($K73,Model!$R$2:$R$636,0))) | F73: =IF($K73="","",INDEX(Raw_data!$AQ$2:$AQ$636,MATCH($K73,Model!$R$2:$R$636,0))) | G73: =IF($K73="","",INDEX(Raw_data!$H$2:$H$636,MATCH($K73,Model!$R$2:$R$636,0))) | H73: =IF($K73="","",INDEX(Model!$B$2:$B$636,MATCH($K73,Model!$R$2:$R$636,0))) | I73: =IF($K73="","",INDEX(Model!$C$2:$C$636,MATCH($K73,Model!$R$2:$R$636,0))) | J73: =IF($K73="","",INDEX(Model!$D$2:$D$636,MATCH($K73,Model!$R$2:$R$636,0))) | K73: =IF(37<=$E$5,LARGE(Model!$R$2:$R$636,37),"")
A74: =IF($K74="","",INDEX(Raw_data!$D$2:$D$636,MATCH($K74,Model!$R$2:$R$636,0))) | B74: =IF($K74="","",INDEX(Raw_data!$F$2:$F$636,MATCH($K74,Model!$R$2:$R$636,0))) | C74: =IF($K74="","",HYPERLINK(INDEX(Raw_data!$C$2:$C$636,MATCH($K74,Model!$R$2:$R$636,0)),INDEX(Raw_data!$C$2:$C$636,MATCH($K74,Model!$R$2:$R$636,0)))) | D74: =IF($K74="","",INDEX(Raw_data!$AL$2:$AL$636,MATCH($K74,Model!$R$2:$R$636,0))) | E74: =IF($K74="","",INDEX(Raw_data!$AM$2:$AM$636,MATCH($K74,Model!$R$2:$R$636,0))) | F74: =IF($K74="","",INDEX(Raw_data!$AQ$2:$AQ$636,MATCH($K74,Model!$R$2:$R$636,0))) | G74: =IF($K74="","",INDEX(Raw_data!$H$2:$H$636,MATCH($K74,Model!$R$2:$R$636,0))) | H74: =IF($K74="","",INDEX(Model!$B$2:$B$636,MATCH($K74,Model!$R$2:$R$636,0))) | I74: =IF($K74="","",INDEX(Model!$C$2:$C$636,MATCH($K74,Model!$R$2:$R$636,0))) | J74: =IF($K74="","",INDEX(Model!$D$2:$D$636,MATCH($K74,Model!$R$2:$R$636,0))) | K74: =IF(38<=$E$5,LARGE(Model!$R$2:$R$636,38),"")
A75: =IF($K75="","",INDEX(Raw_data!$D$2:$D$636,MATCH($K75,Model!$R$2:$R$636,0))) | B75: =IF($K75="","",INDEX(Raw_data!$F$2:$F$636,MATCH($K75,Model!$R$2:$R$636,0))) | C75: =IF($K75="","",HYPERLINK(INDEX(Raw_data!$C$2:$C$636,MATCH($K75,Model!$R$2:$R$636,0)),INDEX(Raw_data!$C$2:$C$636,MATCH($K75,Model!$R$2:$R$636,0)))) | D75: =IF($K75="","",INDEX(Raw_data!$AL$2:$AL$636,MATCH($K75,Model!$R$2:$R$636,0))) | E75: =IF($K75="","",INDEX(Raw_data!$AM$2:$AM$636,MATCH($K75,Model!$R$2:$R$636,0))) | F75: =IF($K75="","",INDEX(Raw_data!$AQ$2:$AQ$636,MATCH($K75,Model!$R$2:$R$636,0))) | G75: =IF($K75="","",INDEX(Raw_data!$H$2:$H$636,MATCH($K75,Model!$R$2:$R$636,0))) | H75: =IF($K75="","",INDEX(Model!$B$2:$B$636,MATCH($K75,Model!$R$2:$R$636,0))) | I75: =IF($K75="","",INDEX(Model!$C$2:$C$636,MATCH($K75,Model!$R$2:$R$636,0))) | J75: =IF($K75="","",INDEX(Model!$D$2:$D$636,MATCH($K75,Model!$R$2:$R$636,0))) | K75: =IF(39<=$E$5,LARGE(Model!$R$2:$R$636,39),"")
A76: =IF($K76="","",INDEX(Raw_data!$D$2:$D$636,MATCH($K76,Model!$R$2:$R$636,0))) | B76: =IF($K76="","",INDEX(Raw_data!$F$2:$F$636,MATCH($K76,Model!$R$2:$R$636,0))) | C76: =IF($K76="","",HYPERLINK(INDEX(Raw_data!$C$2:$C$636,MATCH($K76,Model!$R$2:$R$636,0)),INDEX(Raw_data!$C$2:$C$636,MATCH($K76,Model!$R$2:$R$636,0)))) | D76: =IF($K76="","",INDEX(Raw_data!$AL$2:$AL$636,MATCH($K76,Model!$R$2:$R$636,0))) | E76: =IF($K76="","",INDEX(Raw_data!$AM$2:$AM$636,MATCH($K76,Model!$R$2:$R$636,0))) | F76: =IF($K76="","",INDEX(Raw_data!$AQ$2:$AQ$636,MATCH($K76,Model!$R$2:$R$636,0))) | G76: =IF($K76="","",INDEX(Raw_data!$H$2:$H$636,MATCH($K76,Model!$R$2:$R$636,0))) | H76: =IF($K76="","",INDEX(Model!$B$2:$B$636,MATCH($K76,Model!$R$2:$R$636,0))) | I76: =IF($K76="","",INDEX(Model!$C$2:$C$636,MATCH($K76,Model!$R$2:$R$636,0))) | J76: =IF($K76="","",INDEX(Model!$D$2:$D$636,MATCH($K76,Model!$R$2:$R$636,0))) | K76: =IF(40<=$E$5,LARGE(Model!$R$2:$R$636,40),"")
A77: =IF($K77="","",INDEX(Raw_data!$D$2:$D$636,MATCH($K77,Model!$R$2:$R$636,0))) | B77: =IF($K77="","",INDEX(Raw_data!$F$2:$F$636,MATCH($K77,Model!$R$2:$R$636,0))) | C77: =IF($K77="","",HYPERLINK(INDEX(Raw_data!$C$2:$C$636,MATCH($K77,Model!$R$2:$R$636,0)),INDEX(Raw_data!$C$2:$C$636,MATCH($K77,Model!$R$2:$R$636,0)))) | D77: =IF($K77="","",INDEX(Raw_data!$AL$2:$AL$636,MATCH($K77,Model!$R$2:$R$636,0))) | E77: =IF($K77="","",INDEX(Raw_data!$AM$2:$AM$636,MATCH($K77,Model!$R$2:$R$636,0))) | F77: =IF($K77="","",INDEX(Raw_data!$AQ$2:$AQ$636,MATCH($K77,Model!$R$2:$R$636,0))) | G77: =IF($K77="","",INDEX(Raw_data!$H$2:$H$636,MATCH($K77,Model!$R$2:$R$636,0))) | H77: =IF($K77="","",INDEX(Model!$B$2:$B$636,MATCH($K77,Model!$R$2:$R$636,0))) | I77: =IF($K77="","",INDEX(Model!$C$2:$C$636,MATCH($K77,Model!$R$2:$R$636,0))) | J77: =IF($K77="","",INDEX(Model!$D$2:$D$636,MATCH($K77,Model!$R$2:$R$636,0))) | K77: =IF(41<=$E$5,LARGE(Model!$R$2:$R$636,41),"")
A78: =IF($K78="","",INDEX(Raw_data!$D$2:$D$636,MATCH($K78,Model!$R$2:$R$636,0))) | B78: =IF($K78="","",INDEX(Raw_data!$F$2:$F$636,MATCH($K78,Model!$R$2:$R$636,0))) | C78: =IF($K78="","",HYPERLINK(INDEX(Raw_data!$C$2:$C$636,MATCH($K78,Model!$R$2:$R$636,0)),INDEX(Raw_data!$C$2:$C$636,MATCH($K78,Model!$R$2:$R$636,0)))) | D78: =IF($K78="","",INDEX(Raw_data!$AL$2:$AL$636,MATCH($K78,Model!$R$2:$R$636,0))) | E78: =IF($K78="","",INDEX(Raw_data!$AM$2:$AM$636,MATCH($K78,Model!$R$2:$R$636,0))) | F78: =IF($K78="","",INDEX(Raw_data!$AQ$2:$AQ$636,MATCH($K78,Model!$R$2:$R$636,0))) | G78: =IF($K78="","",INDEX(Raw_data!$H$2:$H$636,MATCH($K78,Model!$R$2:$R$636,0))) | H78: =IF($K78="","",INDEX(Model!$B$2:$B$636,MATCH($K78,Model!$R$2:$R$636,0))) | I78: =IF($K78="","",INDEX(Model!$C$2:$C$636,MATCH($K78,Model!$R$2:$R$636,0))) | J78: =IF($K78="","",INDEX(Model!$D$2:$D$636,MATCH($K78,Model!$R$2:$R$636,0))) | K78: =IF(42<=$E$5,LARGE(Model!$R$2:$R$636,42),"")
